Workbook

Sheet Country or Territory
D2: Chris | E2: Maggie | F2: Allyson | G2: Eddy
C3: Expanded list: | D3: =COUNTA(D7:D231) -> 146 | E3: =COUNTA(E7:E231) -> 138 | F3: =COUNTA(F7:F231) -> 69 | G3: =COUNTA(G7:G231) -> 60
C4: UN Member States only: | D4: =COUNTIFS($C$7:$C$231, "Sovereign", D7:D231, "<>") -> 129 | E4: =COUNTIFS($C$7:$C$231, "Sovereign", E7:E231, "<>") -> 119 | F4: =COUNTIFS($C$7:$C$231, "Sovereign", F7:F231, "<>") -> 62 | G4: =COUNTIFS($C$7:$C$231, "Sovereign", G7:G231, "<>") -> 54
A6: Code | B6: Name | C6: Status | D6: Chris | E6: Maggie | F6: Allyson | G6: Edward
A7: =VLOOKUP(Table1[[#This Row],[Name]],'country codes'!$A$1:$D$253,4,FALSE) -> AFG | B7: Afghanistan | C7: Sovereign | D7: Y
A8: =VLOOKUP(Table1[[#This Row],[Name]],'country codes'!$A$1:$D$253,4,FALSE) -> ALB | B8: Albania | C8: Sovereign | D8: Y | E8: Y
A9: =VLOOKUP(Table1[[#This Row],[Name]],'country codes'!$A$1:$D$253,4,FALSE) -> DZA | B9: Algeria | C9: Sovereign
A10: =VLOOKUP(Table1[[#This Row],[Name]],'country codes'!$A$1:$D$253,4,FALSE) -> ASM | B10: American Samoa | C10: Non-sovereign | D10: Y | E10: Y
A11: =VLOOKUP(Table1[[#This Row],[Name]],'country codes'!$A$1:$D$253,4,FALSE) -> AND | B11: Andorra | C11: Sovereign
A12: =VLOOKUP(Table1[[#This Row],[Name]],'country codes'!$A$1:$D$253,4,FALSE) -> AGO | B12: Angola | C12: Sovereign
A13: =VLOOKUP(Table1[[#This Row],[Name]],'country codes'!$A$1:$D$253,4,FALSE) -> ATG | B13: Antigua and Barbuda | C13: Sovereign | D13: Y | E13: Y | F13: Y | G13: Y
A14: =VLOOKUP(Table1[[#This Row],[Name]],'country codes'!$A$1:$D$253,4,FALSE) -> ARG | B14: Argentina | C14: Sovereign | D14: Y | E14: Y | F14: Y | G14: Y
A15: =VLOOKUP(Table1[[#This Row],[Name]],'country codes'!$A$1:$D$253,4,FALSE) -> ARM | B15: Armenia | C15: Sovereign | D15: Y | E15: Y
A16: =VLOOKUP(Table1[[#This Row],[Name]],'country codes'!$A$1:$D$253,4,FALSE) -> ABW | B16: Aruba | C16: Non-sovereign | D16: Y | E16: Y | F16: Y | G16: Y
A17: =VLOOKUP(Table1[[#This Row],[Name]],'country codes'!$A$1:$D$253,4,FALSE) -> AUS | B17: Australia | C17: Sovereign | D17: Y | E17: Y | F17: Y | G17: Y
A18: =VLOOKUP(Table1[[#This Row],[Name]],'country codes'!$A$1:$D$253,4,FALSE) -> AUT | B18: Austria | C18: Sovereign | D18: Y | E18: Y | F18: Y | G18: Y
A19: =VLOOKUP(Table1[[#This Row],[Name]],'country codes'!$A$1:$D$253,4,FALSE) -> AZE | B19: Azerbaijan | C19: Sovereign | D19: Y | E19: Y
A20: =VLOOKUP(Table1[[#This Row],[Name]],'country codes'!$A$1:$D$253,4,FALSE) -> PT-20 | B20: Azores | C20: Non-sovereign
A21: =VLOOKUP(Table1[[#This Row],[Name]],'country codes'!$A$1:$D$253,4,FALSE) -> BHR | B21: Bahrain | C21: Sovereign
A22: =VLOOKUP(Table1[[#This Row],[Name]],'country codes'!$A$1:$D$253,4,FALSE) -> BGD | B22: Bangladesh | C22: Sovereign
A23: =VLOOKUP(Table1[[#This Row],[Name]],'country codes'!$A$1:$D$253,4,FALSE) -> BRB | B23: Barbados | C23: Sovereign
A24: =VLOOKUP(Table1[[#This Row],[Name]],'country codes'!$A$1:$D$253,4,FALSE) -> BLR | B24: Belarus | C24: Sovereign
A25: =VLOOKUP(Table1[[#This Row],[Name]],'country codes'!$A$1:$D$253,4,FALSE) -> BEL | B25: Belgium | C25: Sovereign | D25: Y | E25: Y
A26: =VLOOKUP(Table1[[#This Row],[Name]],'country codes'!$A$1:$D$253,4,FALSE) -> BLZ | B26: Belize | C26: Sovereign | D26: Y | E26: Y
A27: =VLOOKUP(Table1[[#This Row],[Name]],'country codes'!$A$1:$D$253,4,FALSE) -> BEN | B27: Benin | C27: Sovereign
A28: =VLOOKUP(Table1[[#This Row],[Name]],'country codes'!$A$1:$D$253,4,FALSE) -> BMU | B28: Bermuda | C28: Non-sovereign
A29: =VLOOKUP(Table1[[#This Row],[Name]],'country codes'!$A$1:$D$253,4,FALSE) -> BTN | B29: Bhutan | C29: Sovereign
A30: =VLOOKUP(Table1[[#This Row],[Name]],'country codes'!$A$1:$D$253,4,FALSE) -> BOL | B30: Bolivia | C30: Sovereign | E30: Y
A31: =VLOOKUP(Table1[[#This Row],[Name]],'country codes'!$A$1:$D$253,4,FALSE) -> BIH | B31: Bosnia and Herzegovina | C31: Sovereign | D31: Y | E31: Y
A32: =VLOOKUP(Table1[[#This Row],[Name]],'country codes'!$A$1:$D$253,4,FALSE) -> BWA | B32: Botswana | C32: Sovereign | D32: Y | E32: Y | F32: Y | G32: Y
A33: =VLOOKUP(Table1[[#This Row],[Name]],'country codes'!$A$1:$D$253,4,FALSE) -> BRA | B33: Brazil | C33: Sovereign | D33: Y | E33: Y | F33: Y | G33: Y
A34: =VLOOKUP(Table1[[#This Row],[Name]],'country codes'!$A$1:$D$253,4,FALSE) -> VGB | B34: British Virgin Islands | C34: Non-sovereign
A35: =VLOOKUP(Table1[[#This Row],[Name]],'country codes'!$A$1:$D$253,4,FALSE) -> BRN | B35: Brunei | C35: Sovereign
A36: =VLOOKUP(Table1[[#This Row],[Name]],'country codes'!$A$1:$D$253,4,FALSE) -> BGR | B36: Bulgaria | C36: Sovereign | D36: Y | E36: Y | F36: Y
A37: =VLOOKUP(Table1[[#This Row],[Name]],'country codes'!$A$1:$D$253,4,FALSE) -> BFA | B37: Burkina Faso | C37: Sovereign | D37: Y
A38: =VLOOKUP(Table1[[#This Row],[Name]],'country codes'!$A$1:$D$253,4,FALSE) -> BDI | B38: Burundi | C38: Sovereign | D38: Y | E38: Y
A39: =VLOOKUP(Table1[[#This Row],[Name]],'country codes'!$A$1:$D$253,4,FALSE) -> CPV | B39: Cabo Verde | C39: Sovereign
A40: =VLOOKUP(Table1[[#This Row],[Name]],'country codes'!$A$1:$D$253,4,FALSE) -> KHM | B40: Cambodia | C40: Sovereign | D40: Y | E40: Y | F40: Y | G40: Y
A41: =VLOOKUP(Table1[[#This Row],[Name]],'country codes'!$A$1:$D$253,4,FALSE) -> CMR | B41: Cameroon | C41: Sovereign | D41: Y
A42: =VLOOKUP(Table1[[#This Row],[Name]],'country codes'!$A$1:$D$253,4,FALSE) -> CAN | B42: Canada | C42: Sovereign | D42: Y | E42: Y | F42: Y | G42: Y
A43: =VLOOKUP(Table1[[#This Row],[Name]],'country codes'!$A$1:$D$253,4,FALSE) -> ES-CN | B43: Canary Islands | C43: Non-sovereign | D43: Y | E43: Y | F43: Y | G43: Y
A44: =VLOOKUP(Table1[[#This Row],[Name]],'country codes'!$A$1:$D$253,4,FALSE) -> CYM | B44: Cayman Islands | C44: Non-sovereign | D44: Y | E44: Y | F44: Y | G44: Y
A45: =VLOOKUP(Table1[[#This Row],[Name]],'country codes'!$A$1:$D$253,4,FALSE) -> CAF | B45: Central African Republic | C45: Sovereign
A46: =VLOOKUP(Table1[[#This Row],[Name]],'country codes'!$A$1:$D$253,4,FALSE) -> ES-CE | B46: Ceuta | C46: Non-sovereign
A47: =VLOOKUP(Table1[[#This Row],[Name]],'country codes'!$A$1:$D$253,4,FALSE) -> TCD | B47: Chad | C47: Sovereign
A48: =VLOOKUP(Table1[[#This Row],[Name]],'country codes'!$A$1:$D$253,4,FALSE) -> CHL | B48: Chile | C48: Sovereign | D48: Y | E48: Y | F48: Y | G48: Y
A49: =VLOOKUP(Table1[[#This Row],[Name]],'country codes'!$A$1:$D$253,4,FALSE) -> CHN | B49: China | C49: Sovereign | D49: Y | E49: Y | F49: Y | G49: Y
A50: =VLOOKUP(Table1[[#This Row],[Name]],'country codes'!$A$1:$D$253,4,FALSE) -> COL | B50: Colombia | C50: Sovereign | D50: Y | E50: Y | F50: Y | G50: Y
A51: =VLOOKUP(Table1[[#This Row],[Name]],'country codes'!$A$1:$D$253,4,FALSE) -> COM | B51: Comoros | C51: Sovereign
A52: =VLOOKUP(Table1[[#This Row],[Name]],'country codes'!$A$1:$D$253,4,FALSE) -> COG | B52: Republic of the Congo | C52: Sovereign | D52: Y
A53: =VLOOKUP(Table1[[#This Row],[Name]],'country codes'!$A$1:$D$253,4,FALSE) -> COD | B53: Democratic Republic of the Congo | C53: Sovereign | D53: Y
A54: =VLOOKUP(Table1[[#This Row],[Name]],'country codes'!$A$1:$D$253,4,FALSE) -> COK | B54: Cook Islands | C54: Sovereign | D54: Y | E54: Y
A55: =VLOOKUP(Table1[[#This Row],[Name]],'country codes'!$A$1:$D$253,4,FALSE) -> CRI | B55: Costa Rica | C55: Sovereign | D55: Y | E55: Y | F55: Y | G55: Y
A56: =VLOOKUP(Table1[[#This Row],[Name]],'country codes'!$A$1:$D$253,4,FALSE) -> CIV | B56: Cóte d'Ivoire | C56: Sovereign | D56: Y
A57: =VLOOKUP(Table1[[#This Row],[Name]],'country codes'!$A$1:$D$253,4,FALSE) -> HRV | B57: Croatia | C57: Sovereign | D57: Y | E57: Y | F57: Y | G57: Y
A58: =VLOOKUP(Table1[[#This Row],[Name]],'country codes'!$A$1:$D$253,4,FALSE) -> CUB | B58: Cuba | C58: Sovereign
A59: =VLOOKUP(Table1[[#This Row],[Name]],'country codes'!$A$1:$D$253,4,FALSE) -> CUW | B59: Curação | C59: Sovereign
A60: =VLOOKUP(Table1[[#This Row],[Name]],'country codes'!$A$1:$D$253,4,FALSE) -> CYP | B60: Cyprus | C60: Sovereign | D60: Y | E60: Y
A61: =VLOOKUP(Table1[[#This Row],[Name]],'country codes'!$A$1:$D$253,4,FALSE) -> CZE | B61: Czechia | C61: Sovereign | D61: Y | E61: Y | F61: Y
A62: =VLOOKUP(Table1[[#This Row],[Name]],'country codes'!$A$1:$D$253,4,FALSE) -> DNK | B62: Denmark | C62: Sovereign | D62: Y | E62: Y
A63: =VLOOKUP(Table1[[#This Row],[Name]],'country codes'!$A$1:$D$253,4,FALSE) -> DJI | B63: Djibouti | C63: Sovereign
A64: =VLOOKUP(Table1[[#This Row],[Name]],'country codes'!$A$1:$D$253,4,FALSE) -> DMA | B64: Dominica | C64: Sovereign | D64: Y | E64: Y | F64: Y | G64: Y
A65: =VLOOKUP(Table1[[#This Row],[Name]],'country codes'!$A$1:$D$253,4,FALSE) -> DOM | B65: Dominican Republic | C65: Sovereign | D65: Y | E65: Y | F65: Y | G65: Y
A66: =VLOOKUP(Table1[[#This Row],[Name]],'country codes'!$A$1:$D$253,4,FALSE) -> ECU | B66: Ecuador | C66: Sovereign | E66: Y
A67: =VLOOKUP(Table1[[#This Row],[Name]],'country codes'!$A$1:$D$253,4,FALSE) -> EGY | B67: Egypt | C67: Sovereign | D67: Y | E67: Y | F67: Y | G67: Y
A68: =VLOOKUP(Table1[[#This Row],[Name]],'country codes'!$A$1:$D$253,4,FALSE) -> SLV | B68: El Salvador | C68: Sovereign | E68: Y
A69: =VLOOKUP(Table1[[#This Row],[Name]],'country codes'!$A$1:$D$253,4,FALSE) -> GNQ | B69: Equatorial Guinea | C69: Sovereign | D69: Y
A70: =VLOOKUP(Table1[[#This Row],[Name]],'country codes'!$A$1:$D$253,4,FALSE) -> ERI | B70: Eritrea | C70: Sovereign
A71: =VLOOKUP(Table1[[#This Row],[Name]],'country codes'!$A$1:$D$253,4,FALSE) -> EST | B71: Estonia | C71: Sovereign
A72: =VLOOKUP(Table1[[#This Row],[Name]],'country codes'!$A$1:$D$253,4,FALSE) -> SWZ | B72: Eswatini | C72: Sovereign | D72: Y | E72: Y | F72: Y | G72: Y
A73: =VLOOKUP(Table1[[#This Row],[Name]],'country codes'!$A$1:$D$253,4,FALSE) -> ETH | B73: Ethiopia | C73: Sovereign
A74: =VLOOKUP(Table1[[#This Row],[Name]],'country codes'!$A$1:$D$253,4,FALSE) -> FRO | B74: Faroe Islands | C74: Non-sovereign | D74: Y | E74: Y
A75: =VLOOKUP(Table1[[#This Row],[Name]],'country codes'!$A$1:$D$253,4,FALSE) -> FSM | B75: Federated States of Micronesia | C75: Sovereign
A76: =VLOOKUP(Table1[[#This Row],[Name]],'country codes'!$A$1:$D$253,4,FALSE) -> FJI | B76: Fiji | C76: Sovereign | D76: Y | E76: Y | F76: Y | G76: Y
A77: =VLOOKUP(Table1[[#This Row],[Name]],'country codes'!$A$1:$D$253,4,FALSE) -> FIN | B77: Finland | C77: Sovereign
A78: =VLOOKUP(Table1[[#This Row],[Name]],'country codes'!$A$1:$D$253,4,FALSE) -> FRA | B78: France | C78: Sovereign | D78: Y | E78: Y | F78: Y | G78: Y
A79: =VLOOKUP(Table1[[#This Row],[Name]],'country codes'!$A$1:$D$253,4,FALSE) -> FR-GF | B79: French Guiana | C79: Non-sovereign
A80: =VLOOKUP(Table1[[#This Row],[Name]],'country codes'!$A$1:$D$253,4,FALSE) -> PYF | B80: French Polynesia | C80: Non-sovereign | D80: Y | E80: Y
A81: =VLOOKUP(Table1[[#This Row],[Name]],'country codes'!$A$1:$D$253,4,FALSE) -> GAB | B81: Gabon | C81: Sovereign | D81: Y
A82: =VLOOKUP(Table1[[#This Row],[Name]],'country codes'!$A$1:$D$253,4,FALSE) -> GEO | B82: Georgia | C82: Sovereign | D82: Y | E82: Y
A83: =VLOOKUP(Table1[[#This Row],[Name]],'country codes'!$A$1:$D$253,4,FALSE) -> DEU | B83: Germany | C83: Sovereign | D83: Y | E83: Y | F83: Y | G83: Y
A84: =VLOOKUP(Table1[[#This Row],[Name]],'country codes'!$A$1:$D$253,4,FALSE) -> GHA | B84: Ghana | C84: Sovereign
A85: =VLOOKUP(Table1[[#This Row],[Name]],'country codes'!$A$1:$D$253,4,FALSE) -> GIB | B85: Gibraltar | C85: Non-sovereign | D85: Y | E85: Y
A86: =VLOOKUP(Table1[[#This Row],[Name]],'country codes'!$A$1:$D$253,4,FALSE) -> GRC | B86: Greece | C86: Sovereign | D86: Y | E86: Y | F86: Y | G86: Y
A87: =VLOOKUP(Table1[[#This Row],[Name]],'country codes'!$A$1:$D$253,4,FALSE) -> GRL | B87: Greenland | C87: Non-sovereign
A88: =VLOOKUP(Table1[[#This Row],[Name]],'country codes'!$A$1:$D$253,4,FALSE) -> GRD | B88: Grenada | C88: Sovereign
A89: =VLOOKUP(Table1[[#This Row],[Name]],'country codes'!$A$1:$D$253,4,FALSE) -> FR-GP | B89: Guadeloupe | C89: Non-sovereign | E89: Y
A90: =VLOOKUP(Table1[[#This Row],[Name]],'country codes'!$A$1:$D$253,4,FALSE) -> GTM | B90: Guatemala | C90: Sovereign | D90: Y | E90: Y
A91: =VLOOKUP(Table1[[#This Row],[Name]],'country codes'!$A$1:$D$253,4,FALSE) -> GIN | B91: Guinea | C91: Sovereign
A92: =VLOOKUP(Table1[[#This Row],[Name]],'country codes'!$A$1:$D$253,4,FALSE) -> GNB | B92: Guinea-Bissau | C92: Sovereign | E92: Y
A93: =VLOOKUP(Table1[[#This Row],[Name]],'country codes'!$A$1:$D$253,4,FALSE) -> GUY | B93: Guyana | C93: Sovereign
A94: =VLOOKUP(Table1[[#This Row],[Name]],'country codes'!$A$1:$D$253,4,FALSE) -> HTI | B94: Haiti | C94: Sovereign | E94: Y
A95: =VLOOKUP(Table1[[#This Row],[Name]],'country codes'!$A$1:$D$253,4,FALSE) -> VAT | B95: Vatican | C95: Non-sovereign | D95: Y | E95: Y | F95: Y
A96: =VLOOKUP(Table1[[#This Row],[Name]],'country codes'!$A$1:$D$253,4,FALSE) -> HND | B96: Honduras | C96: Sovereign | E96: Y | F96: Y | G96: Y
A97: =VLOOKUP(Table1[[#This Row],[Name]],'country codes'!$A$1:$D$253,4,FALSE) -> HKG | B97: Hong Kong | C97: Non-sovereign | D97: Y | E97: Y
A98: =VLOOKUP(Table1[[#This Row],[Name]],'country codes'!$A$1:$D$253,4,FALSE) -> HUN | B98: Hungary | C98: Sovereign | D98: Y | E98: Y | F98: Y
A99: =VLOOKUP(Table1[[#This Row],[Name]],'country codes'!$A$1:$D$253,4,FALSE) -> ISL | B99: Iceland | C99: Sovereign | D99: Y | E99: Y
A100: =VLOOKUP(Table1[[#This Row],[Name]],'country codes'!$A$1:$D$253,4,FALSE) -> IND | B100: India | C100: Sovereign | D100: Y | E100: Y
A101: =VLOOKUP(Table1[[#This Row],[Name]],'country codes'!$A$1:$D$253,4,FALSE) -> IDN | B101: Indonesia | C101: Sovereign | D101: Y | E101: Y
A102: =VLOOKUP(Table1[[#This Row],[Name]],'country codes'!$A$1:$D$253,4,FALSE) -> IRN | B102: Iran | C102: Sovereign
...

Sheet with years
D2: Chris | E2: Maggie | F2: Allyson | G2: Eddy
C3: Expanded list: | D3: =COUNTA(D7:D219) -> 140 | E3: =COUNTA(E7:E219) -> 134 | F3: =COUNTA(F7:F219) -> 69 | G3: =COUNTA(G7:G219) -> 60
C4: UN Member States only: | D4: =COUNTIFS($C$7:$C$219, "sovereign state", D7:D219, "<>") -> 125 | E4: =COUNTIFS($C$7:$C$219, "sovereign state", E7:E219, "<>") -> 116 | F4: =COUNTIFS($C$7:$C$219, "sovereign state", F7:F219, "<>") -> 62 | G4: =COUNTIFS($C$7:$C$219, "sovereign state", G7:G219, "<>") -> 54
A6: Code | B6: Country or Territory | C6: Political Status | D6: Chris | E6: Maggie | F6: Allyson | G6: Edward
A7: =VLOOKUP(B7,'country codes'!A2:B252,2,FALSE) -> AF | B7: Afghanistan | C7: Sovereign State | D7: 2018 | I7: Includes sovereign states and dependent territories
A8: =VLOOKUP(B8,'country codes'!A3:B253,2,FALSE) -> AL | B8: Albania | C8: Sovereign State | D8: 2017 | E8: 2017 | I8: Includes all countries entered, i.e., left the airport or seaport and went into town
A9: =VLOOKUP(B9,'country codes'!A4:B253,2,FALSE) -> DZ | B9: Algeria | C9: Sovereign State | I9: Excludes airport-only or port-only transit
A10: =VLOOKUP(B10,'country codes'!A5:B253,2,FALSE) -> AD | B10: Andorra | C10: Sovereign State
A11: =VLOOKUP(B11,'country codes'!A6:B253,2,FALSE) -> AO | B11: Angola | C11: Sovereign State | I11: **Note: there are a lot more dependent territories, only included those we've visited. Full list is on next sheet.
A12: =VLOOKUP(B12,'country codes'!A7:B254,2,FALSE) -> AG | B12: Antigua and Barbuda | C12: Sovereign State | D12: 2014 | E12: 2014 | F12: 2014 | G12: 2014
A13: =VLOOKUP(B13,'country codes'!A8:B255,2,FALSE) -> AR | B13: Argentina | C13: Sovereign State | D13: 2013 | E13: 2013 | F13: 2013 | G13: 2013 | I13: https://mtp.travel/users/me/checklists/locations/geographic/visited_remaining
A14: =VLOOKUP(B14,'country codes'!A9:B256,2,FALSE) -> AM | B14: Armenia | C14: Sovereign State | D14: 2021 | E14: 2021
A15: AW | B15: Aruba | C15: Constituent country of the Kingdom of the Netherlands | D15: 2014 | E15: 2014 | F15: 2014 | G15: 2014
A16: =VLOOKUP(B16,'country codes'!A10:B257,2,FALSE) -> AU | B16: Australia | C16: Sovereign State | D16: 2002 | E16: 2002 | F16: 2002 | G16: 2002
A17: =VLOOKUP(B17,'country codes'!A11:B258,2,FALSE) -> AT | B17: Austria | C17: Sovereign State | D17: 2016 | E17: 2016 | F17: 2016 | G17: 2016
A18: =VLOOKUP(B18,'country codes'!A12:B259,2,FALSE) -> AZ | B18: Azerbaijan | C18: Sovereign State | D18: 2021 | E18: 2021
A19: =VLOOKUP(B19,'country codes'!A14:B261,2,FALSE) -> BH | B19: Bahrain | C19: Sovereign State
A20: =VLOOKUP(B20,'country codes'!A15:B262,2,FALSE) -> BD | B20: Bangladesh | C20: Sovereign State
A21: =VLOOKUP(B21,'country codes'!A16:B263,2,FALSE) -> BB | B21: Barbados | C21: Sovereign State
A22: =VLOOKUP(B22,'country codes'!A18:B264,2,FALSE) -> BY | B22: Belarus | C22: Sovereign State
A23: =VLOOKUP(B23,'country codes'!A19:B265,2,FALSE) -> BE | B23: Belgium | C23: Sovereign State | D23: 1995 | E23: Y
A24: =VLOOKUP(B24,'country codes'!A21:B266,2,FALSE) -> BZ | B24: Belize | C24: Sovereign State | D24: 1997 | E24: Y
A25: =VLOOKUP(B25,'country codes'!A22:B267,2,FALSE) -> BJ | B25: Benin | C25: Sovereign State
A26: BM | B26: Bermuda | C26: Overseas territory of the United Kingdom
A27: =VLOOKUP(B27,'country codes'!A23:B268,2,FALSE) -> BT | B27: Bhutan | C27: Sovereign State
A28: =VLOOKUP(B28,'country codes'!A24:B269,2,FALSE) -> BO | B28: Bolivia | C28: Sovereign State | E28: Y
A29: =VLOOKUP(B29,'country codes'!A25:B270,2,FALSE) -> BA | B29: Bosnia and Herzegovina | C29: Sovereign State | D29: 2017 | E29: 2017
A30: =VLOOKUP(B30,'country codes'!A26:B271,2,FALSE) -> BW | B30: Botswana | C30: Sovereign State | D30: 2003 | E30: 2003 | F30: 2003 | G30: 2003
A31: =VLOOKUP(B31,'country codes'!A27:B272,2,FALSE) -> BR | B31: Brazil | C31: Sovereign State | D31: 2013 | E31: 2013 | F31: 2013 | G31: 2013
A32: =VLOOKUP(B32,'country codes'!A28:B273,2,FALSE) -> BN | B32: Brunei | C32: Sovereign State
A33: =VLOOKUP(B33,'country codes'!A29:B274,2,FALSE) -> BG | B33: Bulgaria | C33: Sovereign State | D33: 2019 | E33: 2019 | F33: 2019
A34: =VLOOKUP(B34,'country codes'!A30:B275,2,FALSE) -> BF | B34: Burkina Faso | C34: Sovereign State | D34: 1988
A35: =VLOOKUP(B35,'country codes'!A32:B277,2,FALSE) -> BI | B35: Burundi | C35: Sovereign State | D35: 1989 | E35: 1989
A36: =VLOOKUP(B36,'country codes'!A33:B278,2,FALSE) -> CV | B36: Cabo Verde | C36: Sovereign State
A37: =VLOOKUP(B37,'country codes'!A33:B279,2,FALSE) -> KH | B37: Cambodia | C37: Sovereign State | D37: 2010 | E37: 2010 | F37: 2010 | G37: 2010
A38: =VLOOKUP(B38,'country codes'!A34:B280,2,FALSE) -> CM | B38: Cameroon | C38: Sovereign State | D38: 1990
A39: =VLOOKUP(B39,'country codes'!A34:B281,2,FALSE) -> CA | B39: Canada | C39: Sovereign State | D39: 1980 | E39: 2024 | F39: 2024 | G39: 2024
A40: =VLOOKUP(B40,'country codes'!A35:B282,2,FALSE) -> IC | B40: Canary Islands | C40: Autonomous Community of Spain | D40: 2019 | E40: 2019 | F40: 2019 | G40: 2019
A41: KY | B41: Cayman Islands | C41: Crown dependency of the United Kingdom | D41: 2019 | E41: 2019 | F41: 2019 | G41: 2019
A42: =VLOOKUP(B42,'country codes'!A35:B282,2,FALSE) -> CF | B42: Central African Republic | C42: Sovereign State
A43: =VLOOKUP(B43,'country codes'!A36:B283,2,FALSE) -> TD | B43: Chad | C43: Sovereign State
A44: =VLOOKUP(B44,'country codes'!A37:B284,2,FALSE) -> CL | B44: Chile | C44: Sovereign State | D44: 2013 | E44: 2013 | F44: 2013 | G44: 2013
A45: =VLOOKUP(B45,'country codes'!A38:B285,2,FALSE) -> CN | B45: China | C45: Sovereign State | D45: 2008 | E45: 2008 | F45: 2008 | G45: 2008
A46: =VLOOKUP(B46,'country codes'!A39:B286,2,FALSE) -> CO | B46: Colombia | C46: Sovereign State | D46: 2014 | E46: 2014 | F46: 2014 | G46: 2014
A47: =VLOOKUP(B47,'country codes'!A40:B287,2,FALSE) -> KM | B47: Comoros | C47: Sovereign State
A48: =VLOOKUP(B48,'country codes'!A41:B288,2,FALSE) -> #N/A | B48: Congo (Brazzaville) | C48: Sovereign State | D48: 1990
A49: =VLOOKUP(B49,'country codes'!A43:B289,2,FALSE) -> #N/A | B49: Congo (Kinshasa) | C49: Sovereign State | D49: 1989
A50: =VLOOKUP(B50,'country codes'!A44:B290,2,FALSE) -> CR | B50: Costa Rica | C50: Sovereign State | D50: 2014 | E50: 2014 | F50: 2014 | G50: 2014
A51: =VLOOKUP(B51,'country codes'!A46:B291,2,FALSE) -> #N/A | B51: Côte d'Ivoire | C51: Sovereign State | D51: 1988
A52: =VLOOKUP(B52,'country codes'!A47:B292,2,FALSE) -> HR | B52: Croatia | C52: Sovereign State | D52: 2016 | E52: 2016 | F52: 2016 | G52: 2016
A53: =VLOOKUP(B53,'country codes'!A48:B293,2,FALSE) -> CU | B53: Cuba | C53: Sovereign State
A54: =VLOOKUP(B54,'country codes'!A49:B294,2,FALSE) -> CY | B54: Cyprus | C54: Sovereign State | D54: 2021 | E54: 2021
A55: =VLOOKUP(B55,'country codes'!A50:B295,2,FALSE) -> #N/A | B55: Czech Republic | C55: Sovereign State | D55: 2016 | E55: 2016 | F55: 2016
A56: =VLOOKUP(B56,'country codes'!A50:B296,2,FALSE) -> DK | B56: Denmark | C56: Sovereign State | D56: 2023 | E56: 2023
A57: =VLOOKUP(B57,'country codes'!A51:B297,2,FALSE) -> DJ | B57: Djibouti | C57: Sovereign State
A58: =VLOOKUP(B58,'country codes'!A52:B298,2,FALSE) -> DM | B58: Dominica | C58: Sovereign State | D58: 2004 | E58: 2004 | F58: 2004 | G58: 2004
A59: =VLOOKUP(B59,'country codes'!A53:B299,2,FALSE) -> DO | B59: Dominican Republic | C59: Sovereign State | D59: 1994 | E59: 2004 | F59: 2004 | G59: 2004
A60: =VLOOKUP(B60,'country codes'!A54:B300,2,FALSE) -> EC | B60: Ecuador | C60: Sovereign State | E60: Y
A61: =VLOOKUP(B61,'country codes'!A55:B301,2,FALSE) -> EG | B61: Egypt | C61: Sovereign State | D61: 2006 | E61: 2006 | F61: 2006 | G61: 2006
A62: =VLOOKUP(B62,'country codes'!A56:B302,2,FALSE) -> SV | B62: El Salvador | C62: Sovereign State | E62: Y
A63: =VLOOKUP(B63,'country codes'!A57:B303,2,FALSE) -> GQ | B63: Equatorial Guinea | C63: Sovereign State | D63: 1990
A64: =VLOOKUP(B64,'country codes'!A58:B304,2,FALSE) -> ER | B64: Eritrea | C64: Sovereign State
A65: =VLOOKUP(B65,'country codes'!A59:B305,2,FALSE) -> EE | B65: Estonia | C65: Sovereign State
A66: =VLOOKUP(B66,'country codes'!A172:B416,2,FALSE) -> #N/A | B66: Eswatini (Swaziland) | C66: Sovereign State | D66: 1997 | E66: 1997 | F66: 1997 | G66: 1997
A67: =VLOOKUP(B67,'country codes'!A60:B306,2,FALSE) -> ET | B67: Ethiopia | C67: Sovereign State
A68: FO | B68: Faroe Islands | C68: Self-governing territory of the Danish Realm | D68: 2024 | E68: 2024
A69: =VLOOKUP(B69,'country codes'!A118:B364,2,FALSE) -> #N/A | B69: Federated States of Micronesia | C69: Sovereign State
A70: =VLOOKUP(B70,'country codes'!A61:B307,2,FALSE) -> FJ | B70: Fiji | C70: Sovereign State | D70: 2009 | E70: 2009 | F70: 2009 | G70: 2009
A71: =VLOOKUP(B71,'country codes'!A62:B308,2,FALSE) -> FI | B71: Finland | C71: Sovereign State
A72: =VLOOKUP(B72,'country codes'!A63:B309,2,FALSE) -> FR | B72: France | C72: Sovereign State | D72: 1995 | E72: 2008 | F72: 2008 | G72: 2008
A73: PF | B73: French Polynesia | C73: Overseas collectivity of France | E73: Y
A74: =VLOOKUP(B74,'country codes'!A64:B310,2,FALSE) -> GA | B74: Gabon | C74: Sovereign State | D74: 1989
A75: =VLOOKUP(B75,'country codes'!A66:B312,2,FALSE) -> GE | B75: Georgia | C75: Sovereign State | D75: 2021 | E75: 2021
A76: =VLOOKUP(B76,'country codes'!A67:B313,2,FALSE) -> DE | B76: Germany | C76: Sovereign State | D76: 2015 | E76: 2015 | F76: 2015 | G76: 2015
A77: =VLOOKUP(B77,'country codes'!A68:B314,2,FALSE) -> GH | B77: Ghana | C77: Sovereign State
A78: GI | B78: Gibraltar | C78: Overseas territory of the United Kingdom | D78: 2016 | E78: 2016
A79: =VLOOKUP(B79,'country codes'!A69:B315,2,FALSE) -> GR | B79: Greece | C79: Sovereign State | D79: 2016 | E79: 2016 | F79: 2016 | G79: 2016
A80: =VLOOKUP(B80,'country codes'!A70:B316,2,FALSE) -> GL | B80: Greenland | C80: Self-governing territory of the Danish Realm
A81: =VLOOKUP(B81,'country codes'!A70:B316,2,FALSE) -> GD | B81: Grenada | C81: Sovereign State
A82: GP | B82: Guadeloupe | C82: Overseas department of France | E82: Y
A83: =VLOOKUP(B83,'country codes'!A71:B317,2,FALSE) -> GT | B83: Guatemala | C83: Sovereign State | D83: 1997 | E83: Y
A84: =VLOOKUP(B84,'country codes'!A72:B318,2,FALSE) -> GN | B84: Guinea | C84: Sovereign State
A85: =VLOOKUP(B85,'country codes'!A73:B319,2,FALSE) -> GW | B85: Guinea-Bissau | C85: Sovereign State | E85: Y
A86: =VLOOKUP(B86,'country codes'!A74:B320,2,FALSE) -> GY | B86: Guyana | C86: Sovereign State
A87: =VLOOKUP(B87,'country codes'!A75:B321,2,FALSE) -> HT | B87: Haiti | C87: Sovereign State | E87: Y
A88: =VLOOKUP(B88,'country codes'!A76:B322,2,FALSE) -> #N/A | B88: Holy See | C88: NOT Sovereign State | D88: 2016 | E88: 2016 | F88: 2016
A89: =VLOOKUP(B89,'country codes'!A77:B323,2,FALSE) -> HN | B89: Honduras | C89: Sovereign State | E89: Y | F89: Y | G89: Y
A90: HK | B90: Hong Kong | C90: Special Administrative Region of China | D90: 2018 | E90: 2018
A91: =VLOOKUP(B91,'country codes'!A78:B324,2,FALSE) -> HU | B91: Hungary | C91: Sovereign State | D91: 2016 | E91: 2016 | F91: 2016
A92: =VLOOKUP(B92,'country codes'!A79:B325,2,FALSE) -> IS | B92: Iceland | C92: Sovereign State | D92: 2024 | E92: 2024
A93: =VLOOKUP(B93,'country codes'!A80:B326,2,FALSE) -> IN | B93: India | C93: Sovereign State | D93: 1991 | E93: Y
A94: =VLOOKUP(B94,'country codes'!A81:B327,2,FALSE) -> ID | B94: Indonesia | C94: Sovereign State | D94: 2023 | E94: 2023
A95: =VLOOKUP(B95,'country codes'!A82:B328,2,FALSE) -> IR | B95: Iran | C95: Sovereign State
A96: =VLOOKUP(B96,'country codes'!A83:B329,2,FALSE) -> IQ | B96: Iraq | C96: Sovereign State
A97: =VLOOKUP(B97,'country codes'!A84:B330,2,FALSE) -> IE | B97: Ireland | C97: Sovereign State | D97: 2023 | E97: 2023 | F97: 2023
A98: IM | B98: Isle of Man | C98: Crown dependency of the United Kingdom | D98: 2024 | E98: 2024
A99: =VLOOKUP(B99,'country codes'!A85:B331,2,FALSE) -> IL | B99: Israel | C99: Sovereign State | D99: 2007 | E99: 2007 | F99: 2007 | G99: 2007
A100: =VLOOKUP(B100,'country codes'!A86:B332,2,FALSE) -> IT | B100: Italy | C100: Sovereign State | D100: 2016 | E100: 2016 | F100: 2016 | G100: 2016
A101: =VLOOKUP(B101,'country codes'!A87:B333,2,FALSE) -> JM | B101: Jamaica | C101: Sovereign State | D101: 2004 | E101: 2004 | F101: 2004 | G101: 2004
A102: =VLOOKUP(B102,'country codes'!A88:B334,2,FALSE) -> JP | B102: Japan | C102: Sovereign State | D102: 2018 | E102: 2018
...

Sheet U.S. States
B2: TOTALS: | C2: =COUNTA(C5:C212) -> 37 | D2: =COUNTA(D5:D212) -> 38
B3: US State | C3: Chris | D3: Maggie | F3: State Capital | K3: The Alaska cruise would give us AK and WA (and the Canadian Rockies!)
B4: Alabama | C4: Y | D4: Y | F4: Montgomery | K4: The Mississippi cruises hit Minnesota, Wisconsin, Iowa, Missouri, Tennessee, Mississippi, and Louisiana (they also pass Illinois and Arkansas, but those are not listed as stops).
B5: Alaska | C5: Y | D5: Y | F5: Juneau
B6: Arizona | C6: Y | D6: Y | F6: Phoenix | K6: So, we’ll have to do a road trip to the Heartland of America!
B7: Arkansas | C7: Y | F7: Little Rock | K7: West of Mississippi River for ND, NE, KS, OK, and AR.
B8: California | C8: Y | D8: Y | F8: Sacramento | K8: East of the Mississippi River for IL, IN, and KY.
B9: Colorado | C9: Y | D9: Y | F9: Denver | K9: New England to hit VT, ME, and NH.
B10: Connecticut | C10: Y | D10: Y | F10: Hartford | K10: And that would leave NM and OR. Could try to do OR in conjunction w/ Alaska Cruise.
B11: Delaware | C11: Y | D11: Y | F11: Dover | K11: Visiting the State capitals will probably be more interesting than visiting the large cities.
B12: Florida | C12: Y | D12: Y | F12: Tallahassee
B13: Georgia | C13: Y | D13: Y | F13: Atlanta
B14: Hawaii | C14: Y | D14: Y | F14: Honolulu
B15: Idaho | C15: Y | D15: Y | F15: Boise
B16: Illinois | D16: Y | F16: Springfield
B17: Indiana | C17: Y | F17: Indianapolis
B18: Iowa | C18: Y | F18: Des Moines
B19: Kansas | F19: Topeka
B20: Kentucky | F20: Frankfort
B21: Louisiana | C21: Y | F21: Baton Rouge
B22: Maine | C22: Y | F22: Augusta
B23: Maryland | C23: Y | D23: Y | F23: Annapolis
B24: Massachusetts | C24: Y | D24: Y | F24: Boston
B25: Michigan | C25: Y | D25: Y | F25: Lansing
B26: Minnesota | C26: Y | D26: Y | F26: St. Paul
B27: Mississippi | C27: Y | D27: Y | F27: Jackson
B28: Missouri | D28: Y | F28: Jefferson City
B29: Montana | C29: Y | D29: Y | F29: Helena
B30: Nebraska | F30: Lincoln
B31: Nevada | C31: Y | D31: Y | F31: Carson City
B32: New Hampshire | D32: Y | F32: Concord
B33: New Jersey | C33: Y | D33: Y | F33: Trenton
B34: New Mexico | D34: Y | F34: Santa Fe
B35: New York | C35: Y | D35: Y | F35: Albany
B36: North Carolina | C36: Y | D36: Y | F36: Raleigh
B37: North Dakota | F37: Bismarck
B38: Ohio | C38: Y | D38: Y | F38: Columbus
B39: Oklahoma | F39: Oklahoma City
B40: Oregon | D40: Y | F40: Salem
B41: Pennsylvania | C41: Y | D41: Y | F41: Harrisburg
B42: Rhode Island | C42: Y | D42: Y | F42: Providence
B43: South Carolina | C43: Y | D43: Y | F43: Columbia
B44: South Dakota | C44: Y | D44: Y | F44: Pierre
B45: Tennessee | C45: Y | D45: Y | F45: Nashville
B46: Texas | C46: Y | D46: Y | F46: Austin
B47: Utah | C47: Y | D47: Y | F47: Salt Lake City
B48: Vermont | D48: Y | F48: Montpelier
B49: Virginia | C49: Y | D49: Y | F49: Richmond
B50: Washington | C50: Y | D50: Y | F50: Olympia
B51: West Virginia | C51: Y | D51: Y | F51: Charleston
B52: Wisconsin | F52: Madison
B53: Wyoming | C53: Y | D53: Y | F53: Cheyenne

Sheet fusion
A1: name | B1: code | C1: Chris | D1: Maggie | E1: Ally | F1: Eddy | G1: latitude | H1: longitude | I1: icon
A2: =VLOOKUP(B2,'Country or Territory'!A:G,2,FALSE) -> #N/A | B2: AF | C2: =IF(VLOOKUP(B2,'Country or Territory'!A:G,4,FALSE)="Y",$C$1 & " has visited","") -> #N/A | D2: =IF(VLOOKUP(B2,'Country or Territory'!A:G,5,FALSE)="Y",$D$1 & " has visited","") -> #N/A | E2: =IF(VLOOKUP(B2,'Country or Territory'!A:G,6,FALSE)="Y",$E$1 & " has visited","") -> #N/A | F2: =IF(VLOOKUP(B2,'Country or Territory'!A:G,7,FALSE)="Y",$F$1 & " has visited","") -> #N/A | G2: =VLOOKUP(B2,latlong!A:F,4,TRUE) -> 34.52813 | H2: =VLOOKUP(B2,latlong!A:F,5,TRUE) -> 69.17233 | I2: =4-COUNTBLANK(C2:F2) -> 4
A3: =VLOOKUP(B3,'Country or Territory'!A:G,2,FALSE) -> #N/A | B3: AL | C3: =IF(VLOOKUP(B3,'Country or Territory'!A:G,4,FALSE)="Y",$C$1 & " has visited","") -> #N/A | D3: =IF(VLOOKUP(B3,'Country or Territory'!A:G,5,FALSE)="Y",$D$1 & " has visited","") -> #N/A | E3: =IF(VLOOKUP(B3,'Country or Territory'!A:G,6,FALSE)="Y",$E$1 & " has visited","") -> #N/A | F3: =IF(VLOOKUP(B3,'Country or Territory'!A:G,7,FALSE)="Y",$F$1 & " has visited","") -> #N/A | G3: =VLOOKUP(B3,latlong!A:F,4,TRUE) -> 41.3275 | H3: =VLOOKUP(B3,latlong!A:F,5,TRUE) -> 19.81889 | I3: =4-COUNTBLANK(C3:F3) -> 4
A4: =VLOOKUP(B4,'Country or Territory'!A:G,2,FALSE) -> #N/A | B4: DZ | C4: =IF(VLOOKUP(B4,'Country or Territory'!A:G,4,FALSE)="Y",$C$1 & " has visited","") -> #N/A | D4: =IF(VLOOKUP(B4,'Country or Territory'!A:G,5,FALSE)="Y",$D$1 & " has visited","") -> #N/A | E4: =IF(VLOOKUP(B4,'Country or Territory'!A:G,6,FALSE)="Y",$E$1 & " has visited","") -> #N/A | F4: =IF(VLOOKUP(B4,'Country or Territory'!A:G,7,FALSE)="Y",$F$1 & " has visited","") -> #N/A | G4: =VLOOKUP(B4,latlong!A:F,4,TRUE) -> 36.7525 | H4: =VLOOKUP(B4,latlong!A:F,5,TRUE) -> 3.04197 | I4: =4-COUNTBLANK(C4:F4) -> 4
A5: =VLOOKUP(B5,'Country or Territory'!A:G,2,FALSE) -> #N/A | B5: AD | C5: =IF(VLOOKUP(B5,'Country or Territory'!A:G,4,FALSE)="Y",$C$1 & " has visited","") -> #N/A | D5: =IF(VLOOKUP(B5,'Country or Territory'!A:G,5,FALSE)="Y",$D$1 & " has visited","") -> #N/A | E5: =IF(VLOOKUP(B5,'Country or Territory'!A:G,6,FALSE)="Y",$E$1 & " has visited","") -> #N/A | F5: =IF(VLOOKUP(B5,'Country or Territory'!A:G,7,FALSE)="Y",$F$1 & " has visited","") -> #N/A | G5: =VLOOKUP(B5,latlong!A:F,4,TRUE) -> 42.50779 | H5: =VLOOKUP(B5,latlong!A:F,5,TRUE) -> 1.52109 | I5: =4-COUNTBLANK(C5:F5) -> 4
A6: =VLOOKUP(B6,'Country or Territory'!A:G,2,FALSE) -> #N/A | B6: AO | C6: =IF(VLOOKUP(B6,'Country or Territory'!A:G,4,FALSE)="Y",$C$1 & " has visited","") -> #N/A | D6: =IF(VLOOKUP(B6,'Country or Territory'!A:G,5,FALSE)="Y",$D$1 & " has visited","") -> #N/A | E6: =IF(VLOOKUP(B6,'Country or Territory'!A:G,6,FALSE)="Y",$E$1 & " has visited","") -> #N/A | F6: =IF(VLOOKUP(B6,'Country or Territory'!A:G,7,FALSE)="Y",$F$1 & " has visited","") -> #N/A | G6: =VLOOKUP(B6,latlong!A:F,4,TRUE) -> -8.83682 | H6: =VLOOKUP(B6,latlong!A:F,5,TRUE) -> 13.23432 | I6: =4-COUNTBLANK(C6:F6) -> 4
A7: =VLOOKUP(B7,'Country or Territory'!A:G,2,FALSE) -> #N/A | B7: AG | C7: =IF(VLOOKUP(B7,'Country or Territory'!A:G,4,FALSE)="Y",$C$1 & " has visited","") -> #N/A | D7: =IF(VLOOKUP(B7,'Country or Territory'!A:G,5,FALSE)="Y",$D$1 & " has visited","") -> #N/A | E7: =IF(VLOOKUP(B7,'Country or Territory'!A:G,6,FALSE)="Y",$E$1 & " has visited","") -> #N/A | F7: =IF(VLOOKUP(B7,'Country or Territory'!A:G,7,FALSE)="Y",$F$1 & " has visited","") -> #N/A | G7: =VLOOKUP(B7,latlong!A:F,4,TRUE) -> 17.11717 | H7: =VLOOKUP(B7,latlong!A:F,5,TRUE) -> -61.84573 | I7: =4-COUNTBLANK(C7:F7) -> 4
A8: =VLOOKUP(B8,'Country or Territory'!A:G,2,FALSE) -> #N/A | B8: AR | C8: =IF(VLOOKUP(B8,'Country or Territory'!A:G,4,FALSE)="Y",$C$1 & " has visited","") -> #N/A | D8: =IF(VLOOKUP(B8,'Country or Territory'!A:G,5,FALSE)="Y",$D$1 & " has visited","") -> #N/A | E8: =IF(VLOOKUP(B8,'Country or Territory'!A:G,6,FALSE)="Y",$E$1 & " has visited","") -> #N/A | F8: =IF(VLOOKUP(B8,'Country or Territory'!A:G,7,FALSE)="Y",$F$1 & " has visited","") -> #N/A | G8: =VLOOKUP(B8,latlong!A:F,4,TRUE) -> -34.61315 | H8: =VLOOKUP(B8,latlong!A:F,5,TRUE) -> -58.37723 | I8: =4-COUNTBLANK(C8:F8) -> 4
A9: =VLOOKUP(B9,'Country or Territory'!A:G,2,FALSE) -> #N/A | B9: AM | C9: =IF(VLOOKUP(B9,'Country or Territory'!A:G,4,FALSE)="Y",$C$1 & " has visited","") -> #N/A | D9: =IF(VLOOKUP(B9,'Country or Territory'!A:G,5,FALSE)="Y",$D$1 & " has visited","") -> #N/A | E9: =IF(VLOOKUP(B9,'Country or Territory'!A:G,6,FALSE)="Y",$E$1 & " has visited","") -> #N/A | F9: =IF(VLOOKUP(B9,'Country or Territory'!A:G,7,FALSE)="Y",$F$1 & " has visited","") -> #N/A | G9: =VLOOKUP(B9,latlong!A:F,4,TRUE) -> 40.18111 | H9: =VLOOKUP(B9,latlong!A:F,5,TRUE) -> 44.51361 | I9: =4-COUNTBLANK(C9:F9) -> 4
A10: =VLOOKUP(B10,'Country or Territory'!A:G,2,FALSE) -> #N/A | B10: AU | C10: =IF(VLOOKUP(B10,'Country or Territory'!A:G,4,FALSE)="Y",$C$1 & " has visited","") -> #N/A | D10: =IF(VLOOKUP(B10,'Country or Territory'!A:G,5,FALSE)="Y",$D$1 & " has visited","") -> #N/A | E10: =IF(VLOOKUP(B10,'Country or Territory'!A:G,6,FALSE)="Y",$E$1 & " has visited","") -> #N/A | F10: =IF(VLOOKUP(B10,'Country or Territory'!A:G,7,FALSE)="Y",$F$1 & " has visited","") -> #N/A | G10: =VLOOKUP(B10,latlong!A:F,4,TRUE) -> -33.86785 | H10: =VLOOKUP(B10,latlong!A:F,5,TRUE) -> 151.20732 | I10: =4-COUNTBLANK(C10:F10) -> 4
A11: =VLOOKUP(B11,'Country or Territory'!A:G,2,FALSE) -> #N/A | B11: AT | C11: =IF(VLOOKUP(B11,'Country or Territory'!A:G,4,FALSE)="Y",$C$1 & " has visited","") -> #N/A | D11: =IF(VLOOKUP(B11,'Country or Territory'!A:G,5,FALSE)="Y",$D$1 & " has visited","") -> #N/A | E11: =IF(VLOOKUP(B11,'Country or Territory'!A:G,6,FALSE)="Y",$E$1 & " has visited","") -> #N/A | F11: =IF(VLOOKUP(B11,'Country or Territory'!A:G,7,FALSE)="Y",$F$1 & " has visited","") -> #N/A | G11: =VLOOKUP(B11,latlong!A:F,4,TRUE) -> 48.20849 | H11: =VLOOKUP(B11,latlong!A:F,5,TRUE) -> 16.37208 | I11: =4-COUNTBLANK(C11:F11) -> 4
A12: =VLOOKUP(B12,'Country or Territory'!A:G,2,FALSE) -> #N/A | B12: AZ | C12: =IF(VLOOKUP(B12,'Country or Territory'!A:G,4,FALSE)="Y",$C$1 & " has visited","") -> #N/A | D12: =IF(VLOOKUP(B12,'Country or Territory'!A:G,5,FALSE)="Y",$D$1 & " has visited","") -> #N/A | E12: =IF(VLOOKUP(B12,'Country or Territory'!A:G,6,FALSE)="Y",$E$1 & " has visited","") -> #N/A | F12: =IF(VLOOKUP(B12,'Country or Territory'!A:G,7,FALSE)="Y",$F$1 & " has visited","") -> #N/A | G12: =VLOOKUP(B12,latlong!A:F,4,TRUE) -> 40.37767 | H12: =VLOOKUP(B12,latlong!A:F,5,TRUE) -> 49.89201 | I12: =4-COUNTBLANK(C12:F12) -> 4
A13: =VLOOKUP(B13,'Country or Territory'!A:G,2,FALSE) -> #N/A | B13: BS | C13: =IF(VLOOKUP(B13,'Country or Territory'!A:G,4,FALSE)="Y",$C$1 & " has visited","") -> #N/A | D13: =IF(VLOOKUP(B13,'Country or Territory'!A:G,5,FALSE)="Y",$D$1 & " has visited","") -> #N/A | E13: =IF(VLOOKUP(B13,'Country or Territory'!A:G,6,FALSE)="Y",$E$1 & " has visited","") -> #N/A | F13: =IF(VLOOKUP(B13,'Country or Territory'!A:G,7,FALSE)="Y",$F$1 & " has visited","") -> #N/A | G13: =VLOOKUP(B13,latlong!A:F,4,TRUE) -> 25.05823 | H13: =VLOOKUP(B13,latlong!A:F,5,TRUE) -> -77.34306 | I13: =4-COUNTBLANK(C13:F13) -> 4
... A198: =VLOOKUP(B198,'Country or Territory'!A:G,2,FALSE) -> #N/A | B198: GI | C198: =IF(VLOOKUP(B198,'Country or Territory'!A:G,4,FALSE)="Y",$C$1 & " has visited","") -> #N/A | D198: =IF(VLOOKUP(B198,'Country or Territory'!A:G,5,FALSE)="Y",$D$1 & " has visited","") -> #N/A | E198: =IF(VLOOKUP(B198,'Country or Territory'!A:G,6,FALSE)="Y",$E$1 & " has visited","") -> #N/A | F198: =IF(VLOOKUP(B198,'Country or Territory'!A:G,7,FALSE)="Y",$F$1 & " has visited","") -> #N/A | G198: =VLOOKUP(B198,latlong!A:F,4,TRUE) -> 36.14474 | H198: =VLOOKUP(B198,latlong!A:F,5,TRUE) -> -5.35257 | I198: =4-COUNTBLANK(C198:F198) -> 4

Sheet Sovereign & Non-Sovereign
B2: Sovereign states and dependent territories | J2: ISO 3166 standard defining codes for the names of countries, dependent territories, and special areas of geographical interest.
B3: https://en.wikipedia.org/wiki/List_of_sovereign_states_and_dependent_territories_by_continent | J3: https://en.wikipedia.org/wiki/ISO_3166-1
B4: Classification according to United Nations Statistics Division geoscheme, for statistical purposes
B5: excluding minor dependent territories that are not travel/tourism destinations
B6: Non-sovereign or dependent territories are:
B7: 1. Integral parts of sovereign states located outside these states' mainland.
B8: 2. Dependent territories of sovereign states.
B9: 3. Special territories recognized by international treaty (such as the special administrative regions of China)
B10: 4. Other territories often regarded as separate geographical territories even though they are integral parts of their mother countries (such as the overseas departments of France)
H12: Xinjiang SAR
B13: Name | C13: Capital | D13: Status
B14: Åland Islands | C14: Mariehamn | D14: Autonomous region of Finland (recognized by international treaty)
B15: Aruba | C15: Oranjestad | D15: Constituent country of the Kingdom of the Netherlands
B16: Curaçao | C16: Willemstad | D16: Constituent country of the Kingdom of the Netherlands
B17: Sint Maarten | C17: Philipsburg | D17: Constituent country of the Kingdom of the Netherlands
B18: Guernsey | C18: Saint Peter Port | D18: Crown dependency of the United Kingdom
B19: Isle of Man | C19: Douglas | D19: Crown dependency of the United Kingdom
B20: Jersey | C20: Saint Helier | D20: Crown dependency of the United Kingdom
B21: Sahrawi Arab Democratic Republic | C21: El Aaiún (official) | D21: De facto sovereign state lacking general international recognition. Claims territory of Western Sahara, most of which is controlled by Morocco.
B22: Nagorno-Karabakh | C22: Stepanakert | D22: De facto sovereign state lacking general international recognition. Recognized by the United Nations as part of Azerbaijan.
B23: Taiwan | C23: Taipei | D23: De facto sovereign state lacking general international recognition. Recognized by the United Nations as part of China.
B24: Northern Cyprus | C24: Nicosia | D24: De facto sovereign state lacking general international recognition. Recognized by the United Nations as part of Cyprus.
... B87: New Caledonia | C87: Nouméa | D87: Sui generis collectivity (special collectivity) of France
B89: Afghanistan | C89: Kabul
B90: Albania | C90: Tirana
B91: Algeria | C91: Algiers
B92: Andorra | C92: Andorra la Vella
B93: Angola | C93: Luanda
B94: Antigua and Barbuda | C94: St. John's
B95: Argentina | C95: Buenos Aires
B96: Armenia [Europe] | C96: Yerevan
B97: Australia | C97: Canberra
B98: Austria | C98: Vienna
B99: Azerbaijan [Europe] | C99: Baku
B100: Bahamas | C100: Nassau
... B284: Zimbabwe | C284: Harare

Sheet country codes
A1: NAME | B1: alpha 2 | C1: alpha 3 | D1: ADM0_A3 | E1: ISO 3166-2 | F1: reference code
A2: Afghanistan | B2: AF | C2: AFG | D2: =VLOOKUP(A2,'geojson fields'!$A$1:$M$280,12, FALSE) -> AFG | F2: =IF(ISBLANK(E2),B2,E2) -> AF
A3: Aland | B3: AX | C3: ALA | D3: =VLOOKUP(A3,'geojson fields'!$A$1:$M$280,12, FALSE) -> ALD | F3: =IF(ISBLANK(E3),B3,E3) -> AX
A4: Albania | B4: AL | C4: ALB | D4: =VLOOKUP(A4,'geojson fields'!$A$1:$M$280,12, FALSE) -> ALB | F4: =IF(ISBLANK(E4),B4,E4) -> AL
A5: Algeria | B5: DZ | C5: DZA | D5: =VLOOKUP(A5,'geojson fields'!$A$1:$M$280,12, FALSE) -> DZA | F5: =IF(ISBLANK(E5),B5,E5) -> DZ
A6: American Samoa | B6: AS | C6: ASM | D6: =VLOOKUP(A6,'geojson fields'!$A$1:$M$280,12, FALSE) -> ASM | F6: =IF(ISBLANK(E6),B6,E6) -> AS
A7: Andorra | B7: AD | C7: AND | D7: =VLOOKUP(A7,'geojson fields'!$A$1:$M$280,12, FALSE) -> AND | F7: =IF(ISBLANK(E7),B7,E7) -> AD
A8: Angola | B8: AO | C8: AGO | D8: =VLOOKUP(A8,'geojson fields'!$A$1:$M$280,12, FALSE) -> AGO | F8: =IF(ISBLANK(E8),B8,E8) -> AO
A9: Anguilla | B9: AI | C9: AIA | D9: =VLOOKUP(A9,'geojson fields'!$A$1:$M$280,12, FALSE) -> AIA | F9: =IF(ISBLANK(E9),B9,E9) -> AI
A10: Antarctica | B10: AQ | C10: ATA | D10: =VLOOKUP(A10,'geojson fields'!$A$1:$M$280,12, FALSE) -> ATA | F10: =IF(ISBLANK(E10),B10,E10) -> AQ
A11: Antigua and Barbuda | B11: AG | C11: ATG | D11: =VLOOKUP(A11,'geojson fields'!$A$1:$M$280,12, FALSE) -> ATG | F11: =IF(ISBLANK(E11),B11,E11) -> AG
A12: Argentina | B12: AR | C12: ARG | D12: =VLOOKUP(A12,'geojson fields'!$A$1:$M$280,12, FALSE) -> ARG | F12: =IF(ISBLANK(E12),B12,E12) -> AR
A13: Armenia | B13: AM | C13: ARM | D13: =VLOOKUP(A13,'geojson fields'!$A$1:$M$280,12, FALSE) -> ARM | F13: =IF(ISBLANK(E13),B13,E13) -> AM
... A17: Azerbaijan | B17: AZ | C17: AZE | D17: =VLOOKUP(A17,'geojson fields'!$A$1:$M$280,12, FALSE) -> AZE | F17: =IF(ISBLANK(E17),B17,E17) -> AZ
A18: Azores | D18: =VLOOKUP(A18,'geojson fields'!$A$1:$M$280,12, FALSE) -> PT-20 | E18: PT-20 | F18: =IF(ISBLANK(E18),B18,E18) -> PT-20
A19: Bahamas | B19: BS | C19: BHS | D19: =VLOOKUP(A19,'geojson fields'!$A$1:$M$280,12, FALSE) -> BHS | F19: =IF(ISBLANK(E19),B19,E19) -> BS
A20: Bahrain | B20: BH | C20: BHR | D20: =VLOOKUP(A20,'geojson fields'!$A$1:$M$280,12, FALSE) -> BHR | F20: =IF(ISBLANK(E20),B20,E20) -> BH
A21: Baleares | D21: =VLOOKUP(A21,'geojson fields'!$A$1:$M$280,12, FALSE) -> ES-PM | E21: ES-PM
A22: Bangladesh | B22: BD | C22: BGD | D22: =VLOOKUP(A22,'geojson fields'!$A$1:$M$280,12, FALSE) -> BGD | F22: =IF(ISBLANK(E22),B22,E22) -> BD
A23: Barbados | B23: BB | C23: BRB | D23: =VLOOKUP(A23,'geojson fields'!$A$1:$M$280,12, FALSE) -> BRB | F23: =IF(ISBLANK(E23),B23,E23) -> BB
A24: Belarus | B24: BY | C24: BLR | D24: =VLOOKUP(A24,'geojson fields'!$A$1:$M$280,12, FALSE) -> BLR | F24: =IF(ISBLANK(E24),B24,E24) -> BY
A25: Belgium | B25: BE | C25: BEL | D25: =VLOOKUP(A25,'geojson fields'!$A$1:$M$280,12, FALSE) -> BEL | F25: =IF(ISBLANK(E25),B25,E25) -> BE
A26: Belize | B26: BZ | C26: BLZ | D26: =VLOOKUP(A26,'geojson fields'!$A$1:$M$280,12, FALSE) -> BLZ | F26: =IF(ISBLANK(E26),B26,E26) -> BZ
A27: Benin | B27: BJ | C27: BEN | D27: =VLOOKUP(A27,'geojson fields'!$A$1:$M$280,12, FALSE) -> BEN | F27: =IF(ISBLANK(E27),B27,E27) -> BJ
A28: Bermuda | B28: BM | C28: BMU | D28: =VLOOKUP(A28,'geojson fields'!$A$1:$M$280,12, FALSE) -> BMU | F28: =IF(ISBLANK(E28),B28,E28) -> BM
A29: Bhutan | B29: BT | C29: BTN | D29: =VLOOKUP(A29,'geojson fields'!$A$1:$M$280,12, FALSE) -> BTN | F29: =IF(ISBLANK(E29),B29,E29) -> BT
A30: Bolivia | B30: BO | C30: BOL | D30: =VLOOKUP(A30,'geojson fields'!$A$1:$M$280,12, FALSE) -> BOL | F30: =IF(ISBLANK(E30),B30,E30) -> BO
A31: Bonaire | B31: BQ | C31: BES | D31: =VLOOKUP(A31,'geojson fields'!$A$1:$M$280,12, FALSE) -> NL-BQ1 | F31: =IF(ISBLANK(E31),B31,E31) -> BQ
A32: Bosnia and Herzegovina | B32: BA | C32: BIH | D32: =VLOOKUP(A32,'geojson fields'!$A$1:$M$280,12, FALSE) -> BIH | F32: =IF(ISBLANK(E32),B32,E32) -> BA
A33: Botswana | B33: BW | C33: BWA | D33: =VLOOKUP(A33,'geojson fields'!$A$1:$M$280,12, FALSE) -> BWA | F33: =IF(ISBLANK(E33),B33,E33) -> BW
... A43: Canada | B43: CA | C43: CAN | D43: =VLOOKUP(A43,'geojson fields'!$A$1:$M$280,12, FALSE) -> CAN | F43: =IF(ISBLANK(E43),B43,E43) -> CA
A44: Canary Islands | B44: IC | D44: =VLOOKUP(A44,'geojson fields'!$A$1:$M$280,12, FALSE) -> ES-CN | E44: ES-CN | F44: =IF(ISBLANK(E44),B44,E44) -> ES-CN
A45: Cayman Islands | B45: KY | C45: CYM | D45: =VLOOKUP(A45,'geojson fields'!$A$1:$M$280,12, FALSE) -> CYM | F45: =IF(ISBLANK(E45),B45,E45) -> KY
A46: Central African Republic | B46: CF | C46: CAF | D46: =VLOOKUP(A46,'geojson fields'!$A$1:$M$280,12, FALSE) -> CAF | F46: =IF(ISBLANK(E46),B46,E46) -> CF
A47: Ceuta | D47: =VLOOKUP(A47,'geojson fields'!$A$1:$M$280,12, FALSE) -> ES-CE | E47: ES-CE | F47: =IF(ISBLANK(E47),B47,E47) -> ES-CE
A48: Chad | B48: TD | C48: TCD | D48: =VLOOKUP(A48,'geojson fields'!$A$1:$M$280,12, FALSE) -> TCD | F48: =IF(ISBLANK(E48),B48,E48) -> TD
A49: Chile | B49: CL | C49: CHL | D49: =VLOOKUP(A49,'geojson fields'!$A$1:$M$280,12, FALSE) -> CHL | F49: =IF(ISBLANK(E49),B49,E49) -> CL
A50: China | B50: CN | C50: CHN | D50: =VLOOKUP(A50,'geojson fields'!$A$1:$M$280,12, FALSE) -> CHN | F50: =IF(ISBLANK(E50),B50,E50) -> CN
A51: Clipperton Island | D51: =VLOOKUP(A51,'geojson fields'!$A$1:$M$280,12, FALSE) -> CLP
A52: Colombia | B52: CO | C52: COL | D52: =VLOOKUP(A52,'geojson fields'!$A$1:$M$280,12, FALSE) -> COL | F52: =IF(ISBLANK(E52),B52,E52) -> CO
A53: Comoros | B53: KM | C53: COM | D53: =VLOOKUP(A53,'geojson fields'!$A$1:$M$280,12, FALSE) -> COM | F53: =IF(ISBLANK(E53),B53,E53) -> KM
A54: Cook Islands | B54: CK | C54: COK | D54: =VLOOKUP(A54,'geojson fields'!$A$1:$M$280,12, FALSE) -> COK | F54: =IF(ISBLANK(E54),B54,E54) -> CK
A55: Costa Rica | B55: CR | C55: CRI | D55: =VLOOKUP(A55,'geojson fields'!$A$1:$M$280,12, FALSE) -> CRI | F55: =IF(ISBLANK(E55),B55,E55) -> CR
A56: Cóte d'Ivoire | B56: CI | C56: CIV | D56: =VLOOKUP(A56,'geojson fields'!$A$1:$M$280,12, FALSE) -> CIV | F56: =IF(ISBLANK(E56),B56,E56) -> CI
A57: Croatia | B57: HR | C57: HRV | D57: =VLOOKUP(A57,'geojson fields'!$A$1:$M$280,12, FALSE) -> HRV | F57: =IF(ISBLANK(E57),B57,E57) -> HR
A58: Cuba | B58: CU | C58: CUB | D58: =VLOOKUP(A58,'geojson fields'!$A$1:$M$280,12, FALSE) -> CUB | F58: =IF(ISBLANK(E58),B58,E58) -> CU
A59: Curação | B59: CW | C59: CUW | D59: =VLOOKUP(A59,'geojson fields'!$A$1:$M$280,12, FALSE) -> CUW | F59: =IF(ISBLANK(E59),B59,E59) -> CW
A60: Cyprus | B60: CY | C60: CYP | D60: =VLOOKUP(A60,'geojson fields'!$A$1:$M$280,12, FALSE) -> CYP | F60: =IF(ISBLANK(E60),B60,E60) -> CY
A61: Czechia | B61: CZ | C61: CZE | D61: =VLOOKUP(A61,'geojson fields'!$A$1:$M$280,12, FALSE) -> CZE | F61: =IF(ISBLANK(E61),B61,E61) -> CZ
A62: Democratic Republic of the Congo | B62: CD | C62: COD | D62: =VLOOKUP(A62,'geojson fields'!$A$1:$M$280,12, FALSE) -> COD | F62: =IF(ISBLANK(E62),B62,E62) -> CD
A63: Denmark | B63: DK | C63: DNK | D63: =VLOOKUP(A63,'geojson fields'!$A$1:$M$280,12, FALSE) -> DNK | F63: =IF(ISBLANK(E63),B63,E63) -> DK
... A80: France | B80: FR | C80: FRA | D80: =VLOOKUP(A80,'geojson fields'!$A$1:$M$280,12, FALSE) -> FRA | F80: =IF(ISBLANK(E80),B80,E80) -> FR
A81: French Guiana | B81: GF | C81: GUF | D81: =VLOOKUP(A81,'geojson fields'!$A$1:$M$280,12, FALSE) -> FR-GF | E81: FR-GF | F81: =IF(ISBLANK(E81),B81,E81) -> FR-GF
A82: French Polynesia | B82: PF | C82: PYF | D82: =VLOOKUP(A82,'geojson fields'!$A$1:$M$280,12, FALSE) -> PYF | F82: =IF(ISBLANK(E82),B82,E82) -> PF
A83: French Southern and Antarctic Lands | B83: TF | C83: ATF | D83: =VLOOKUP(A83,'geojson fields'!$A$1:$M$280,12, FALSE) -> ATF | F83: =IF(ISBLANK(E83),B83,E83) -> TF
A84: Gabon | B84: GA | C84: GAB | D84: =VLOOKUP(A84,'geojson fields'!$A$1:$M$280,12, FALSE) -> GAB | F84: =IF(ISBLANK(E84),B84,E84) -> GA
A85: Gambia | B85: GM | C85: GMB | D85: =VLOOKUP(A85,'geojson fields'!$A$1:$M$280,12, FALSE) -> GMB | F85: =IF(ISBLANK(E85),B85,E85) -> GM
A86: Georgia | B86: GE | C86: GEO | D86: =VLOOKUP(A86,'geojson fields'!$A$1:$M$280,12, FALSE) -> GEO | F86: =IF(ISBLANK(E86),B86,E86) -> GE
A87: Germany | B87: DE | C87: DEU | D87: =VLOOKUP(A87,'geojson fields'!$A$1:$M$280,12, FALSE) -> DEU | F87: =IF(ISBLANK(E87),B87,E87) -> DE
A88: Ghana | B88: GH | C88: GHA | D88: =VLOOKUP(A88,'geojson fields'!$A$1:$M$280,12, FALSE) -> GHA | F88: =IF(ISBLANK(E88),B88,E88) -> GH
A89: Gibraltar | B89: GI | C89: GIB | D89: =VLOOKUP(A89,'geojson fields'!$A$1:$M$280,12, FALSE) -> GIB | F89: =IF(ISBLANK(E89),B89,E89) -> GI
A90: Greece | B90: GR | C90: GRC | D90: =VLOOKUP(A90,'geojson fields'!$A$1:$M$280,12, FALSE) -> GRC | F90: =IF(ISBLANK(E90),B90,E90) -> GR
A91: Greenland | B91: GL | C91: GRL | D91: =VLOOKUP(A91,'geojson fields'!$A$1:$M$280,12, FALSE) -> GRL | F91: =IF(ISBLANK(E91),B91,E91) -> GL
A92: Grenada | B92: GD | C92: GRD | D92: =VLOOKUP(A92,'geojson fields'!$A$1:$M$280,12, FALSE) -> GRD | F92: =IF(ISBLANK(E92),B92,E92) -> GD
A93: Guadeloupe | B93: GP | C93: GLP | D93: =VLOOKUP(A93,'geojson fields'!$A$1:$M$280,12, FALSE) -> FR-GP | E93: FR-GP | F93: =IF(ISBLANK(E93),B93,E93) -> FR-GP
A94: Guam | B94: GU | C94: GUM | D94: =VLOOKUP(A94,'geojson fields'!$A$1:$M$280,12, FALSE) -> GUM | F94: =IF(ISBLANK(E94),B94,E94) -> GU
A95: Guatemala | B95: GT | C95: GTM | D95: =VLOOKUP(A95,'geojson fields'!$A$1:$M$280,12, FALSE) -> GTM | F95: =IF(ISBLANK(E95),B95,E95) -> GT
A96: Guernsey | B96: GG | C96: GGY | D96: =VLOOKUP(A96,'geojson fields'!$A$1:$M$280,12, FALSE) -> GGY | F96: =IF(ISBLANK(E96),B96,E96) -> GG
A97: Guinea | B97: GN | C97: GIN | D97: =VLOOKUP(A97,'geojson fields'!$A$1:$M$280,12, FALSE) -> GIN | F97: =IF(ISBLANK(E97),B97,E97) -> GN
A98: Guinea-Bissau | B98: GW | C98: GNB | D98: =VLOOKUP(A98,'geojson fields'!$A$1:$M$280,12, FALSE) -> GNB | F98: =IF(ISBLANK(E98),B98,E98) -> GW
A99: Guyana | B99: GY | C99: GUY | D99: =VLOOKUP(A99,'geojson fields'!$A$1:$M$280,12, FALSE) -> GUY | F99: =IF(ISBLANK(E99),B99,E99) -> GY
A100: Haiti | B100: HT | C100: HTI | D100: =VLOOKUP(A100,'geojson fields'!$A$1:$M$280,12, FALSE) -> HTI | F100: =IF(ISBLANK(E100),B100,E100) -> HT
A101: Heard Island and McDonald Islands | B101: HM | C101: HMD | D101: =VLOOKUP(A101,'geojson fields'!$A$1:$M$280,12, FALSE) -> HMD | F101: =IF(ISBLANK(E101),B101,E101) -> HM
A102: Honduras | B102: HN | C102: HND | D102: =VLOOKUP(A102,'geojson fields'!$A$1:$M$280,12, FALSE) -> HND | F102: =IF(ISBLANK(E102),B102,E102) -> HN
A103: Hong Kong | B103: HK | C103: HKG | D103: =VLOOKUP(A103,'geojson fields'!$A$1:$M$280,12, FALSE) -> HKG | F103: =IF(ISBLANK(E103),B103,E103) -> HK
A104: Hungary | B104: HU | C104: HUN | D104: =VLOOKUP(A104,'geojson fields'!$A$1:$M$280,12, FALSE) -> HUN | F104: =IF(ISBLANK(E104),B104,E104) -> HU
A105: Iceland | B105: IS | C105: ISL | D105: =VLOOKUP(A105,'geojson fields'!$A$1:$M$280,12, FALSE) -> ISL | F105: =IF(ISBLANK(E105),B105,E105) -> IS
... A120: Kiribati | B120: KI | C120: KIR | D120: =VLOOKUP(A120,'geojson fields'!$A$1:$M$280,12, FALSE) -> KIR | F120: =IF(ISBLANK(E120),B120,E120) -> KI
A121: Kosovo | B121: XK | D121: =VLOOKUP(A121,'geojson fields'!$A$1:$M$280,12, FALSE) -> KOS | F121: =IF(ISBLANK(E121),B121,E121) -> XK
A122: Kuwait | B122: KW | C122: KWT | D122: =VLOOKUP(A122,'geojson fields'!$A$1:$M$280,12, FALSE) -> KWT | F122: =IF(ISBLANK(E122),B122,E122) -> KW
A123: Kyrgyzstan | B123: KG | C123: KGZ | D123: =VLOOKUP(A123,'geojson fields'!$A$1:$M$280,12, FALSE) -> KGZ | F123: =IF(ISBLANK(E123),B123,E123) -> KG
A124: La Réunion | B124: RE | C124: REU | D124: =VLOOKUP(A124,'geojson fields'!$A$1:$M$280,12, FALSE) -> FR-RE | E124: FR-RE | F124: =IF(ISBLANK(E124),B124,E124) -> FR-RE
A125: Laos | B125: LA | C125: LAO | D125: =VLOOKUP(A125,'geojson fields'!$A$1:$M$280,12, FALSE) -> LAO | F125: =IF(ISBLANK(E125),B125,E125) -> LA
A126: Latvia | B126: LV | C126: LVA | D126: =VLOOKUP(A126,'geojson fields'!$A$1:$M$280,12, FALSE) -> LVA | F126: =IF(ISBLANK(E126),B126,E126) -> LV
A127: Lebanon | B127: LB | C127: LBN | D127: =VLOOKUP(A127,'geojson fields'!$A$1:$M$280,12, FALSE) -> LBN | F127: =IF(ISBLANK(E127),B127,E127) -> LB
A128: Lesotho | B128: LS | C128: LSO | D128: =VLOOKUP(A128,'geojson fields'!$A$1:$M$280,12, FALSE) -> LSO | F128: =IF(ISBLANK(E128),B128,E128) -> LS
A129: Liberia | B129: LR | C129: LBR | D129: =VLOOKUP(A129,'geojson fields'!$A$1:$M$280,12, FALSE) -> LBR | F129: =IF(ISBLANK(E129),B129,E129) -> LR
A130: Libya | B130: LY | C130: LBY | D130: =VLOOKUP(A130,'geojson fields'!$A$1:$M$280,12, FALSE) -> LBY | F130: =IF(ISBLANK(E130),B130,E130) -> LY
A131: Liechtenstein | B131: LI | C131: LIE | D131: =VLOOKUP(A131,'geojson fields'!$A$1:$M$280,12, FALSE) -> LIE | F131: =IF(ISBLANK(E131),B131,E131) -> LI
A132: Lithuania | B132: LT | C132: LTU | D132: =VLOOKUP(A132,'geojson fields'!$A$1:$M$280,12, FALSE) -> LTU | F132: =IF(ISBLANK(E132),B132,E132) -> LT
A133: Luxembourg | B133: LU | C133: LUX | D133: =VLOOKUP(A133,'geojson fields'!$A$1:$M$280,12, FALSE) -> LUX | F133: =IF(ISBLANK(E133),B133,E133) -> LU
A134: Macao | B134: MO | C134: MAC | D134: =VLOOKUP(A134,'geojson fields'!$A$1:$M$280,12, FALSE) -> MAC | F134: =IF(ISBLANK(E134),B134,E134) -> MO
A135: Madagascar | B135: MG | C135: MDG | D135: =VLOOKUP(A135,'geojson fields'!$A$1:$M$280,12, FALSE) -> MDG | F135: =IF(ISBLANK(E135),B135,E135) -> MG
A136: Madeira | B136: MD | D136: =VLOOKUP(A136,'geojson fields'!$A$1:$M$280,12, FALSE) -> PT-30 | E136: PT-30 | F136: =IF(ISBLANK(E136),B136,E136) -> PT-30
A137: Malawi | B137: MW | C137: MWI | D137: =VLOOKUP(A137,'geojson fields'!$A$1:$M$280,12, FALSE) -> MWI | F137: =IF(ISBLANK(E137),B137,E137) -> MW
A138: Malaysia | B138: MY | C138: MYS | D138: =VLOOKUP(A138,'geojson fields'!$A$1:$M$280,12, FALSE) -> MYS | F138: =IF(ISBLANK(E138),B138,E138) -> MY
A139: Maldives | B139: MV | C139: MDV | D139: =VLOOKUP(A139,'geojson fields'!$A$1:$M$280,12, FALSE) -> MDV | F139: =IF(ISBLANK(E139),B139,E139) -> MV
A140: Mali | B140: ML | C140: MLI | D140: =VLOOKUP(A140,'geojson fields'!$A$1:$M$280,12, FALSE) -> MLI | F140: =IF(ISBLANK(E140),B140,E140) -> ML
A141: Malta | B141: MT | C141: MLT | D141: =VLOOKUP(A141,'geojson fields'!$A$1:$M$280,12, FALSE) -> MLT | F141: =IF(ISBLANK(E141),B141,E141) -> MT
A142: Marshall Islands | B142: MH | C142: MHL | D142: =VLOOKUP(A142,'geojson fields'!$A$1:$M$280,12, FALSE) -> MHL | F142: =IF(ISBLANK(E142),B142,E142) -> MH
...

Sheet geojson fields
A1: NAME | B1: featurecla | C1: scalerank | D1: LABELRANK | E1: SOVEREIGNT | F1: SOV_A3 | G1: ADM0_DIF | H1: LEVEL | I1: TYPE | J1: TLC | K1: ADMIN | L1: ADM0_A3 | M1: GEOU_DIF | N1: GEOUNIT | O1: GU_A3 | P1: SU_DIF | Q1: SUBUNIT | R1: SU_A3 | S1: BRK_DIFF | T1: NAME_LONG | U1: BRK_A3 | V1: BRK_NAME | W1: BRK_GROUP | X1: ABBREV | Y1: POSTAL | Z1: FORMAL_EN | AA1: FORMAL_FR | AB1: NAME_CIAWF | AC1: NOTE_ADM0 | AD1: NOTE_BRK | AE1: NAME_SORT | AF1: NAME_ALT | AG1: MAPCOLOR7 | AH1: MAPCOLOR8 | AI1: MAPCOLOR9 | AJ1: MAPCOLOR13 | AK1: POP_EST | AL1: POP_RANK | AM1: POP_YEAR | AN1: GDP_MD | AO1: GDP_YEAR | AP1: ECONOMY | AQ1: INCOME_GRP | AR1: FIPS_10 | AS1: ISO_A2 | AT1: ISO_A2_EH | AU1: ISO_A3 | AV1: ISO_A3_EH | AW1: ISO_N3 | AX1: ISO_N3_EH | AY1: UN_A3 | AZ1: WB_A2 | BA1: WB_A3 | BB1: WOE_ID | BC1: WOE_ID_EH | BD1: WOE_NOTE | BE1: ADM0_ISO | BF1: ADM0_DIFF | BG1: ADM0_TLC | BH1: ADM0_A3_US | BI1: ADM0_A3_FR | BJ1: ADM0_A3_RU | BK1: ADM0_A3_ES | BL1: ADM0_A3_CN | BM1: ADM0_A3_TW | BN1: ADM0_A3_IN | BO1: ADM0_A3_NP | BP1: ADM0_A3_PK | BQ1: ADM0_A3_DE | BR1: ADM0_A3_GB | BS1: ADM0_A3_BR | BT1: ADM0_A3_IL | BU1: ADM0_A3_PS | BV1: ADM0_A3_SA | BW1: ADM0_A3_EG | BX1: ADM0_A3_MA | BY1: ADM0_A3_PT | BZ1: ADM0_A3_AR | CA1: ADM0_A3_JP | CB1: ADM0_A3_KO | CC1: ADM0_A3_VN | CD1: ADM0_A3_TR | CE1: ADM0_A3_ID | CF1: ADM0_A3_PL | CG1: ADM0_A3_GR | CH1: ADM0_A3_IT | CI1: ADM0_A3_NL | CJ1: ADM0_A3_SE | CK1: ADM0_A3_BD | CL1: ADM0_A3_UA | CM1: ADM0_A3_UN | CN1: ADM0_A3_WB | CO1: CONTINENT | CP1: REGION_UN | CQ1: SUBREGION | CR1: REGION_WB | CS1: NAME_LEN | CT1: LONG_LEN | CU1: ABBREV_LEN | CV1: TINY | CW1: HOMEPART | CX1: MIN_ZOOM | CY1: MIN_LABEL | CZ1: MAX_LABEL | DA1: LABEL_X | DB1: LABEL_Y | DC1: NE_ID | DD1: WIKIDATAID | DE1: NAME_AR | DF1: NAME_BN | DG1: NAME_DE | DH1: NAME_EN | DI1: NAME_ES | DJ1: NAME_FA | DK1: NAME_FR | DL1: NAME_EL | DM1: NAME_HE | DN1: NAME_HI | DO1: NAME_HU | DP1: NAME_ID | DQ1: NAME_IT | DR1: NAME_JA | DS1: NAME_KO | DT1: NAME_NL | DU1: NAME_PL | DV1: NAME_PT | DW1: NAME_RU | DX1: NAME_SV | DY1: NAME_TR | DZ1: NAME_UK | EA1: NAME_UR | EB1: NAME_VI | EC1: NAME_ZH | ED1: NAME_ZHT | EE1: FCLASS_ISO | EF1: TLC_DIFF | EG1: FCLASS_TLC | EH1: FCLASS_US | EI1: FCLASS_FR | EJ1: FCLASS_RU | EK1: FCLASS_ES | EL1: FCLASS_CN | EM1: FCLASS_TW | EN1: FCLASS_IN | EO1: FCLASS_NP | EP1: FCLASS_PK | EQ1: FCLASS_DE | ER1: FCLASS_GB | ES1: FCLASS_BR | ET1: FCLASS_IL | EU1: FCLASS_PS | EV1: FCLASS_SA | EW1: FCLASS_EG | EX1: FCLASS_MA | EY1: FCLASS_PT | EZ1: FCLASS_AR | FA1: FCLASS_JP | FB1: FCLASS_KO | FC1: FCLASS_VN | FD1: FCLASS_TR | FE1: FCLASS_ID | FF1: FCLASS_PL | FG1: FCLASS_GR | FH1: FCLASS_IT | FI1: FCLASS_NL | FJ1: FCLASS_SE | FK1: FCLASS_BD | FL1: FCLASS_UA | FM1: iso_3166_2 | FN1: adm1_code | FO1: diss_me | FP1: wikipedia | FQ1: iso_a2 | FR1: adm0_sr | FS1: name_alt | FT1: name_local | FU1: type | FV1: type_en | FW1: code_local | FX1: code_hasc | FY1: note | FZ1: hasc_maybe | GA1: region | GB1: provnum_ne | GC1: gadm_level | GD1: check_me | GE1: datarank | GF1: abbrev | GG1: postal | GH1: area_sqkm | GI1: sameascity | GJ1: labelrank | GK1: name_len | GL1: mapcolor9 | GM1: mapcolor13 | GN1: fips | GO1: fips_alt | GP1: woe_id | GQ1: woe_label | GR1: woe_name | GS1: latitude | GT1: longitude | GU1: sov_a3 | GV1: adm0_a3 | GW1: adm0_label | GX1: admin | GY1: geonunit | GZ1: gu_a3 | HA1: gn_id | HB1: gn_name | HC1: gns_id | HD1: gns_name | HE1: gn_level | HF1: gn_region | HG1: gn_a1_code | HH1: region_sub | HI1: sub_code | HJ1: gns_level | HK1: gns_lang | HL1: gns_adm1 | HM1: gns_region | HN1: min_label | HO1: max_label | HP1: min_zoom | HQ1: wikidataid | HR1: name_ar | HS1: name_bn | HT1: name_de | HU1: name_en | HV1: name_es | HW1: name_fr | HX1: name_el | HY1: name_hi | HZ1: name_hu | IA1: name_id | IB1: name_it | IC1: name_ja | ID1: name_ko | IE1: name_nl | IF1: name_pl | IG1: name_pt | IH1: name_ru | II1: name_sv | IJ1: name_tr | IK1: name_vi | IL1: name_zh | IM1: ne_id | IN1: name_he | IO1: name_uk | IP1: name_ur | IQ1: name_fa | IR1: name_zht | IS1: region_cod
A2: Afghanistan | B2: Admin-0 country | C2: 0 | D2: 3 | E2: Afghanistan | F2: AFG | G2: 0 | H2: 2 | I2: Sovereign country | J2: 1 | K2: Afghanistan | L2: AFG | M2: 0 | N2: Afghanistan | O2: AFG | P2: 0 | Q2: Afghanistan | R2: AFG | S2: 0 | T2: Afghanistan | U2: AFG | V2: Afghanistan | X2: Afg. | Y2: AF | Z2: Islamic State of Afghanistan | AB2: Afghanistan | AE2: Afghanistan | AG2: 5 | AH2: 6 | AI2: 8 | AJ2: 7 | AK2: 38041754 | AL2: 15 | AM2: 2019 | AN2: 19291 | AO2: 2019 | AP2: 7. Least developed region | AQ2: 5. Low income | AR2: AF | AS2: AF | AT2: AF | AU2: AFG | AV2: AFG | AW2: 4 | AX2: 4 | AY2: 4 | AZ2: AF | BA2: AFG | BB2: 23424739 | BC2: 23424739 | BD2: Exact WOE match as country | BE2: AFG | BG2: AFG | BH2: AFG | BI2: AFG | BJ2: AFG | BK2: AFG | BL2: AFG | BM2: AFG | BN2: AFG | BO2: AFG | BP2: AFG | BQ2: AFG | BR2: AFG | BS2: AFG | BT2: AFG | BU2: AFG | BV2: AFG | BW2: AFG | BX2: AFG | BY2: AFG | BZ2: AFG | CA2: AFG | CB2: AFG | CC2: AFG | CD2: AFG | CE2: AFG | CF2: AFG | CG2: AFG | CH2: AFG | CI2: AFG | CJ2: AFG | CK2: AFG | CL2: AFG | CM2: -99 | CN2: -99 | CO2: Asia | CP2: Asia | CQ2: Southern Asia | CR2: South Asia | CS2: 11 | CT2: 11 | CU2: 4 | CV2: -99 | CW2: 1 | CX2: 0 | CY2: 3 | CZ2: 7 | DA2: 66.496586 | DB2: 34.164262 | DC2: 1159320319 | DD2: Q889 | DE2: Ø£ÙØºØ§Ù†Ø³ØªØ§Ù† | DF2: à¦†à¦«à¦—à¦¾à¦¨à¦¿à¦¸à§à¦¤à¦¾à¦¨ | DG2: Afghanistan | DH2: Afghanistan | DI2: AfganistÃ¡n | DJ2: Ø§ÙØºØ§Ù†Ø³ØªØ§Ù† | DK2: Afghanistan | DL2: Î‘Ï†Î³Î±Î½Î¹ÏƒÏ„Î¬Î½ | DM2: ××¤×’× ×™×¡×˜×Ÿ | DN2: à¤…à¤«à¤¼à¥à¤—à¤¾à¤¨à¤¿à¤¸à¥à¤¤à¤¾à¤¨ | DO2: AfganisztÃ¡n | DP2: Afganistan | DQ2: Afghanistan | DR2: ã‚¢ãƒ•ã‚¬ãƒ‹ã‚¹ã‚¿ãƒ³ | DS2: ì•„í”„ê°€ë‹ˆìŠ¤íƒ„ | DT2: Afghanistan | DU2: Afganistan | DV2: AfeganistÃ£o | DW2: ÐÑ„Ð³Ð°Ð½Ð¸ÑÑ‚Ð°Ð½ | DX2: Afghanistan | DY2: Afganistan | DZ2: ÐÑ„Ð³Ð°Ð½Ñ–ÑÑ‚Ð°Ð½ | EA2: Ø§ÙØºØ§Ù†Ø³ØªØ§Ù† | EB2: Afghanistan | EC2: é˜¿å¯Œæ±— | ED2: é˜¿å¯Œæ±— | EE2: Admin-0 country | EG2: Admin-0 country
A3: Akrotiri | B3: Admin-0 country | C3: 3 | D3: 3 | E3: United Kingdom | F3: GB1 | G3: 1 | H3: 2 | I3: Dependency | J3: 1 | K3: Akrotiri Sovereign Base Area | L3: WSB | M3: 0 | N3: Akrotiri Sovereign Base Area | O3: WSB | P3: 0 | Q3: Akrotiri Sovereign Base Area | R3: WSB | S3: 0 | T3: Akrotiri | U3: WSB | V3: Akrotiri | X3: Akr. | Y3: AK | AC3: U.K. | AD3: U.K. Base | AE3: Akrotiri Sovereign Base Area | AG3: 6 | AH3: 6 | AI3: 6 | AJ3: 3 | AK3: 7850 | AL3: 5 | AM3: 2017 | AN3: 314 | AO3: 2016 | AP3: 2. Developed region: nonG7 | AQ3: 2. High income: nonOECD | AR3: -99 | AS3: -99 | AT3: -99 | AU3: -99 | AV3: -99 | AW3: -99 | AX3: -99 | AY3: -99 | AZ3: -99 | BA3: -99 | BB3: -99 | BC3: -99 | BD3: No WOE equivalent. | BE3: -99 | BF3: 1 | BG3: WSB | BH3: WSB | BI3: WSB | BJ3: WSB | BK3: WSB | BL3: WSB | BM3: WSB | BN3: WSB | BO3: WSB | BP3: WSB | BQ3: WSB | BR3: WSB | BS3: WSB | BT3: WSB | BU3: WSB | BV3: WSB | BW3: WSB | BX3: WSB | BY3: WSB | BZ3: WSB | CA3: WSB | CB3: WSB | CC3: WSB | CD3: WSB | CE3: WSB | CF3: WSB | CG3: WSB | CH3: WSB | CI3: WSB | CJ3: WSB | CK3: WSB | CL3: WSB | CM3: -99 | CN3: -99 | CO3: Asia | CP3: Asia | CQ3: Western Asia | CR3: Europe & Central Asia | CS3: 8 | CT3: 8 | CU3: 4 | CV3: -99 | CW3: -99 | CX3: 0 | CY3: 6.5 | CZ3: 11 | DA3: 32.979025 | DB3: 34.60083 | DC3: 1159320741 | DD3: Q9143535 | DE3: Ø£ÙƒØ±ÙˆØªÙŠØ±ÙŠ | DF3: à¦†à¦•à§à¦°à§‹à¦¤à¦¿à¦°à¦¿ | DG3: Akrotiri | DH3: Akrotiri Sovereign Base Area | DI3: Akrotiri | DJ3: Ø¢Ú©Ø±ÙˆØªÛŒÛŒØ±ÛŒ | DK3: Akrotiri | DL3: Î”Ï…Ï„Î¹ÎºÎ® Î ÎµÏÎ¹Î¿Ï‡Î® ÎšÏ…ÏÎ¯Î±ÏÏ‡Ï‰Î½ Î’Î¬ÏƒÎµÏ‰Î½ | DM3: ××§×¨×•×˜×™×¨×™ | DN3: à¤…à¤•à¥à¤°à¥‹à¤¤à¤¿à¤°à¥€ | DO3: AkrotÃ­ri | DP3: Akrotiri | DQ3: Akrotiri | DR3: ã‚¢ã‚¯ãƒ­ãƒ†ã‚£ãƒª | DS3: ì•„í¬ë¡œí‹°ë¦¬ | DT3: Akrotiri | DU3: Akrotiri | DV3: AcrotÃ­ri | DW3: ÐÐºÑ€Ð¾Ñ‚Ð¸Ñ€Ð¸ | DX3: Akrotiri | DY3: AÄŸrotur | DZ3: ÐÐºÑ€Ð¾Ñ‚Ñ–Ñ€Ñ– | EA3: Ø§ÛŒÚ©Ø±ÙˆÙ¹ÛŒØ±ÛŒ | EB3: Akrotiri | EC3: é˜¿å…‹ç½—è’‚é‡Œä¸»æƒåŸºåœ°åŒº | ED3: é˜¿å…‹ç½—è’‚é‡Œä¸»æƒåŸºåœ°åŒº | EE3: Unrecognized | EF3: 1 | EG3: Admin-0 dependency | EH3: Admin-0 dependency | EI3: Admin-0 dependency | EK3: Admin-0 dependency | EQ3: Admin-0 dependency | ER3: Admin-0 dependency | EY3: Admin-0 dependency | FA3: Admin-0 dependency | FB3: Admin-0 dependency | FD3: Admin-0 dependency | FF3: Admin-0 dependency | FG3: Admin-0 dependency | FH3: Admin-0 dependency | FI3: Admin-0 dependency | FJ3: Admin-0 dependency | FL3: Admin-0 dependency
A4: Aland | B4: Admin-0 country | C4: 3 | D4: 6 | E4: Finland | F4: FI1 | G4: 1 | H4: 2 | I4: Country | J4: 1 | K4: Aland | L4: ALD | M4: 0 | N4: Aland | O4: ALD | P4: 0 | Q4: Aland | R4: ALD | S4: 0 | T4: Ã…land Islands | U4: ALD | V4: Ã…land | X4: Ã…land | Y4: AI | Z4: Ã…land Islands | AC4: Fin. | AE4: Aland | AG4: 4 | AH4: 1 | AI4: 4 | AJ4: 6 | AK4: 29884 | AL4: 7 | AM4: 2019 | AN4: 1563 | AO4: 2016 | AP4: 2. Developed region: nonG7 | AQ4: 1. High income: OECD | AR4: -99 | AS4: AX | AT4: AX | AU4: ALA | AV4: ALA | AW4: 248 | AX4: 248 | AY4: 248 | AZ4: -99 | BA4: -99 | BB4: 12577865 | BC4: 12577865 | BD4: Exact WOE match as country | BE4: ALD | BG4: ALD | BH4: ALD | BI4: ALD | BJ4: ALD | BK4: ALD | BL4: ALD | BM4: ALD | BN4: ALD | BO4: ALD | BP4: ALD | BQ4: ALD | BR4: ALD | BS4: ALD | BT4: ALD | BU4: ALD | BV4: ALD | BW4: ALD | BX4: ALD | BY4: ALD | BZ4: ALD | CA4: ALD | CB4: ALD | CC4: ALD | CD4: ALD | CE4: ALD | CF4: ALD | CG4: ALD | CH4: ALD | CI4: ALD | CJ4: ALD | CK4: ALD | CL4: ALD | CM4: -99 | CN4: -99 | CO4: Europe | CP4: Europe | CQ4: Northern Europe | CR4: Europe & Central Asia | CS4: 5 | CT4: 13 | CU4: 5 | CV4: 5 | CW4: -99 | CX4: 0 | CY4: 5 | CZ4: 10 | DA4: 19.869671 | DB4: 60.156467 | DC4: 1159320621 | DD4: Q5689 | DE4: Ø¬Ø²Ø± Ø£ÙˆÙ„Ø§Ù†Ø¯ | DF4: à¦…à¦²à¦¾à¦¨à§à¦¦ à¦¦à§à¦¬à§€à¦ªà¦ªà§à¦žà§à¦œ | DG4: Ã…land | DH4: Ã…land | DI4: Ã…land | DJ4: Ø¬Ø²Ø§ÛŒØ± Ø§Ù„Ù†Ø¯ | DK4: Ã…land | DL4: ÎÎ»Î±Î½Ï„ | DM4: ××•×œ× ×“ | DN4: à¤‘à¤²à¥ˆà¤£à¥à¤¡ à¤¦à¥à¤µà¥€à¤ªà¤¸à¤®à¥‚à¤¹ | DO4: Ã…land | DP4: Ã…land | DQ4: Isole Ã…land | DR4: ã‚ªãƒ¼ãƒ©ãƒ³ãƒ‰è«¸å³¶ | DS4: ì˜¬ëž€ë“œ ì œë„ | DT4: Ã…land | DU4: Wyspy Alandzkie | DV4: Ã…land | DW4: ÐÐ»Ð°Ð½Ð´ÑÐºÐ¸Ðµ Ð¾ÑÑ‚Ñ€Ð¾Ð²Ð° | DX4: Ã…land | DY4: Ã…land | DZ4: ÐÐ»Ð°Ð½Ð´ÑÑŒÐºÑ– Ð¾ÑÑ‚Ñ€Ð¾Ð²Ð¸ | EA4: Ø¬Ø²Ø§Ø¦Ø± Ø§ÛŒÙ„Ø§Ù†Úˆ | EB4: Ã…land | EC4: å¥¥å…° | ED4: å¥§è˜­ | EE4: Admin-0 dependency | EG4: Admin-0 dependency | EJ4: Unrecognized | EL4: Unrecognized
A5: Albania | B5: Admin-0 country | C5: 0 | D5: 6 | E5: Albania | F5: ALB | G5: 0 | H5: 2 | I5: Sovereign country | J5: 1 | K5: Albania | L5: ALB | M5: 0 | N5: Albania | O5: ALB | P5: 0 | Q5: Albania | R5: ALB | S5: 0 | T5: Albania | U5: ALB | V5: Albania | X5: Alb. | Y5: AL | Z5: Republic of Albania | AB5: Albania | AE5: Albania | AG5: 1 | AH5: 4 | AI5: 1 | AJ5: 6 | AK5: 2854191 | AL5: 12 | AM5: 2019 | AN5: 15279 | AO5: 2019 | AP5: 6. Developing region | AQ5: 4. Lower middle income | AR5: AL | AS5: AL | AT5: AL | AU5: ALB | AV5: ALB | AW5: 8 | AX5: 8 | AY5: 8 | AZ5: AL | BA5: ALB | BB5: 23424742 | BC5: 23424742 | BD5: Exact WOE match as country | BE5: ALB | BG5: ALB | BH5: ALB | BI5: ALB | BJ5: ALB | BK5: ALB | BL5: ALB | BM5: ALB | BN5: ALB | BO5: ALB | BP5: ALB | BQ5: ALB | BR5: ALB | BS5: ALB | BT5: ALB | BU5: ALB | BV5: ALB | BW5: ALB | BX5: ALB | BY5: ALB | BZ5: ALB | CA5: ALB | CB5: ALB | CC5: ALB | CD5: ALB | CE5: ALB | CF5: ALB | CG5: ALB | CH5: ALB | CI5: ALB | CJ5: ALB | CK5: ALB | CL5: ALB | CM5: -99 | CN5: -99 | CO5: Europe | CP5: Europe | CQ5: Southern Europe | CR5: Europe & Central Asia | CS5: 7 | CT5: 7 | CU5: 4 | CV5: -99 | CW5: 1 | CX5: 0 | CY5: 5 | CZ5: 10 | DA5: 20.11384 | DB5: 40.654855 | DC5: 1159320325 | DD5: Q222 | DE5: Ø£Ù„Ø¨Ø§Ù†ÙŠØ§ | DF5: à¦†à¦²à¦¬à§‡à¦¨à¦¿à¦¯à¦¼à¦¾ | DG5: Albanien | DH5: Albania | DI5: Albania | DJ5: Ø¢Ù„Ø¨Ø§Ù†ÛŒ | DK5: Albanie | DL5: Î‘Î»Î²Î±Î½Î¯Î± | DM5: ××œ×‘× ×™×” | DN5: à¤…à¤²à¥à¤¬à¤¾à¤¨à¤¿à¤¯à¤¾ | DO5: AlbÃ¡nia | DP5: Albania | DQ5: Albania | DR5: ã‚¢ãƒ«ãƒãƒ‹ã‚¢ | DS5: ì•Œë°”ë‹ˆì•„ | DT5: AlbaniÃ« | DU5: Albania | DV5: AlbÃ¢nia | DW5: ÐÐ»Ð±Ð°Ð½Ð¸Ñ | DX5: Albanien | DY5: Arnavutluk | DZ5: ÐÐ»Ð±Ð°Ð½Ñ–Ñ | EA5: Ø§Ù„Ø¨Ø§Ù†ÛŒØ§ | EB5: Albania | EC5: é˜¿å°”å·´å°¼äºš | ED5: é˜¿çˆ¾å·´å°¼äºž | EE5: Admin-0 country | EG5: Admin-0 country
A6: Algeria | B6: Admin-0 country | C6: 0 | D6: 3 | E6: Algeria | F6: DZA | G6: 0 | H6: 2 | I6: Sovereign country | J6: 1 | K6: Algeria | L6: DZA | M6: 0 | N6: Algeria | O6: DZA | P6: 0 | Q6: Algeria | R6: DZA | S6: 0 | T6: Algeria | U6: DZA | V6: Algeria | X6: Alg. | Y6: DZ | Z6: People's Democratic Republic of Algeria | AB6: Algeria | AE6: Algeria | AG6: 5 | AH6: 1 | AI6: 6 | AJ6: 3 | AK6: 43053054 | AL6: 15 | AM6: 2019 | AN6: 171091 | AO6: 2019 | AP6: 6. Developing region | AQ6: 3. Upper middle income | AR6: AG | AS6: DZ | AT6: DZ | AU6: DZA | AV6: DZA | AW6: 12 | AX6: 12 | AY6: 12 | AZ6: DZ | BA6: DZA | BB6: 23424740 | BC6: 23424740 | BD6: Exact WOE match as country | BE6: DZA | BG6: DZA | BH6: DZA | BI6: DZA | BJ6: DZA | BK6: DZA | BL6: DZA | BM6: DZA | BN6: DZA | BO6: DZA | BP6: DZA | BQ6: DZA | BR6: DZA | BS6: DZA | BT6: DZA | BU6: DZA | BV6: DZA | BW6: DZA | BX6: DZA | BY6: DZA | BZ6: DZA | CA6: DZA | CB6: DZA | CC6: DZA | CD6: DZA | CE6: DZA | CF6: DZA | CG6: DZA | CH6: DZA | CI6: DZA | CJ6: DZA | CK6: DZA | CL6: DZA | CM6: -99 | CN6: -99 | CO6: Africa | CP6: Africa | CQ6: Northern Africa | CR6: Middle East & North Africa | CS6: 7 | CT6: 7 | CU6: 4 | CV6: -99 | CW6: 1 | CX6: 0 | CY6: 2.5 | CZ6: 7 | DA6: 2.808241 | DB6: 27.397406 | DC6: 1159320565 | DD6: Q262 | DE6: Ø§Ù„Ø¬Ø²Ø§Ø¦Ø± | DF6: à¦†à¦²à¦œà§‡à¦°à¦¿à¦¯à¦¼à¦¾ | DG6: Algerien | DH6: Algeria | DI6: Argelia | DJ6: Ø§Ù„Ø¬Ø²Ø§ÛŒØ± | DK6: AlgÃ©rie | DL6: Î‘Î»Î³ÎµÏÎ¯Î± | DM6: ××œ×’'×™×¨×™×” | DN6: à¤…à¤²à¥à¤œà¥€à¤°à¤¿à¤¯à¤¾ | DO6: AlgÃ©ria | DP6: Aljazair | DQ6: Algeria | DR6: ã‚¢ãƒ«ã‚¸ã‚§ãƒªã‚¢ | DS6: ì•Œì œë¦¬ | DT6: Algerije | DU6: Algieria | DV6: ArgÃ©lia | DW6: ÐÐ»Ð¶Ð¸Ñ€ | DX6: Algeriet | DY6: Cezayir | DZ6: ÐÐ»Ð¶Ð¸Ñ€ | EA6: Ø§Ù„Ø¬Ø²Ø§Ø¦Ø± | EB6: AlgÃ©rie | EC6: é˜¿å°”åŠåˆ©äºš | ED6: é˜¿çˆ¾åŠåˆ©äºž | EE6: Admin-0 country | EG6: Admin-0 country
A7: American Samoa | B7: Admin-0 country | C7: 5 | D7: 4 | E7: United States of America | F7: US1 | G7: 1 | H7: 2 | I7: Dependency | J7: 1 | K7: American Samoa | L7: ASM | M7: 0 | N7: American Samoa | O7: ASM | P7: 0 | Q7: American Samoa | R7: ASM | S7: 0 | T7: American Samoa | U7: ASM | V7: American Samoa | X7: Am. Samoa | Y7: AS | Z7: American Samoa | AB7: American Samoa | AC7: U.S.A. | AE7: American Samoa | AG7: 4 | AH7: 5 | AI7: 1 | AJ7: 1 | AK7: 55312 | AL7: 8 | AM7: 2019 | AN7: 636 | AO7: 2018 | AP7: 6. Developing region | AQ7: 3. Upper middle income | AR7: AQ | AS7: AS | AT7: AS | AU7: ASM | AV7: ASM | AW7: 16 | AX7: 16 | AY7: 16 | AZ7: AS | BA7: ASM | BB7: 23424746 | BC7: 23424746 | BD7: Exact WOE match as country | BE7: ASM | BG7: ASM | BH7: ASM | BI7: ASM | BJ7: ASM | BK7: ASM | BL7: ASM | BM7: ASM | BN7: ASM | BO7: ASM | BP7: ASM | BQ7: ASM | BR7: ASM | BS7: ASM | BT7: ASM | BU7: ASM | BV7: ASM | BW7: ASM | BX7: ASM | BY7: ASM | BZ7: ASM | CA7: ASM | CB7: ASM | CC7: ASM | CD7: ASM | CE7: ASM | CF7: ASM | CG7: ASM | CH7: ASM | CI7: ASM | CJ7: ASM | CK7: ASM | CL7: ASM | CM7: -99 | CN7: -99 | CO7: Oceania | CP7: Oceania | CQ7: Polynesia | CR7: East Asia & Pacific | CS7: 14 | CT7: 14 | CU7: 9 | CV7: 3 | CW7: -99 | CX7: 0 | CY7: 4 | CZ7: 9 | DA7: -170.74715 | DB7: -14.32671 | DC7: 1159321357 | DD7: Q16641 | DE7: Ø³Ø§Ù…ÙˆØ§ Ø§Ù„Ø£Ù…Ø±ÙŠÙƒÙŠØ© | DF7: à¦®à¦¾à¦°à§à¦•à¦¿à¦¨ à¦¸à¦¾à¦®à§‹à¦¯à¦¼à¦¾ | DG7: Amerikanisch-Samoa | DH7: American Samoa | DI7: Samoa Estadounidense | DJ7: Ø³Ø§Ù…ÙˆØ¢ÛŒ Ø¢Ù…Ø±ÛŒÚ©Ø§ | DK7: Samoa amÃ©ricaines | DL7: Î‘Î¼ÎµÏÎ¹ÎºÎ±Î½Î¹ÎºÎ® Î£Î±Î¼ÏŒÎ± | DM7: ×¡×ž×•××” ×”××ž×¨×™×§× ×™×ª | DN7: à¤…à¤®à¥‡à¤°à¤¿à¤•à¥€ à¤¸à¤®à¥‹à¤† | DO7: Amerikai Szamoa | DP7: Samoa Amerika | DQ7: Samoa Americane | DR7: ã‚¢ãƒ¡ãƒªã‚«é ˜ã‚µãƒ¢ã‚¢ | DS7: ì•„ë©”ë¦¬ì¹¸ì‚¬ëª¨ì•„ | DT7: Amerikaans-Samoa | DU7: Samoa AmerykaÅ„skie | DV7: Samoa Americana | DW7: ÐÐ¼ÐµÑ€Ð¸ÐºÐ°Ð½ÑÐºÐ¾Ðµ Ð¡Ð°Ð¼Ð¾Ð° | DX7: Amerikanska Samoa | DY7: Amerikan SamoasÄ± | DZ7: Ð¡Ñ…Ñ–Ð´Ð½Ðµ Ð¡Ð°Ð¼Ð¾Ð° | EA7: Ø§Ù…Ø±ÛŒÚ©ÛŒ Ø³Ù…ÙˆÙˆØ§ | EB7: Samoa thuá»™c Má»¹ | EC7: ç¾Žå±žè¨æ‘©äºš | ED7: ç¾Žå±¬è–©æ‘©äºž | EE7: Admin-0 dependency | EG7: Admin-0 dependency
A8: Andorra | B8: Admin-0 country | C8: 0 | D8: 6 | E8: Andorra | F8: AND | G8: 0 | H8: 2 | I8: Sovereign country | J8: 1 | K8: Andorra | L8: AND | M8: 0 | N8: Andorra | O8: AND | P8: 0 | Q8: Andorra | R8: AND | S8: 0 | T8: Andorra | U8: AND | V8: Andorra | X8: And. | Y8: AND | Z8: Principality of Andorra | AB8: Andorra | AE8: Andorra | AG8: 1 | AH8: 4 | AI8: 1 | AJ8: 8 | AK8: 77142 | AL8: 8 | AM8: 2019 | AN8: 3154 | AO8: 2019 | AP8: 2. Developed region: nonG7 | AQ8: 2. High income: nonOECD | AR8: AN | AS8: AD | AT8: AD | AU8: AND | AV8: AND | AW8: 20 | AX8: 20 | AY8: 20 | AZ8: AD | BA8: ADO | BB8: 23424744 | BC8: 23424744 | BD8: Exact WOE match as country | BE8: AND | BG8: AND | BH8: AND | BI8: AND | BJ8: AND | BK8: AND | BL8: AND | BM8: AND | BN8: AND | BO8: AND | BP8: AND | BQ8: AND | BR8: AND | BS8: AND | BT8: AND | BU8: AND | BV8: AND | BW8: AND | BX8: AND | BY8: AND | BZ8: AND | CA8: AND | CB8: AND | CC8: AND | CD8: AND | CE8: AND | CF8: AND | CG8: AND | CH8: AND | CI8: AND | CJ8: AND | CK8: AND | CL8: AND | CM8: -99 | CN8: -99 | CO8: Europe | CP8: Europe | CQ8: Southern Europe | CR8: Europe & Central Asia | CS8: 7 | CT8: 7 | CU8: 4 | CV8: 5 | CW8: 1 | CX8: 0 | CY8: 5 | CZ8: 10 | DA8: 1.539409 | DB8: 42.547643 | DC8: 1159320327 | DD8: Q228 | DE8: Ø£Ù†Ø¯ÙˆØ±Ø§ | DF8: à¦…à§à¦¯à¦¾à¦¨à§à¦¡à§‹à¦°à¦¾ | DG8: Andorra | DH8: Andorra | DI8: Andorra | DJ8: Ø¢Ù†Ø¯ÙˆØ±Ø§ | DK8: Andorre | DL8: Î‘Î½Î´ÏŒÏÏÎ± | DM8: ×× ×“×•×¨×” | DN8: à¤…à¤£à¥à¤¡à¥‹à¤°à¤¾ | DO8: Andorra | DP8: Andorra | DQ8: Andorra | DR8: ã‚¢ãƒ³ãƒ‰ãƒ© | DS8: ì•ˆë„ë¼ | DT8: Andorra | DU8: Andora | DV8: Andorra | DW8: ÐÐ½Ð´Ð¾Ñ€Ñ€Ð° | DX8: Andorra | DY8: Andorra | DZ8: ÐÐ½Ð´Ð¾Ñ€Ñ€Ð° | EA8: Ø§Ù†ÚˆÙˆØ±Ø§ | EB8: Andorra | EC8: å®‰é“å°” | ED8: å®‰é“çˆ¾ | EE8: Admin-0 country | EG8: Admin-0 country
A9: Angola | B9: Admin-0 country | C9: 0 | D9: 3 | E9: Angola | F9: AGO | G9: 0 | H9: 2 | I9: Sovereign country | J9: 1 | K9: Angola | L9: AGO | M9: 0 | N9: Angola | O9: AGO | P9: 0 | Q9: Angola | R9: AGO | S9: 0 | T9: Angola | U9: AGO | V9: Angola | X9: Ang. | Y9: AO | Z9: People's Republic of Angola | AB9: Angola | AE9: Angola | AG9: 3 | AH9: 2 | AI9: 6 | AJ9: 1 | AK9: 31825295 | AL9: 15 | AM9: 2019 | AN9: 88815 | AO9: 2019 | AP9: 7. Least developed region | AQ9: 3. Upper middle income | AR9: AO | AS9: AO | AT9: AO | AU9: AGO | AV9: AGO | AW9: 24 | AX9: 24 | AY9: 24 | AZ9: AO | BA9: AGO | BB9: 23424745 | BC9: 23424745 | BD9: Exact WOE match as country | BE9: AGO | BG9: AGO | BH9: AGO | BI9: AGO | BJ9: AGO | BK9: AGO | BL9: AGO | BM9: AGO | BN9: AGO | BO9: AGO | BP9: AGO | BQ9: AGO | BR9: AGO | BS9: AGO | BT9: AGO | BU9: AGO | BV9: AGO | BW9: AGO | BX9: AGO | BY9: AGO | BZ9: AGO | CA9: AGO | CB9: AGO | CC9: AGO | CD9: AGO | CE9: AGO | CF9: AGO | CG9: AGO | CH9: AGO | CI9: AGO | CJ9: AGO | CK9: AGO | CL9: AGO | CM9: -99 | CN9: -99 | CO9: Africa | CP9: Africa | CQ9: Middle Africa | CR9: Sub-Saharan Africa | CS9: 6 | CT9: 6 | CU9: 4 | CV9: -99 | CW9: 1 | CX9: 0 | CY9: 3 | CZ9: 7 | DA9: 17.984249 | DB9: -12.182762 | DC9: 1159320323 | DD9: Q916 | DE9: Ø£Ù†ØºÙˆÙ„Ø§ | DF9: à¦…à§à¦¯à¦¾à¦™à§à¦—à§‹à¦²à¦¾ | DG9: Angola | DH9: Angola | DI9: Angola | DJ9: Ø¢Ù†Ú¯ÙˆÙ„Ø§ | DK9: Angola | DL9: Î‘Î½Î³ÎºÏŒÎ»Î± | DM9: ×× ×’×•×œ×” | DN9: à¤…à¤‚à¤—à¥‹à¤²à¤¾ | DO9: Angola | DP9: Angola | DQ9: Angola | DR9: ã‚¢ãƒ³ã‚´ãƒ© | DS9: ì•™ê³¨ë¼ | DT9: Angola | DU9: Angola | DV9: Angola | DW9: ÐÐ½Ð³Ð¾Ð»Ð° | DX9: Angola | DY9: Angola | DZ9: ÐÐ½Ð³Ð¾Ð»Ð° | EA9: Ø§Ù†Ú¯ÙˆÙ„Ø§ | EB9: Angola | EC9: å®‰å“¥æ‹‰ | ED9: å®‰å“¥æ‹‰ | EE9: Admin-0 country | EG9: Admin-0 country
A10: Anguilla | B10: Admin-0 country | C10: 3 | D10: 6 | E10: United Kingdom | F10: GB1 | G10: 1 | H10: 2 | I10: Dependency | J10: 1 | K10: Anguilla | L10: AIA | M10: 0 | N10: Anguilla | O10: AIA | P10: 0 | Q10: Anguilla | R10: AIA | S10: 0 | T10: Anguilla | U10: AIA | V10: Anguilla | X10: Ang. | Y10: AI | AB10: Anguilla | AC10: U.K. | AE10: Anguilla | AG10: 6 | AH10: 6 | AI10: 6 | AJ10: 3 | AK10: 14731 | AL10: 6 | AM10: 2018 | AN10: 175 | AO10: 2009 | AP10: 6. Developing region | AQ10: 3. Upper middle income | AR10: AV | AS10: AI | AT10: AI | AU10: AIA | AV10: AIA | AW10: 660 | AX10: 660 | AY10: 660 | AZ10: -99 | BA10: -99 | BB10: 23424751 | BC10: 23424751 | BD10: Exact WOE match as country | BE10: AIA | BG10: AIA | BH10: AIA | BI10: AIA | BJ10: AIA | BK10: AIA | BL10: AIA | BM10: AIA | BN10: AIA | BO10: AIA | BP10: AIA | BQ10: AIA | BR10: AIA | BS10: AIA | BT10: AIA | BU10: AIA | BV10: AIA | BW10: AIA | BX10: AIA | BY10: AIA | BZ10: AIA | CA10: AIA | CB10: AIA | CC10: AIA | CD10: AIA | CE10: AIA | CF10: AIA | CG10: AIA | CH10: AIA | CI10: AIA | CJ10: AIA | CK10: AIA | CL10: AIA | CM10: -99 | CN10: -99 | CO10: North America | CP10: Americas | CQ10: Caribbean | CR10: Latin America & Caribbean | CS10: 8 | CT10: 8 | CU10: 4 | CV10: -99 | CW10: -99 | CX10: 0 | CY10: 5 | CZ10: 10 | DA10: -63.026361 | DB10: 18.242979 | DC10: 1159320703 | DD10: Q25228 | DE10: Ø£Ù†ØºÙˆÙŠÙ„Ø§ | DF10: à¦à§à¦¯à¦¾à¦™à§à¦—à§à¦‡à¦²à¦¾ | DG10: Anguilla | DH10: Anguilla | DI10: Anguila | DJ10: Ø¢Ù†Ú¯ÙˆÛŒÙ„Ø§ | DK10: Anguilla | DL10: Î‘Î½Î³ÎºÎ¿Ï…Î¯Î»Î± | DM10: ×× ×’×•×•×™×œ×” | DN10: à¤…à¤‚à¤—à¥à¤‡à¤²à¤¾ | DO10: Anguilla | DP10: Anguilla | DQ10: Anguilla | DR10: ã‚¢ãƒ³ã‚®ãƒ© | DS10: ì•µê·ˆë¼ | DT10: Anguilla | DU10: Anguilla | DV10: Anguilla | DW10: ÐÐ½Ð³Ð¸Ð»ÑŒÑ | DX10: Anguilla | DY10: Anguilla | DZ10: ÐÐ½Ð³Ñ–Ð»ÑŒÑ | EA10: Ø§ÛŒÙ†Ú¯ÙˆÛŒÙ„Ø§ | EB10: Anguilla | EC10: å®‰åœ­æ‹‰ | ED10: å®‰å‰æ‹‰ | EE10: Admin-0 dependency | EG10: Admin-0 dependency
A11: Antarctica | B11: Admin-0 country | C11: 0 | D11: 4 | E11: Antarctica | F11: ATA | G11: 0 | H11: 2 | I11: Indeterminate | J11: 1 | K11: Antarctica | L11: ATA | M11: 0 | N11: Antarctica | O11: ATA | P11: 0 | Q11: Antarctica | R11: ATA | S11: 0 | T11: Antarctica | U11: ATA | V11: Antarctica | X11: Ant. | Y11: AQ | AC11: By treaty | AD11: Multiple claims held in abeyance by treaty | AE11: Antarctica | AG11: 4 | AH11: 5 | AI11: 1 | AJ11: -99 | AK11: 4490 | AL11: 4 | AM11: 2019 | AN11: 898 | AO11: 2013 | AP11: 6. Developing region | AQ11: 2. High income: nonOECD | AR11: AY | AS11: AQ | AT11: AQ | AU11: ATA | AV11: ATA | AW11: 10 | AX11: 10 | AY11: 10 | AZ11: -99 | BA11: -99 | BB11: 28289409 | BC11: 28289409 | BD11: Exact WOE match as country | BE11: ATA | BG11: ATA | BH11: ATA | BI11: ATA | BJ11: ATA | BK11: ATA | BL11: ATA | BM11: ATA | BN11: ATA | BO11: ATA | BP11: ATA | BQ11: ATA | BR11: ATA | BS11: ATA | BT11: ATA | BU11: ATA | BV11: ATA | BW11: ATA | BX11: ATA | BY11: ATA | BZ11: ATA | CA11: ATA | CB11: ATA | CC11: ATA | CD11: ATA | CE11: ATA | CF11: ATA | CG11: ATA | CH11: ATA | CI11: ATA | CJ11: ATA | CK11: ATA | CL11: ATA | CM11: -99 | CN11: -99 | CO11: Antarctica | CP11: Antarctica | CQ11: Antarctica | CR11: Antarctica | CS11: 10 | CT11: 10 | CU11: 4 | CV11: -99 | CW11: 1 | CX11: 0 | CY11: 4 | CZ11: 9 | DA11: 35.885455 | DB11: -79.843222 | DC11: 1159320335 | DD11: Q51 | DE11: Ø§Ù„Ù‚Ø§Ø±Ø© Ø§Ù„Ù‚Ø·Ø¨ÙŠØ© Ø§Ù„Ø¬Ù†ÙˆØ¨ÙŠØ© | DF11: à¦…à§à¦¯à¦¾à¦¨à§à¦Ÿà¦¾à¦°à§à¦•à¦Ÿà¦¿à¦•à¦¾ | DG11: Antarktika | DH11: Antarctica | DI11: AntÃ¡rtida | DJ11: Ø¬Ù†ÙˆØ¨Ú¯Ø§Ù† | DK11: Antarctique | DL11: Î‘Î½Ï„Î±ÏÎºÏ„Î¹ÎºÎ® | DM11: ×× ×˜××¨×§×˜×™×§×” | DN11: à¤…à¤‚à¤Ÿà¤¾à¤°à¥à¤•à¤Ÿà¤¿à¤•à¤¾ | DO11: Antarktika | DP11: Antartika | DQ11: Antartide | DR11: å—æ¥µå¤§é™¸ | DS11: ë‚¨ê·¹ | DT11: Antarctica | DU11: Antarktyda | DV11: AntÃ¡rtida | DW11: ÐÐ½Ñ‚Ð°Ñ€ÐºÑ‚Ð¸Ð´Ð° | DX11: Antarktis | DY11: Antarktika | DZ11: ÐÐ½Ñ‚Ð°Ñ€ÐºÑ‚Ð¸Ð´Ð° | EA11: Ø§Ù†Ù¹Ø§Ø±Ú©Ù¹Ú©Ø§ | EB11: ChÃ¢u Nam Cá»±c | EC11: å—æžæ´² | ED11: å—æ¥µæ´² | EE11: Admin-0 dependency | EG11: Admin-0 dependency
A12: Antigua and Barbuda | B12: Admin-0 country | C12: 3 | D12: 6 | E12: Antigua and Barbuda | F12: ATG | G12: 0 | H12: 2 | I12: Sovereign country | J12: 1 | K12: Antigua and Barbuda | L12: ATG | M12: 0 | N12: Antigua and Barbuda | O12: ATG | P12: 0 | Q12: Antigua and Barbuda | R12: ATG | S12: 0 | T12: Antigua and Barbuda | U12: ATG | V12: Antigua and Barb. | X12: Ant.B. | Y12: AG | Z12: Antigua and Barbuda | AB12: Antigua and Barbuda | AE12: Antigua and Barbuda | AG12: 2 | AH12: 2 | AI12: 5 | AJ12: 5 | AK12: 97118 | AL12: 8 | AM12: 2019 | AN12: 1661 | AO12: 2019 | AP12: 6. Developing region | AQ12: 3. Upper middle income | AR12: AC | AS12: AG | AT12: AG | AU12: ATG | AV12: ATG | AW12: 28 | AX12: 28 | AY12: 28 | AZ12: AG | BA12: ATG | BB12: 23424737 | BC12: 23424737 | BD12: Exact WOE match as country | BE12: ATG | BG12: ATG | BH12: ATG | BI12: ATG | BJ12: ATG | BK12: ATG | BL12: ATG | BM12: ATG | BN12: ATG | BO12: ATG | BP12: ATG | BQ12: ATG | BR12: ATG | BS12: ATG | BT12: ATG | BU12: ATG | BV12: ATG | BW12: ATG | BX12: ATG | BY12: ATG | BZ12: ATG | CA12: ATG | CB12: ATG | CC12: ATG | CD12: ATG | CE12: ATG | CF12: ATG | CG12: ATG | CH12: ATG | CI12: ATG | CJ12: ATG | CK12: ATG | CL12: ATG | CM12: -99 | CN12: -99 | CO12: North America | CP12: Americas | CQ12: Caribbean | CR12: Latin America & Caribbean | CS12: 17 | CT12: 19 | CU12: 6 | CV12: 4 | CW12: 1 | CX12: 0 | CY12: 5 | CZ12: 9.5 | DA12: -61.790612 | DB12: 17.352249 | DC12: 1159320345 | DD12: Q781 | DE12: Ø£Ù†ØªÙŠØºÙˆØ§ ÙˆØ¨Ø§Ø±Ø¨ÙˆØ¯Ø§ | DF12: à¦…à§à¦¯à¦¾à¦¨à§à¦Ÿà¦¿à¦—à§à¦¯à¦¼à¦¾ à¦“ à¦¬à¦¾à¦°à§à¦¬à§à¦¡à¦¾ | DG12: Antigua und Barbuda | DH12: Antigua and Barbuda | DI12: Antigua y Barbuda | DJ12: Ø¢Ù†ØªÛŒÚ¯ÙˆØ§ Ùˆ Ø¨Ø§Ø±Ø¨ÙˆØ¯Ø§ | DK12: Antigua-et-Barbuda | DL12: Î‘Î½Ï„Î¯Î³ÎºÎ¿Ï…Î± ÎºÎ±Î¹ ÎœÏ€Î±ÏÎ¼Ï€Î¿ÏÎ½Ï„Î± | DM12: ×× ×˜×™×’×•××” ×•×‘×¨×‘×•×“×” | DN12: à¤…à¤£à¥à¤Ÿà¥€à¤—à¥à¤† à¤”à¤° à¤¬à¤¾à¤°à¤¬à¥‚à¤¡à¤¾ | DO12: Antigua Ã©s Barbuda | DP12: Antigua dan Barbuda | DQ12: Antigua e Barbuda | DR12: ã‚¢ãƒ³ãƒ†ã‚£ã‚°ã‚¢ãƒ»ãƒãƒ¼ãƒ–ãƒ¼ãƒ€ | DS12: ì•¤í‹°ê°€ ë°”ë¶€ë‹¤ | DT12: Antigua en Barbuda | DU12: Antigua i Barbuda | DV12: AntÃ­gua e Barbuda | DW12: ÐÐ½Ñ‚Ð¸Ð³ÑƒÐ° Ð¸ Ð‘Ð°Ñ€Ð±ÑƒÐ´Ð° | DX12: Antigua och Barbuda | DY12: Antigua ve Barbuda | DZ12: ÐÐ½Ñ‚Ð¸Ð³ÑƒÐ° Ñ– Ð‘Ð°Ñ€Ð±ÑƒÐ´Ð° | EA12: Ø§ÛŒÙ†Ù¹ÛŒÚ¯ÙˆØ§ Ùˆ Ø¨Ø§Ø±Ø¨ÙˆÚˆØ§ | EB12: Antigua vÃ Barbuda | EC12: å®‰æç“œå’Œå·´å¸ƒè¾¾ | ED12: å®‰åœ°å¡åŠå·´å¸ƒé” | EE12: Admin-0 country | EG12: Admin-0 country
A13: Argentina | B13: Admin-0 country | C13: 0 | D13: 2 | E13: Argentina | F13: ARG | G13: 0 | H13: 2 | I13: Sovereign country | J13: 1 | K13: Argentina | L13: ARG | M13: 0 | N13: Argentina | O13: ARG | P13: 0 | Q13: Argentina | R13: ARG | S13: 0 | T13: Argentina | U13: ARG | V13: Argentina | X13: Arg. | Y13: AR | Z13: Argentine Republic | AB13: Argentina | AE13: Argentina | AG13: 3 | AH13: 1 | AI13: 3 | AJ13: 13 | AK13: 44938712 | AL13: 15 | AM13: 2019 | AN13: 445445 | AO13: 2019 | AP13: 5. Emerging region: G20 | AQ13: 3. Upper middle income | AR13: AR | AS13: AR | AT13: AR | AU13: ARG | AV13: ARG | AW13: 32 | AX13: 32 | AY13: 32 | AZ13: AR | BA13: ARG | BB13: 23424747 | BC13: 23424747 | BD13: Exact WOE match as country | BE13: ARG | BG13: ARG | BH13: ARG | BI13: ARG | BJ13: ARG | BK13: ARG | BL13: ARG | BM13: ARG | BN13: ARG | BO13: ARG | BP13: ARG | BQ13: ARG | BR13: ARG | BS13: ARG | BT13: ARG | BU13: ARG | BV13: ARG | BW13: ARG | BX13: ARG | BY13: ARG | BZ13: ARG | CA13: ARG | CB13: ARG | CC13: ARG | CD13: ARG | CE13: ARG | CF13: ARG | CG13: ARG | CH13: ARG | CI13: ARG | CJ13: ARG | CK13: ARG | CL13: ARG | CM13: -99 | CN13: -99 | CO13: South America | CP13: Americas | CQ13: South America | CR13: Latin America & Caribbean | CS13: 9 | CT13: 9 | CU13: 4 | CV13: -99 | CW13: 1 | CX13: 0 | CY13: 2 | CZ13: 7 | DA13: -64.173331 | DB13: -33.501159 | DC13: 1159320331 | DD13: Q414 | DE13: Ø§Ù„Ø£Ø±Ø¬Ù†ØªÙŠÙ† | DF13: à¦†à¦°à§à¦œà§‡à¦¨à§à¦Ÿà¦¿à¦¨à¦¾ | DG13: Argentinien | DH13: Argentina | DI13: Argentina | DJ13: Ø¢Ø±Ú˜Ø§Ù†ØªÛŒÙ† | DK13: Argentine | DL13: Î‘ÏÎ³ÎµÎ½Ï„Î¹Î½Î® | DM13: ××¨×’× ×˜×™× ×” | DN13: à¤…à¤°à¥à¤œà¥‡à¤£à¥à¤Ÿà¥€à¤¨à¤¾ | DO13: ArgentÃ­na | DP13: Argentina | DQ13: Argentina | DR13: ã‚¢ãƒ«ã‚¼ãƒ³ãƒãƒ³ | DS13: ì•„ë¥´í—¨í‹°ë‚˜ | DT13: ArgentiniÃ« | DU13: Argentyna | DV13: Argentina | DW13: ÐÑ€Ð³ÐµÐ½Ñ‚Ð¸Ð½Ð° | DX13: Argentina | DY13: Arjantin | DZ13: ÐÑ€Ð³ÐµÐ½Ñ‚Ð¸Ð½Ð° | EA13: Ø§Ø±Ø¬Ù†Ù¹Ø§Ø¦Ù† | EB13: Argentina | EC13: é˜¿æ ¹å»· | ED13: é˜¿æ ¹å»· | EE13: Admin-0 country | EG13: Admin-0 country
A14: Armenia | B14: Admin-0 country | C14: 0 | D14: 6 | E14: Armenia | F14: ARM | G14: 0 | H14: 2 | I14: Sovereign country | J14: 1 | K14: Armenia | L14: ARM | M14: 0 | N14: Armenia | O14: ARM | P14: 0 | Q14: Armenia | R14: ARM | S14: 0 | T14: Armenia | U14: ARM | V14: Armenia | X14: Arm. | Y14: ARM | Z14: Republic of Armenia | AB14: Armenia | AE14: Armenia | AG14: 3 | AH14: 1 | AI14: 2 | AJ14: 10 | AK14: 2957731 | AL14: 12 | AM14: 2019 | AN14: 13672 | AO14: 2019 | AP14: 6. Developing region | AQ14: 4. Lower middle income | AR14: AM | AS14: AM | AT14: AM | AU14: ARM | AV14: ARM | AW14: 51 | AX14: 51 | AY14: 51 | AZ14: AM | BA14: ARM | BB14: 23424743 | BC14: 23424743 | BD14: Exact WOE match as country | BE14: ARM | BG14: ARM | BH14: ARM | BI14: ARM | BJ14: ARM | BK14: ARM | BL14: ARM | BM14: ARM | BN14: ARM | BO14: ARM | BP14: ARM | BQ14: ARM | BR14: ARM | BS14: ARM | BT14: ARM | BU14: ARM | BV14: ARM | BW14: ARM | BX14: ARM | BY14: ARM | BZ14: ARM | CA14: ARM | CB14: ARM | CC14: ARM | CD14: ARM | CE14: ARM | CF14: ARM | CG14: ARM | CH14: ARM | CI14: ARM | CJ14: ARM | CK14: ARM | CL14: ARM | CM14: -99 | CN14: -99 | CO14: Asia | CP14: Asia | CQ14: Western Asia | CR14: Europe & Central Asia | CS14: 7 | CT14: 7 | CU14: 4 | CV14: -99 | CW14: 1 | CX14: 0 | CY14: 5 | CZ14: 10 | DA14: 44.800564 | DB14: 40.459077 | DC14: 1159320333 | DD14: Q399 | DE14: Ø£Ø±Ù…ÙŠÙ†ÙŠØ§ | DF14: à¦†à¦°à§à¦®à§‡à¦¨à¦¿à¦¯à¦¼à¦¾ | DG14: Armenien | DH14: Armenia | DI14: Armenia | DJ14: Ø§Ø±Ù…Ù†Ø³ØªØ§Ù† | DK14: ArmÃ©nie | DL14: Î‘ÏÎ¼ÎµÎ½Î¯Î± | DM14: ××¨×ž× ×™×” | DN14: à¤†à¤°à¥à¤®à¥€à¤¨à¤¿à¤¯à¤¾ | DO14: Ã–rmÃ©nyorszÃ¡g | DP14: Armenia | DQ14: Armenia | DR14: ã‚¢ãƒ«ãƒ¡ãƒ‹ã‚¢ | DS14: ì•„ë¥´ë©”ë‹ˆì•„ | DT14: ArmeniÃ« | DU14: Armenia | DV14: ArmÃ©nia | DW14: ÐÑ€Ð¼ÐµÐ½Ð¸Ñ | DX14: Armenien | DY14: Ermenistan | DZ14: Ð’Ñ–Ñ€Ð¼ÐµÐ½Ñ–Ñ | EA14: Ø¢Ø±Ù…ÛŒÙ†ÛŒØ§ | EB14: Armenia | EC14: äºšç¾Žå°¼äºš | ED14: äºžç¾Žå°¼äºž | EE14: Admin-0 country | EG14: Admin-0 country
A15: Aruba | B15: Admin-0 country | C15: 3 | D15: 5 | E15: Netherlands | F15: NL1 | G15: 1 | H15: 2 | I15: Country | J15: 1 | K15: Aruba | L15: ABW | M15: 0 | N15: Aruba | O15: ABW | P15: 0 | Q15: Aruba | R15: ABW | S15: 0 | T15: Aruba | U15: ABW | V15: Aruba | X15: Aruba | Y15: AW | Z15: Aruba | AB15: Aruba | AC15: Neth. | AE15: Aruba | AG15: 4 | AH15: 2 | AI15: 2 | AJ15: 9 | AK15: 106314 | AL15: 9 | AM15: 2019 | AN15: 3056 | AO15: 2017 | AP15: 6. Developing region | AQ15: 2. High income: nonOECD | AR15: AA | AS15: AW | AT15: AW | AU15: ABW | AV15: ABW | AW15: 533 | AX15: 533 | AY15: 533 | AZ15: AW | BA15: ABW | BB15: 23424736 | BC15: 23424736 | BD15: Exact WOE match as country | BE15: ABW | BG15: ABW | BH15: ABW | BI15: ABW | BJ15: ABW | BK15: ABW | BL15: ABW | BM15: ABW | BN15: ABW | BO15: ABW | BP15: ABW | BQ15: ABW | BR15: ABW | BS15: ABW | BT15: ABW | BU15: ABW | BV15: ABW | BW15: ABW | BX15: ABW | BY15: ABW | BZ15: ABW | CA15: ABW | CB15: ABW | CC15: ABW | CD15: ABW | CE15: ABW | CF15: ABW | CG15: ABW | CH15: ABW | CI15: ABW | CJ15: ABW | CK15: ABW | CL15: ABW | CM15: -99 | CN15: -99 | CO15: North America | CP15: Americas | CQ15: Caribbean | CR15: Latin America & Caribbean | CS15: 5 | CT15: 5 | CU15: 5 | CV15: 4 | CW15: -99 | CX15: 0 | CY15: 5 | CZ15: 10 | DA15: -69.972795 | DB15: 12.5174 | DC15: 1159321097 | DD15: Q21203 | DE15: Ø£Ø±ÙˆØ¨Ø§ | DF15: à¦†à¦°à§à¦¬à¦¾ | DG15: Aruba | DH15: Aruba | DI15: Aruba | DJ15: Ø¢Ø±ÙˆØ¨Ø§ | DK15: Aruba | DL15: Î‘ÏÎ¿ÏÎ¼Ï€Î± | DM15: ××¨×•×‘×” | DN15: à¤…à¤°à¥‚à¤¬à¤¾ | DO15: Aruba | DP15: Aruba | DQ15: Aruba | DR15: ã‚¢ãƒ«ãƒ | DS15: ì•„ë£¨ë°” | DT15: Aruba | DU15: Aruba | DV15: Aruba | DW15: ÐÑ€ÑƒÐ±Ð° | DX15: Aruba | DY15: Aruba | DZ15: ÐÑ€ÑƒÐ±Ð° | EA15: Ø§Ø±ÙˆØ¨Ø§ | EB15: Aruba | EC15: é˜¿é²å·´ | ED15: é˜¿é­¯å·´ | EE15: Admin-0 dependency | EG15: Admin-0 dependency
A16: Ashmore and Cartier Is. | B16: Admin-0 country | C16: 6 | D16: 5 | E16: Australia | F16: AU1 | G16: 1 | H16: 2 | I16: Dependency | J16: 1 | K16: Ashmore and Cartier Islands | L16: ATC | M16: 0 | N16: Ashmore and Cartier Islands | O16: ATC | P16: 0 | Q16: Ashmore and Cartier Islands | R16: ATC | S16: 0 | T16: Ashmore and Cartier Islands | U16: ATC | V16: Ashmore and Cartier Is. | X16: A.C.Is. | Y16: AU | Z16: Territory of Ashmore and Cartier Islands | AC16: Auz. | AE16: Ashmore and Cartier Islands | AG16: 1 | AH16: 2 | AI16: 2 | AJ16: 7 | AK16: 0 | AL16: 1 | AM16: 2019 | AN16: 0 | AO16: 2019 | AP16: 7. Least developed region | AQ16: 5. Low income | AR16: AT | AS16: -99 | AT16: AU | AU16: -99 | AV16: AUS | AW16: 36 | AX16: 36 | AY16: -99 | AZ16: -99 | BA16: -99 | BB16: 23424749 | BC16: 23424749 | BD16: WOE Admin-1 states provinces match. | BE16: AUS | BF16: 1 | BG16: ATC | BH16: ATC | BI16: ATC | BJ16: ATC | BK16: ATC | BL16: ATC | BM16: ATC | BN16: ATC | BO16: ATC | BP16: ATC | BQ16: ATC | BR16: ATC | BS16: ATC | BT16: ATC | BU16: ATC | BV16: ATC | BW16: ATC | BX16: ATC | BY16: ATC | BZ16: ATC | CA16: ATC | CB16: ATC | CC16: ATC | CD16: ATC | CE16: ATC | CF16: ATC | CG16: ATC | CH16: ATC | CI16: ATC | CJ16: ATC | CK16: ATC | CL16: ATC | CM16: -99 | CN16: -99 | CO16: Oceania | CP16: Oceania | CQ16: Australia and New Zealand | CR16: East Asia & Pacific | CS16: 23 | CT16: 27 | CU16: 7 | CV16: -99 | CW16: -99 | CX16: 0 | CY16: 4.5 | CZ16: 9.5 | DA16: 123.58637 | DB16: -12.432571 | DC16: 1159320353 | DD16: Q133888 | DE16: Ø¬Ø²Ø± Ø£Ø´Ù…ÙˆØ± ÙˆÙƒØ§Ø±ØªÙŠÙŠØ± | DF16: à¦†à¦¸à¦®à¦° à¦à¦¬à¦‚ à¦•à¦¾à¦°à§à¦Ÿà¦¿à¦¯à¦¼à§‡ à¦¦à§à¦¬à§€à¦ªà¦ªà§à¦žà§à¦œ | DG16: Ashmore- und Cartierinseln | DH16: Ashmore and Cartier Islands | DI16: Islas Ashmore y Cartier | DJ16: Ø¬Ø²ÛŒØ±Ù‡Ù‡Ø§ÛŒ Ø¢Ø´Ù…ÙˆØ± Ùˆ Ú©Ø§Ø±ØªÛŒØ± | DK16: ÃŽles Ashmore-et-Cartier | DL16: Î†ÏƒÎ¼Î¿Ï ÎºÎ±Î¹ ÎšÎ±ÏÏ„Î¹Î­ ÎÎ·ÏƒÎ¹Î¬ | DM16: ××™×™ ××©×ž×•×¨ ×•×§×¨×˜×™×™×” | DN16: à¤à¤¶à¤®à¥‹à¤° à¤”à¤° à¤•à¤¾à¤°à¥à¤Ÿà¤¿à¤¯à¤° à¤¦à¥à¤µà¥€à¤ª à¤¸à¤®à¥‚à¤¹ | DO16: Ashmore- Ã©s Cartier-szigetek | DP16: Kepulauan Ashmore dan Cartier | DQ16: Isole Ashmore e Cartier | DR16: ã‚¢ã‚·ãƒ¥ãƒ¢ã‚¢ãƒ»ã‚«ãƒ«ãƒ†ã‚£ã‚¨è«¸å³¶ | DS16: ì• ì‹œëª¨ì–´ ì¹´ë¥´í‹°ì— ì œë„ | DT16: Ashmore- en Cartiereilanden | DU16: Wyspy Ashmore i Cartiera | DV16: Ilhas Ashmore e Cartier | DW16: ÐžÑÑ‚Ñ€Ð¾Ð²Ð° ÐÑˆÐ¼Ð¾Ñ€ Ð¸ ÐšÐ°Ñ€Ñ‚ÑŒÐµ | DX16: Ashmore- och CartierÃ¶arna | DY16: Ashmore ve Cartier AdalarÄ± | DZ16: ÐžÑÑ‚Ñ€Ð¾Ð²Ð¸ ÐÑˆÐ¼Ð¾Ñ€ Ñ– ÐšÐ°Ñ€Ñ‚ÑŒÑ” | EA16: Ø¬Ø²Ø§Ø¦Ø± Ø§ÛŒØ´Ù…ÙˆØ± Ùˆ Ú©Ø§Ø±Ù¹ÛŒØ± | EB16: Quáº§n Ä‘áº£o Ashmore vÃ Cartier | EC16: é˜¿ä»€èŽ«å°”å’Œå¡æ·ç¾¤å²› | ED16: äºžä»€æ‘©åŠå¡åœ°çˆ¾ç¾¤å³¶ | EE16: Unrecognized | EF16: 1 | EG16: Admin-0 dependency
A17: Australia | B17: Admin-0 country | C17: 0 | D17: 2 | E17: Australia | F17: AU1 | G17: 1 | H17: 2 | I17: Country | J17: 1 | K17: Australia | L17: AUS | M17: 0 | N17: Australia | O17: AUS | P17: 0 | Q17: Australia | R17: AUS | S17: 0 | T17: Australia | U17: AUS | V17: Australia | X17: Auz. | Y17: AU | Z17: Commonwealth of Australia | AB17: Australia | AE17: Australia | AG17: 1 | AH17: 2 | AI17: 2 | AJ17: 7 | AK17: 25364307 | AL17: 15 | AM17: 2019 | AN17: 1396567 | AO17: 2019 | AP17: 2. Developed region: nonG7 | AQ17: 1. High income: OECD | AR17: AS | AS17: AU | AT17: AU | AU17: AUS | AV17: AUS | AW17: 36 | AX17: 36 | AY17: 36 | AZ17: AU | BA17: AUS | BB17: -90 | BC17: 23424748 | BD17: Includes Ashmore and Cartier Islands (23424749) and Coral Sea Islands (23424790). | BE17: AUS | BG17: AUS | BH17: AUS | BI17: AUS | BJ17: AUS | BK17: AUS | BL17: AUS | BM17: AUS | BN17: AUS | BO17: AUS | BP17: AUS | BQ17: AUS | BR17: AUS | BS17: AUS | BT17: AUS | BU17: AUS | BV17: AUS | BW17: AUS | BX17: AUS | BY17: AUS | BZ17: AUS | CA17: AUS | CB17: AUS | CC17: AUS | CD17: AUS | CE17: AUS | CF17: AUS | CG17: AUS | CH17: AUS | CI17: AUS | CJ17: AUS | CK17: AUS | CL17: AUS | CM17: -99 | CN17: -99 | CO17: Oceania | CP17: Oceania | CQ17: Australia and New Zealand | CR17: East Asia & Pacific | CS17: 9 | CT17: 9 | CU17: 4 | CV17: -99 | CW17: 1 | CX17: 0 | CY17: 1.7 | CZ17: 5.7 | DA17: 134.04972 | DB17: -24.129522 | DC17: 1159320355 | DD17: Q408 | DE17: Ø£Ø³ØªØ±Ø§Ù„ÙŠØ§ | DF17: à¦…à¦¸à§à¦Ÿà§à¦°à§‡à¦²à¦¿à¦¯à¦¼à¦¾ | DG17: Australien | DH17: Australia | DI17: Australia | DJ17: Ø§Ø³ØªØ±Ø§Ù„ÛŒØ§ | DK17: Australie | DL17: Î‘Ï…ÏƒÏ„ÏÎ±Î»Î¯Î± | DM17: ××•×¡×˜×¨×œ×™×” | DN17: à¤‘à¤¸à¥à¤Ÿà¥à¤°à¥‡à¤²à¤¿à¤¯à¤¾ | DO17: AusztrÃ¡lia | DP17: Australia | DQ17: Australia | DR17: ã‚ªãƒ¼ã‚¹ãƒˆãƒ©ãƒªã‚¢ | DS17: ì˜¤ìŠ¤íŠ¸ë ˆì¼ë¦¬ì•„ | DT17: AustraliÃ« | DU17: Australia | DV17: AustrÃ¡lia | DW17: ÐÐ²ÑÑ‚Ñ€Ð°Ð»Ð¸Ñ | DX17: Australien | DY17: Avustralya | DZ17: ÐÐ²ÑÑ‚Ñ€Ð°Ð»Ñ–Ñ | EA17: Ø¢Ø³Ù¹Ø±ÛŒÙ„ÛŒØ§ | EB17: Ãšc | EC17: æ¾³å¤§åˆ©äºš | ED17: æ¾³å¤§åˆ©äºž | EE17: Admin-0 country | EG17: Admin-0 country
A18: Austria | B18: Admin-0 country | C18: 0 | D18: 4 | E18: Austria | F18: AUT | G18: 0 | H18: 2 | I18: Sovereign country | J18: 1 | K18: Austria | L18: AUT | M18: 0 | N18: Austria | O18: AUT | P18: 0 | Q18: Austria | R18: AUT | S18: 0 | T18: Austria | U18: AUT | V18: Austria | X18: Aust. | Y18: A | Z18: Republic of Austria | AB18: Austria | AE18: Austria | AG18: 3 | AH18: 1 | AI18: 3 | AJ18: 4 | AK18: 8877067 | AL18: 13 | AM18: 2019 | AN18: 445075 | AO18: 2019 | AP18: 2. Developed region: nonG7 | AQ18: 1. High income: OECD | AR18: AU | AS18: AT | AT18: AT | AU18: AUT | AV18: AUT | AW18: 40 | AX18: 40 | AY18: 40 | AZ18: AT | BA18: AUT | BB18: 23424750 | BC18: 23424750 | BD18: Exact WOE match as country | BE18: AUT | BG18: AUT | BH18: AUT | BI18: AUT | BJ18: AUT | BK18: AUT | BL18: AUT | BM18: AUT | BN18: AUT | BO18: AUT | BP18: AUT | BQ18: AUT | BR18: AUT | BS18: AUT | BT18: AUT | BU18: AUT | BV18: AUT | BW18: AUT | BX18: AUT | BY18: AUT | BZ18: AUT | CA18: AUT | CB18: AUT | CC18: AUT | CD18: AUT | CE18: AUT | CF18: AUT | CG18: AUT | CH18: AUT | CI18: AUT | CJ18: AUT | CK18: AUT | CL18: AUT | CM18: -99 | CN18: -99 | CO18: Europe | CP18: Europe | CQ18: Western Europe | CR18: Europe & Central Asia | CS18: 7 | CT18: 7 | CU18: 5 | CV18: -99 | CW18: 1 | CX18: 0 | CY18: 3 | CZ18: 8 | DA18: 14.130515 | DB18: 47.518859 | DC18: 1159320379 | DD18: Q40 | DE18: Ø§Ù„Ù†Ù…Ø³Ø§ | DF18: à¦…à¦¸à§à¦Ÿà§à¦°à¦¿à¦¯à¦¼à¦¾ | DG18: Ã–sterreich | DH18: Austria | DI18: Austria | DJ18: Ø§ØªØ±ÛŒØ´ | DK18: Autriche | DL18: Î‘Ï…ÏƒÏ„ÏÎ¯Î± | DM18: ××•×¡×˜×¨×™×” | DN18: à¤‘à¤¸à¥à¤Ÿà¥à¤°à¤¿à¤¯à¤¾ | DO18: Ausztria | DP18: Austria | DQ18: Austria | DR18: ã‚ªãƒ¼ã‚¹ãƒˆãƒªã‚¢ | DS18: ì˜¤ìŠ¤íŠ¸ë¦¬ì•„ | DT18: Oostenrijk | DU18: Austria | DV18: Ãustria | DW18: ÐÐ²ÑÑ‚Ñ€Ð¸Ñ | DX18: Ã–sterrike | DY18: Avusturya | DZ18: ÐÐ²ÑÑ‚Ñ€Ñ–Ñ | EA18: Ø¢Ø³Ù¹Ø±ÛŒØ§ | EB18: Ão | EC18: å¥¥åœ°åˆ© | ED18: å¥§åœ°åˆ© | EE18: Admin-0 country | EG18: Admin-0 country
A19: Azerbaijan | B19: Admin-0 country | C19: 0 | D19: 5 | E19: Azerbaijan | F19: AZE | G19: 0 | H19: 2 | I19: Sovereign country | J19: 1 | K19: Azerbaijan | L19: AZE | M19: 0 | N19: Azerbaijan | O19: AZE | P19: 0 | Q19: Azerbaijan | R19: AZE | S19: 0 | T19: Azerbaijan | U19: AZE | V19: Azerbaijan | X19: Aze. | Y19: AZ | Z19: Republic of Azerbaijan | AB19: Azerbaijan | AE19: Azerbaijan | AG19: 1 | AH19: 6 | AI19: 5 | AJ19: 8 | AK19: 10023318 | AL19: 14 | AM19: 2019 | AN19: 48047 | AO19: 2019 | AP19: 6. Developing region | AQ19: 3. Upper middle income | AR19: AJ | AS19: AZ | AT19: AZ | AU19: AZE | AV19: AZE | AW19: 31 | AX19: 31 | AY19: 31 | AZ19: AZ | BA19: AZE | BB19: 23424741 | BC19: 23424741 | BD19: Exact WOE match as country | BE19: AZE | BG19: AZE | BH19: AZE | BI19: AZE | BJ19: AZE | BK19: AZE | BL19: AZE | BM19: AZE | BN19: AZE | BO19: AZE | BP19: AZE | BQ19: AZE | BR19: AZE | BS19: AZE | BT19: AZE | BU19: AZE | BV19: AZE | BW19: AZE | BX19: AZE | BY19: AZE | BZ19: AZE | CA19: AZE | CB19: AZE | CC19: AZE | CD19: AZE | CE19: AZE | CF19: AZE | CG19: AZE | CH19: AZE | CI19: AZE | CJ19: AZE | CK19: AZE | CL19: AZE | CM19: -99 | CN19: -99 | CO19: Asia | CP19: Asia | CQ19: Western Asia | CR19: Europe & Central Asia | CS19: 10 | CT19: 10 | CU19: 4 | CV19: -99 | CW19: 1 | CX19: 0 | CY19: 4 | CZ19: 9 | DA19: 47.210994 | DB19: 40.402387 | DC19: 1159320381 | DD19: Q227 | DE19: Ø£Ø°Ø±Ø¨ÙŠØ¬Ø§Ù† | DF19: à¦†à¦œà¦¾à¦°à¦¬à¦¾à¦‡à¦œà¦¾à¦¨ | DG19: Aserbaidschan | DH19: Azerbaijan | DI19: AzerbaiyÃ¡n | DJ19: Ø¬Ù…Ù‡ÙˆØ±ÛŒ Ø¢Ø°Ø±Ø¨Ø§ÛŒØ¬Ø§Ù† | DK19: AzerbaÃ¯djan | DL19: Î‘Î¶ÎµÏÎ¼Ï€Î±ÏŠÏ„Î¶Î¬Î½ | DM19: ××–×¨×‘×™×™×’'×Ÿ | DN19: à¤…à¤œà¤¼à¤°à¤¬à¥ˆà¤œà¤¾à¤¨ | DO19: AzerbajdzsÃ¡n | DP19: Azerbaijan | DQ19: Azerbaigian | DR19: ã‚¢ã‚¼ãƒ«ãƒã‚¤ã‚¸ãƒ£ãƒ³ | DS19: ì•„ì œë¥´ë°”ì´ìž” | DT19: Azerbeidzjan | DU19: AzerbejdÅ¼an | DV19: AzerbaijÃ£o | DW19: ÐÐ·ÐµÑ€Ð±Ð°Ð¹Ð´Ð¶Ð°Ð½ | DX19: Azerbajdzjan | DY19: Azerbaycan | DZ19: ÐÐ·ÐµÑ€Ð±Ð°Ð¹Ð´Ð¶Ð°Ð½ | EA19: Ø¢Ø°Ø±Ø¨Ø§Ø¦ÛŒØ¬Ø§Ù† | EB19: Azerbaijan | EC19: é˜¿å¡žæ‹œç–† | ED19: äºžå¡žæ‹œç„¶ | EE19: Admin-0 country | EG19: Admin-0 country
A20: Azores | B20: Admin-1 states provinces | C20: 7 | L20: PT-20 | FN20: PRT-735 | FO20: 735 | FQ20: PT | FR20: 3 | FS20: AÃ§ores | FU20: RegiÃµes autÃ´noma | FV20: Autonomous region | FX20: PT.AC | GB20: 3 | GC20: 1 | GD20: 0 | GE20: 6 | GG20: AC | GH20: 0 | GI20: -99 | GJ20: 7 | GK20: 6 | GL20: 1 | GM20: 4 | GN20: PO23 | GP20: 15021776 | GQ20: Azores, PT, Portugal | GR20: Azores | GS20: 38.6351 | GT20: -28.0394 | GU20: PRT | GV20: PT-20 | GW20: 5 | GX20: Portugal | GY20: Azores | GZ20: PAZ | HA20: 3411865 | HB20: Regiao Autonoma dos Acores | HC20: 6133108 | HD20: Acores, Regiao Autonoma dos | HE20: 1 | HG20: PT.23 | HJ20: 1 | HL20: PO23 | HN20: 8 | HO20: 11 | HP20: 7.7 | HQ20: Q25263 | HR20: Ø§Ù„Ø£Ø²ÙˆØ± | HS20: à¦…à§à¦¯à¦¾à¦œà§‹à¦°à§‡à¦¸ | HT20: Azoren | HU20: Azores | HV20: Azores | HW20: AÃ§ores | HX20: Î‘Î¶ÏŒÏÎµÏ‚ | HY20: à¤à¤œà¤¼à¥‹à¤°à¥‡à¤¸ | HZ20: Azori-szigetek | IA20: Azores | IB20: Azzorre | IC20: ã‚¢ã‚¾ãƒ¬ã‚¹è«¸å³¶ | ID20: ì•„ì†Œë¥´ìŠ¤ ì œë„ | IE20: Azoren | IF20: Azory | IG20: AÃ§ores | IH20: ÐÐ·Ð¾Ñ€ÑÐºÐ¸Ðµ Ð¾ÑÑ‚Ñ€Ð¾Ð²Ð° | II20: Azorerna | IJ20: Azorlar | IK20: AÃ§ores | IL20: äºšé€Ÿå°”ç¾¤å²› | IM20: 1159310543 | IN20: ×”××™×™× ×”××–×•×¨×™×™× | IO20: ÐÐ·Ð¾Ñ€ÑÑŒÐºÑ– Ð¾ÑÑ‚Ñ€Ð¾Ð²Ð¸ | IP20: Ø¢Ø²ÙˆØ±Ø³ | IQ20: Ø¢Ø²ÙˆØ± | IR20: äºžé€Ÿç¾¤å³¶
A21: Bahamas | B21: Admin-0 country | C21: 3 | D21: 4 | E21: The Bahamas | F21: BHS | G21: 0 | H21: 2 | I21: Sovereign country | J21: 1 | K21: The Bahamas | L21: BHS | M21: 0 | N21: The Bahamas | O21: BHS | P21: 0 | Q21: The Bahamas | R21: BHS | S21: 0 | T21: Bahamas | U21: BHS | V21: Bahamas | X21: Bhs. | Y21: BS | Z21: Commonwealth of the Bahamas | AB21: Bahamas, The | AE21: Bahamas, The | AG21: 1 | AH21: 1 | AI21: 2 | AJ21: 5 | AK21: 389482 | AL21: 10 | AM21: 2019 | AN21: 13578 | AO21: 2019 | AP21: 6. Developing region | AQ21: 2. High income: nonOECD | AR21: BF | AS21: BS | AT21: BS | AU21: BHS | AV21: BHS | AW21: 44 | AX21: 44 | AY21: 44 | AZ21: BS | BA21: BHS | BB21: 23424758 | BC21: 23424758 | BD21: Exact WOE match as country | BE21: BHS | BG21: BHS | BH21: BHS | BI21: BHS | BJ21: BHS | BK21: BHS | BL21: BHS | BM21: BHS | BN21: BHS | BO21: BHS | BP21: BHS | BQ21: BHS | BR21: BHS | BS21: BHS | BT21: BHS | BU21: BHS | BV21: BHS | BW21: BHS | BX21: BHS | BY21: BHS | BZ21: BHS | CA21: BHS | CB21: BHS | CC21: BHS | CD21: BHS | CE21: BHS | CF21: BHS | CG21: BHS | CH21: BHS | CI21: BHS | CJ21: BHS | CK21: BHS | CL21: BHS | CM21: -99 | CN21: -99 | CO21: North America | CP21: Americas | CQ21: Caribbean | CR21: Latin America & Caribbean | CS21: 7 | CT21: 7 | CU21: 4 | CV21: -99 | CW21: 1 | CX21: 0 | CY21: 4 | CZ21: 9 | DA21: -77.146688 | DB21: 26.401789 | DC21: 1159320415 | DD21: Q778 | DE21: Ø¨Ø§Ù‡Ø§Ù…Ø§Ø³ | DF21: à¦¬à¦¾à¦¹à¦¾à¦®à¦¾ à¦¦à§à¦¬à§€à¦ªà¦ªà§à¦žà§à¦œ | DG21: Bahamas | DH21: The Bahamas | DI21: Bahamas | DJ21: Ø¨Ø§Ù‡Ø§Ù…Ø§ | DK21: Bahamas | DL21: ÎœÏ€Î±Ï‡Î¬Î¼ÎµÏ‚ | DM21: ××™×™ ×‘×”××ž×” | DN21: à¤¬à¤¹à¤¾à¤®à¤¾à¤¸ | DO21: Bahama-szigetek | DP21: Bahama | DQ21: Bahamas | DR21: ãƒãƒãƒž | DS21: ë°”í•˜ë§ˆ | DT21: Bahama's | DU21: Bahamy | DV21: Bahamas | DW21: Ð‘Ð°Ð³Ð°Ð¼ÑÐºÐ¸Ðµ ÐžÑÑ‚Ñ€Ð¾Ð²Ð° | DX21: Bahamas | DY21: Bahamalar | DZ21: Ð‘Ð°Ð³Ð°Ð¼ÑÑŒÐºÑ– ÐžÑÑ‚Ñ€Ð¾Ð²Ð¸ | EA21: Ø¨ÛØ§Ù…Ø§Ø³ | EB21: Bahamas | EC21: å·´å“ˆé©¬ | ED21: å·´å“ˆé¦¬ | EE21: Admin-0 country | EG21: Admin-0 country
A22: Bahrain | B22: Admin-0 country | C22: 5 | D22: 4 | E22: Bahrain | F22: BHR | G22: 0 | H22: 2 | I22: Sovereign country | J22: 1 | K22: Bahrain | L22: BHR | M22: 0 | N22: Bahrain | O22: BHR | P22: 0 | Q22: Bahrain | R22: BHR | S22: 0 | T22: Bahrain | U22: BHR | V22: Bahrain | X22: Bahr. | Y22: BH | Z22: Kingdom of Bahrain | AB22: Bahrain | AE22: Bahrain | AG22: 1 | AH22: 1 | AI22: 1 | AJ22: 9 | AK22: 1641172 | AL22: 12 | AM22: 2019 | AN22: 38574 | AO22: 2019 | AP22: 6. Developing region | AQ22: 2. High income: nonOECD | AR22: BA | AS22: BH | AT22: BH | AU22: BHR | AV22: BHR | AW22: 48 | AX22: 48 | AY22: 48 | AZ22: BH | BA22: BHR | BB22: 23424753 | BC22: 23424753 | BD22: Exact WOE match as country | BE22: BHR | BG22: BHR | BH22: BHR | BI22: BHR | BJ22: BHR | BK22: BHR | BL22: BHR | BM22: BHR | BN22: BHR | BO22: BHR | BP22: BHR | BQ22: BHR | BR22: BHR | BS22: BHR | BT22: BHR | BU22: BHR | BV22: BHR | BW22: BHR | BX22: BHR | BY22: BHR | BZ22: BHR | CA22: BHR | CB22: BHR | CC22: BHR | CD22: BHR | CE22: BHR | CF22: BHR | CG22: BHR | CH22: BHR | CI22: BHR | CJ22: BHR | CK22: BHR | CL22: BHR | CM22: -99 | CN22: -99 | CO22: Asia | CP22: Asia | CQ22: Western Asia | CR22: Middle East & North Africa | CS22: 7 | CT22: 7 | CU22: 5 | CV22: 2 | CW22: 1 | CX22: 0 | CY22: 4 | CZ22: 9 | DA22: 50.554816 | DB22: 26.055972 | DC22: 1159320413 | DD22: Q398 | DE22: Ø§Ù„Ø¨Ø­Ø±ÙŠÙ† | DF22: à¦¬à¦¾à¦¹à¦°à¦¾à¦‡à¦¨ | DG22: Bahrain | DH22: Bahrain | DI22: BarÃ©in | DJ22: Ø¨Ø­Ø±ÛŒÙ† | DK22: BahreÃ¯n | DL22: ÎœÏ€Î±Ï‡ÏÎ­Î¹Î½ | DM22: ×‘×—×¨×™×™×Ÿ | DN22: à¤¬à¤¹à¤°à¥€à¤¨ | DO22: Bahrein | DP22: Bahrain | DQ22: Bahrein | DR22: ãƒãƒ¼ãƒ¬ãƒ¼ãƒ³ | DS22: ë°”ë ˆì¸ | DT22: Bahrein | DU22: Bahrajn | DV22: Bahrein | DW22: Ð‘Ð°Ñ…Ñ€ÐµÐ¹Ð½ | DX22: Bahrain | DY22: Bahreyn | DZ22: Ð‘Ð°Ñ…Ñ€ÐµÐ¹Ð½ | EA22: Ø¨Ø­Ø±ÛŒÙ† | EB22: Bahrain | EC22: å·´æž— | ED22: å·´æž— | EE22: Admin-0 country | EG22: Admin-0 country
A23: Baikonur | B23: Admin-0 country | C23: 0 | D23: 5 | E23: Kazakhstan | F23: KA1 | G23: 1 | H23: 2 | I23: Lease | J23: 1 | K23: Baykonur Cosmodrome | L23: KAB | M23: 0 | N23: Baykonur Cosmodrome | O23: KAB | P23: 0 | Q23: Baykonur Cosmodrome | R23: KAB | S23: 1 | T23: Baikonur Cosmodrome | U23: B40 | V23: Baykonur | X23: Bayk. | Y23: BK | AC23: Russia | AD23: Leased to Russia by Kazakhstan | AE23: Baikonur Cosmodrome | AF23: Baykonur Cosmodrome | AG23: 6 | AH23: 1 | AI23: 6 | AJ23: 1 | AK23: 36175 | AL23: 7 | AM23: 2009 | AN23: 596 | AO23: 2013 | AP23: 2. Developed region: nonG7 | AQ23: 3. Upper middle income | AR23: -99 | AS23: -99 | AT23: KZ | AU23: -99 | AV23: KAZ | AW23: -99 | AX23: 398 | AY23: -99 | AZ23: -99 | BA23: -99 | BB23: -90 | BC23: 20070177 | BD23: A subunit of Kazakhstan in WOE. | BE23: KAZ | BF23: 1 | BG23: B40 | BH23: KAZ | BI23: KAZ | BJ23: KAZ | BK23: KAZ | BL23: KAZ | BM23: KAZ | BN23: KAZ | BO23: KAZ | BP23: KAZ | BQ23: KAZ | BR23: KAZ | BS23: KAZ | BT23: KAZ | BU23: KAZ | BV23: KAZ | BW23: KAZ | BX23: KAZ | BY23: KAZ | BZ23: KAZ | CA23: KAZ | CB23: KAZ | CC23: KAZ | CD23: KAZ | CE23: KAZ | CF23: KAZ | CG23: KAZ | CH23: KAZ | CI23: KAZ | CJ23: KAZ | CK23: KAZ | CL23: KAZ | CM23: -99 | CN23: -99 | CO23: Asia | CP23: Asia | CQ23: Central Asia | CR23: Europe & Central Asia | CS23: 8 | CT23: 19 | CU23: 5 | CV23: -99 | CW23: -99 | CX23: 5 | CY23: 6 | CZ23: 9.5 | DA23: 63.383897 | DB23: 45.978332 | DC23: 1159320965 | DD23: Q165413 | DE23: Ø¨Ø§ÙŠÙƒÙˆÙ†ÙˆØ± | DF23: à¦¬à¦¾à¦‡à¦•à§à¦¨à§‹à¦° | DG23: Baikonur | DH23: Baikonur | DI23: Baikonur | DJ23: Ø¨Ø§ÛŒÙ‚ÙˆÙ†ÙˆØ±ØŒ Ù‚Ø²Ø§Ù‚Ø³ØªØ§Ù† | DK23: BaÃ¯konour | DL23: ÎœÏ€Î±ÏŠÎºÎ¿Î½Î¿ÏÏ | DM23: ×‘×™×™×§×•× ×•×¨ | DN23: à¤¬à¤¾à¤¯à¤•à¥‹à¤¨à¥‚à¤° | DO23: Bajkonur | DP23: Baykonur | DQ23: BayqoÃ±yr | DR23: ãƒã‚¤ã‚³ãƒŒãƒ¼ãƒ« | DS23: ë°”ì´ì½”ëˆ„ë¥´ | DT23: Bajkonoer | DU23: Bajkonur | DV23: Baikonur | DW23: Ð‘Ð°Ð¹ÐºÐ¾Ð½ÑƒÑ€ | DX23: Bajkonur | DY23: Baykonur | DZ23: Ð‘Ð°Ð¹ÐºÐ¾Ð½Ð¸Ñ€ | EA23: Ø¨Ø§ÛŒÚ©ÙˆÙ†ÙˆØ± | EB23: Baikonur | EC23: æ‹œç§‘åŠªå°” | ED23: æ‹œç§‘åŠªçˆ¾ | EE23: Unrecognized | EF23: 1 | EG23: Admin-0 lease | EH23: Admin-0 lease | EI23: Unrecognized | EJ23: Unrecognized | EK23: Unrecognized | EL23: Unrecognized | EM23: Unrecognized | EN23: Unrecognized | EO23: Unrecognized | EP23: Unrecognized | EQ23: Unrecognized | ER23: Unrecognized | ES23: Unrecognized | ET23: Unrecognized | EU23: Unrecognized | EV23: Unrecognized | EW23: Unrecognized | EX23: Unrecognized | EY23: Unrecognized | EZ23: Unrecognized | FA23: Unrecognized | FB23: Unrecognized | FC23: Unrecognized | FD23: Unrecognized | FE23: Unrecognized | FF23: Unrecognized | FG23: Unrecognized | FH23: Unrecognized | FI23: Unrecognized | FJ23: Unrecognized | FK23: Unrecognized | FL23: Unrecognized
A24: Bajo Nuevo Bank | B24: Admin-0 country | C24: 6 | D24: 8 | E24: Bajo Nuevo Bank (Petrel Is.) | F24: BJN | G24: 0 | H24: 2 | I24: Indeterminate | J24: 1 | K24: Bajo Nuevo Bank (Petrel Is.) | L24: BJN | M24: 0 | N24: Bajo Nuevo Bank (Petrel Is.) | O24: BJN | P24: 0 | Q24: Bajo Nuevo Bank (Petrel Is.) | R24: BJN | S24: 1 | T24: Bajo Nuevo Bank (Petrel Islands) | U24: B41 | V24: Bajo Nuevo Bank (Petrel Is.) | AC24: Disputed | AD24: Claimed by Colombia, Jamaica, Nicaragua and the United States | AE24: Bajo Nuevo Bank (Petrel Is.) | AG24: 3 | AH24: 7 | AI24: 6 | AJ24: -99 | AK24: 0 | AL24: 1 | AM24: 2019 | AN24: 0 | AO24: 2019 | AP24: 7. Least developed region | AQ24: 5. Low income | AR24: -99 | AS24: -99 | AT24: -99 | AU24: -99 | AV24: -99 | AW24: -99 | AX24: -99 | AY24: -99 | AZ24: -99 | BA24: -99 | BB24: -99 | BC24: -99 | BD24: No WOE equivalent. | BE24: -99 | BF24: 1 | BG24: B41 | BH24: USA | BI24: COL | BJ24: COL | BK24: COL | BL24: COL | BM24: COL | BN24: COL | BO24: COL | BP24: COL | BQ24: COL | BR24: COL | BS24: COL | BT24: COL | BU24: COL | BV24: COL | BW24: COL | BX24: COL | BY24: COL | BZ24: COL | CA24: COL | CB24: COL | CC24: COL | CD24: COL | CE24: COL | CF24: COL | CG24: COL | CH24: COL | CI24: COL | CJ24: COL | CK24: COL | CL24: COL | CM24: -99 | CN24: -99 | CO24: North America | CP24: Americas | CQ24: Caribbean | CR24: Latin America & Caribbean | CS24: 15 | CT24: 32 | CU24: 0 | CV24: -99 | CW24: 1 | CX24: 7 | CY24: 7 | CZ24: 11 | DA24: -79.845836 | DB24: 15.791588 | DC24: 1159320425 | DD24: Q1257783 | DE24: Ø¶ÙØ© Ø¨Ø§Ø¬Ùˆ Ù†ÙŠÙˆÙÙˆ | DF24: à¦¬à¦¾à¦¹à§‹ à¦¨à§à¦¯à¦¼à§‡à¦¬à§‹ à¦¤à§€à¦° | DG24: Bajo-Nuevo-Bank | DH24: Bajo Nuevo Bank | DI24: Bajo Nuevo | DJ24: Ø¨Ø§Ø¬Ùˆ Ù†ÙˆØ¦Ùˆ Ø¨Ù†Ú© (Petrel Is.) | DK24: Banc de Bajo Nuevo | DL24: ÎœÏ€Î¬Ï„Î¶Î¿ ÎÎ¿Ï…Î­Î²Î¿ ÎœÏ€Î±Î½Îº | DM24: ×‘××—×• × ×•××‘×• ×‘×× ×§ | DN24: à¤¬à¤¾à¤–à¥‹ à¤¨à¥à¤¯à¥à¤à¤µà¥‹ à¤¤à¤Ÿ | DO24: Petrel-szigetek | DP24: Tepi Bajo Nuevo | DQ24: Bajo Nuevo Bank | DR24: ãƒãƒ›ãƒŒã‚¨ãƒœ | DS24: ë°”í˜¸ ëˆ„ì—ë³´ ë±…í¬ | DT24: Bajo Nuevo | DU24: Bajo Nuevo | DV24: Ilha Baixo Novo | DW24: Ð‘Ð°Ñ…Ð¾-ÐÑƒÑÐ²Ð¾ | DX24: Bajo Nuevo | DY24: Bajo Nuevo Bank | DZ24: Ð‘Ð°Ñ…Ð¾-ÐÑƒÐµÐ²Ð¾ | EA24: Ø¨Ø§Ø®Ùˆ Ù†ÙˆØ¦ÙˆÙˆ Ú©Ù†Ø§Ø±Û | EB24: Bajo Nuevo Bank | EC24: å·´éœåŠªåŸƒæ²ƒæµ…æ»© | ED24: å·´éœåŠªåŸƒæ²ƒæ·ºç˜ | EE24: Unrecognized | EF24: 1 | EG24: Admin-0 indeterminant | EH24: Unrecognized | EI24: Unrecognized | EJ24: Unrecognized | EK24: Unrecognized | EL24: Unrecognized | EM24: Unrecognized | EN24: Unrecognized | EO24: Unrecognized | EP24: Unrecognized | EQ24: Unrecognized | ER24: Unrecognized | ES24: Unrecognized | ET24: Unrecognized | EU24: Unrecognized | EV24: Unrecognized | EW24: Unrecognized | EX24: Unrecognized | EY24: Unrecognized | EZ24: Unrecognized | FA24: Unrecognized | FB24: Unrecognized | FC24: Unrecognized | FD24: Unrecognized | FE24: Unrecognized | FF24: Unrecognized | FG24: Unrecognized | FH24: Unrecognized | FI24: Unrecognized | FJ24: Unrecognized | FK24: Unrecognized | FL24: Unrecognized
A25: Baleares | B25: Admin-1 states provinces | C25: 3 | L25: ES-PM | FN25: ESP-5808 | FO25: 5808 | FQ25: ES | FR25: 6 | FU25: Comunidad AutÃ³noma | FV25: Autonomous Community | FX25: ES.PM | GA25: Islas Baleares | GB25: 1 | GC25: 1 | GD25: 20 | GE25: 3 | GG25: PM | GH25: 0 | GI25: -99 | GJ25: 3 | GK25: 8 | GL25: 5 | GM25: 5 | GN25: SP07 | GP25: 12602088 | GQ25: Balearic Islands, ES, Spain | GR25: Islas Baleares | GS25: 39.6162 | GT25: 2.99156 | GU25: ESP | GV25: ES-PM | GW25: 3 | GX25: Spain | HA25: 6424360 | HB25: Illes Balears | HC25: -372237 | HD25: Islas Baleares, Comunidad Autonoma de las | HE25: 2 | HG25: ES.PM | HJ25: 1 | HM25: SP07 | HN25: 7.7 | HO25: 11 | HP25: 7.7 | HQ25: Q5765 | HR25: Ø¬Ø²Ø± Ø§Ù„Ø¨Ù„ÙŠØ§Ø± | HS25: à¦¬à¦¾à¦²à§‡à¦¯à¦¼à¦¾à¦° à¦¦à§à¦¬à§€à¦ªà¦ªà§à¦žà§à¦œ | HT25: Balearische Inseln | HU25: Balearic Islands | HV25: Islas Baleares | HW25: ÃŽles BalÃ©ares | HX25: Î’Î±Î»ÎµÎ±ÏÎ¯Î´ÎµÏ‚ ÎÎ®ÏƒÎ¿Î¹ | HY25: à¤¬à¥ˆà¤²à¥‡à¤°à¤¿à¤• à¤¦à¥à¤µà¥€à¤ªà¤¸à¤®à¥‚à¤¹ | HZ25: BaleÃ¡r-szigetek | IA25: Kepulauan Balears | IB25: isole Baleari | IC25: ãƒãƒ¬ã‚¢ãƒ¬ã‚¹è«¸å³¶ | ID25: ë°œë ˆì•„ë ˆìŠ¤ ì œë„ | IE25: Balearen | IF25: Baleary | IG25: Ilhas Baleares | IH25: Ð‘Ð°Ð»ÐµÐ°Ñ€ÑÐºÐ¸Ðµ Ð¾ÑÑ‚Ñ€Ð¾Ð²Ð° | II25: Balearerna | IJ25: Balear AdalarÄ± | IK25: Quáº§n Ä‘áº£o Baleares | IL25: å·´åˆ©é˜¿é‡Œç¾¤å²› | IM25: 1159308465 | IN25: ×”××™×™× ×”×‘×œ××¨×™×™× | IO25: Ð‘Ð°Ð»ÐµÐ°Ñ€ÑÑŒÐºÑ– Ð¾ÑÑ‚Ñ€Ð¾Ð²Ð¸ | IP25: Ø¬Ø²Ø§Ø¦Ø± Ø¨Ù„ÛŒØ¨Ø§Ø± | IQ25: Ø¬Ø²Ø§ÛŒØ± Ø¨Ø§Ù„Ø¦Ø§Ø±ÛŒ | IR25: å·´åˆ©äºžåˆ©ç¾¤å³¶ | IS25: ES.PM
A26: Bangladesh | B26: Admin-0 country | C26: 0 | D26: 3 | E26: Bangladesh | F26: BGD | G26: 0 | H26: 2 | I26: Sovereign country | J26: 1 | K26: Bangladesh | L26: BGD | M26: 0 | N26: Bangladesh | O26: BGD | P26: 0 | Q26: Bangladesh | R26: BGD | S26: 0 | T26: Bangladesh | U26: BGD | V26: Bangladesh | X26: Bang. | Y26: BD | Z26: People's Republic of Bangladesh | AB26: Bangladesh | AE26: Bangladesh | AG26: 3 | AH26: 4 | AI26: 7 | AJ26: 7 | AK26: 163046161 | AL26: 17 | AM26: 2019 | AN26: 302571 | AO26: 2019 | AP26: 7. Least developed region | AQ26: 5. Low income | AR26: BG | AS26: BD | AT26: BD | AU26: BGD | AV26: BGD | AW26: 50 | AX26: 50 | AY26: 50 | AZ26: BD | BA26: BGD | BB26: 23424759 | BC26: 23424759 | BD26: Exact WOE match as country | BE26: BGD | BG26: BGD | BH26: BGD | BI26: BGD | BJ26: BGD | BK26: BGD | BL26: BGD | BM26: BGD | BN26: BGD | BO26: BGD | BP26: BGD | BQ26: BGD | BR26: BGD | BS26: BGD | BT26: BGD | BU26: BGD | BV26: BGD | BW26: BGD | BX26: BGD | BY26: BGD | BZ26: BGD | CA26: BGD | CB26: BGD | CC26: BGD | CD26: BGD | CE26: BGD | CF26: BGD | CG26: BGD | CH26: BGD | CI26: BGD | CJ26: BGD | CK26: BGD | CL26: BGD | CM26: -99 | CN26: -99 | CO26: Asia | CP26: Asia | CQ26: Southern Asia | CR26: South Asia | CS26: 10 | CT26: 10 | CU26: 5 | CV26: -99 | CW26: 1 | CX26: 0 | CY26: 3 | CZ26: 8 | DA26: 89.684963 | DB26: 24.214956 | DC26: 1159320407 | DD26: Q902 | DE26: Ø¨Ù†ØºÙ„Ø§Ø¯ÙŠØ´ | DF26: à¦¬à¦¾à¦‚à¦²à¦¾à¦¦à§‡à¦¶ | DG26: Bangladesch | DH26: Bangladesh | DI26: BangladÃ©s | DJ26: Ø¨Ù†Ú¯Ù„Ø§Ø¯Ø´ | DK26: Bangladesh | DL26: ÎœÏ€Î±Î½Î³ÎºÎ»Î±Î½Ï„Î­Ï‚ | DM26: ×‘× ×’×œ×“×© | DN26: à¤¬à¤¾à¤‚à¤—à¥à¤²à¤¾à¤¦à¥‡à¤¶ | DO26: Banglades | DP26: Bangladesh | DQ26: Bangladesh | DR26: ãƒãƒ³ã‚°ãƒ©ãƒ‡ã‚·ãƒ¥ | DS26: ë°©ê¸€ë¼ë°ì‹œ | DT26: Bangladesh | DU26: Bangladesz | DV26: Bangladesh | DW26: Ð‘Ð°Ð½Ð³Ð»Ð°Ð´ÐµÑˆ | DX26: Bangladesh | DY26: BangladeÅŸ | DZ26: Ð‘Ð°Ð½Ð³Ð»Ð°Ð´ÐµÑˆ | EA26: Ø¨Ù†Ú¯Ù„Û Ø¯ÛŒØ´ | EB26: Bangladesh | EC26: å­ŸåŠ æ‹‰å›½ | ED26: å­ŸåŠ æ‹‰ | EE26: Admin-0 country | EG26: Admin-0 country
A27: Barbados | B27: Admin-0 country | C27: 3 | D27: 5 | E27: Barbados | F27: BRB | G27: 0 | H27: 2 | I27: Sovereign country | J27: 1 | K27: Barbados | L27: BRB | M27: 0 | N27: Barbados | O27: BRB | P27: 0 | Q27: Barbados | R27: BRB | S27: 0 | T27: Barbados | U27: BRB | V27: Barbados | X27: Barb. | Y27: BB | Z27: Barbados | AB27: Barbados | AE27: Barbados | AG27: 4 | AH27: 1 | AI27: 5 | AJ27: 3 | AK27: 287025 | AL27: 10 | AM27: 2019 | AN27: 5209 | AO27: 2019 | AP27: 6. Developing region | AQ27: 2. High income: nonOECD | AR27: BB | AS27: BB | AT27: BB | AU27: BRB | AV27: BRB | AW27: 52 | AX27: 52 | AY27: 52 | AZ27: BB | BA27: BRB | BB27: 23424754 | BC27: 23424754 | BD27: Exact WOE match as country | BE27: BRB | BG27: BRB | BH27: BRB | BI27: BRB | BJ27: BRB | BK27: BRB | BL27: BRB | BM27: BRB | BN27: BRB | BO27: BRB | BP27: BRB | BQ27: BRB | BR27: BRB | BS27: BRB | BT27: BRB | BU27: BRB | BV27: BRB | BW27: BRB | BX27: BRB | BY27: BRB | BZ27: URY | CA27: BRB | CB27: BRB | CC27: BRB | CD27: BRB | CE27: BRB | CF27: BRB | CG27: BRB | CH27: BRB | CI27: BRB | CJ27: BRB | CK27: BRB | CL27: BRB | CM27: -99 | CN27: -99 | CO27: North America | CP27: Americas | CQ27: Caribbean | CR27: Latin America & Caribbean | CS27: 8 | CT27: 8 | CU27: 5 | CV27: 3 | CW27: 1 | CX27: 0 | CY27: 4.5 | CZ27: 9.5 | DA27: -59.568966 | DB27: 13.163709 | DC27: 1159320449 | DD27: Q244 | DE27: Ø¨Ø§Ø±Ø¨Ø§Ø¯ÙˆØ³ | DF27: à¦¬à¦¾à¦°à§à¦¬à¦¾à¦¡à§‹à¦¸ | DG27: Barbados | DH27: Barbados | DI27: Barbados | DJ27: Ø¨Ø§Ø±Ø¨Ø§Ø¯ÙˆØ³ | DK27: Barbade | DL27: ÎœÏ€Î±ÏÎ¼Ï€Î¬Î½Ï„Î¿Ï‚ | DM27: ×‘×¨×‘×“×•×¡ | DN27: à¤¬à¤¾à¤°à¤¬à¤¾à¤¡à¥‹à¤¸ | DO27: Barbados | DP27: Barbados | DQ27: Barbados | DR27: ãƒãƒ«ãƒãƒ‰ã‚¹ | DS27: ë°”ë² ì´ë„ìŠ¤ | DT27: Barbados | DU27: Barbados | DV27: Barbados | DW27: Ð‘Ð°Ñ€Ð±Ð°Ð´Ð¾Ñ | DX27: Barbados | DY27: Barbados | DZ27: Ð‘Ð°Ñ€Ð±Ð°Ð´Ð¾Ñ | EA27: Ø¨Ø§Ø±Ø¨Ø§ÚˆÙˆØ³ | EB27: Barbados | EC27: å·´å·´å¤šæ–¯ | ED27: å·´è²å¤š | EE27: Admin-0 country | EG27: Admin-0 country
A28: Belarus | B28: Admin-0 country | C28: 0 | D28: 4 | E28: Belarus | F28: BLR | G28: 0 | H28: 2 | I28: Sovereign country | J28: 1 | K28: Belarus | L28: BLR | M28: 0 | N28: Belarus | O28: BLR | P28: 0 | Q28: Belarus | R28: BLR | S28: 0 | T28: Belarus | U28: BLR | V28: Belarus | X28: Bela. | Y28: BY | Z28: Republic of Belarus | AB28: Belarus | AE28: Belarus | AG28: 1 | AH28: 1 | AI28: 5 | AJ28: 11 | AK28: 9466856 | AL28: 13 | AM28: 2019 | AN28: 63080 | AO28: 2019 | AP28: 6. Developing region | AQ28: 3. Upper middle income | AR28: BO | AS28: BY | AT28: BY | AU28: BLR | AV28: BLR | AW28: 112 | AX28: 112 | AY28: 112 | AZ28: BY | BA28: BLR | BB28: 23424765 | BC28: 23424765 | BD28: Exact WOE match as country | BE28: BLR | BG28: BLR | BH28: BLR | BI28: BLR | BJ28: BLR | BK28: BLR | BL28: BLR | BM28: BLR | BN28: BLR | BO28: BLR | BP28: BLR | BQ28: BLR | BR28: BLR | BS28: BLR | BT28: BLR | BU28: BLR | BV28: BLR | BW28: BLR | BX28: BLR | BY28: BLR | BZ28: BLR | CA28: BLR | CB28: BLR | CC28: BLR | CD28: BLR | CE28: BLR | CF28: BLR | CG28: BLR | CH28: BLR | CI28: BLR | CJ28: BLR | CK28: BLR | CL28: BLR | CM28: -99 | CN28: -99 | CO28: Europe | CP28: Europe | CQ28: Eastern Europe | CR28: Europe & Central Asia | CS28: 7 | CT28: 7 | CU28: 5 | CV28: -99 | CW28: 1 | CX28: 0 | CY28: 3 | CZ28: 8 | DA28: 28.417701 | DB28: 53.821888 | DC28: 1159320427 | DD28: Q184 | DE28: Ø¨ÙŠÙ„Ø§Ø±ÙˆØ³ÙŠØ§ | DF28: à¦¬à§‡à¦²à¦¾à¦°à§à¦¶ | DG28: Belarus | DH28: Belarus | DI28: Bielorrusia | DJ28: Ø¨Ù„Ø§Ø±ÙˆØ³ | DK28: BiÃ©lorussie | DL28: Î›ÎµÏ…ÎºÎ¿ÏÏ‰ÏƒÎ¯Î± | DM28: ×‘×œ××¨×•×¡ | DN28: à¤¬à¥‡à¤²à¤¾à¤°à¥‚à¤¸ | DO28: FehÃ©roroszorszÃ¡g | DP28: Belarus | DQ28: Bielorussia | DR28: ãƒ™ãƒ©ãƒ«ãƒ¼ã‚· | DS28: ë²¨ë¼ë£¨ìŠ¤ | DT28: Wit-Rusland | DU28: BiaÅ‚oruÅ› | DV28: BielorrÃºssia | DW28: Ð‘ÐµÐ»Ð¾Ñ€ÑƒÑÑÐ¸Ñ | DX28: Belarus | DY28: Beyaz Rusya | DZ28: Ð‘Ñ–Ð»Ð¾Ñ€ÑƒÑÑŒ | EA28: Ø¨ÛŒÙ„Ø§Ø±ÙˆØ³ | EB28: Belarus | EC28: ç™½ä¿„ç½—æ–¯ | ED28: ç™½ä¿„ç¾…æ–¯ | EE28: Admin-0 country | EG28: Admin-0 country
A29: Belgium | B29: Admin-0 country | C29: 0 | D29: 2 | E29: Belgium | F29: BEL | G29: 0 | H29: 2 | I29: Sovereign country | J29: 1 | K29: Belgium | L29: BEL | M29: 0 | N29: Belgium | O29: BEL | P29: 0 | Q29: Belgium | R29: BEL | S29: 0 | T29: Belgium | U29: BEL | V29: Belgium | X29: Belg. | Y29: B | Z29: Kingdom of Belgium | AB29: Belgium | AE29: Belgium | AG29: 3 | AH29: 2 | AI29: 1 | AJ29: 8 | AK29: 11484055 | AL29: 14 | AM29: 2019 | AN29: 533097 | AO29: 2019 | AP29: 2. Developed region: nonG7 | AQ29: 1. High income: OECD | AR29: BE | AS29: BE | AT29: BE | AU29: BEL | AV29: BEL | AW29: 56 | AX29: 56 | AY29: 56 | AZ29: BE | BA29: BEL | BB29: 23424757 | BC29: 23424757 | BD29: Exact WOE match as country | BE29: BEL | BG29: BEL | BH29: BEL | BI29: BEL | BJ29: BEL | BK29: BEL | BL29: BEL | BM29: BEL | BN29: BEL | BO29: BEL | BP29: BEL | BQ29: BEL | BR29: BEL | BS29: BEL | BT29: BEL | BU29: BEL | BV29: BEL | BW29: BEL | BX29: BEL | BY29: BEL | BZ29: BEL | CA29: BEL | CB29: BEL | CC29: BEL | CD29: BEL | CE29: BEL | CF29: BEL | CG29: BEL | CH29: BEL | CI29: BEL | CJ29: BEL | CK29: BEL | CL29: BEL | CM29: -99 | CN29: -99 | CO29: Europe | CP29: Europe | CQ29: Western Europe | CR29: Europe & Central Asia | CS29: 7 | CT29: 7 | CU29: 5 | CV29: -99 | CW29: 1 | CX29: 0 | CY29: 4 | CZ29: 9 | DA29: 4.800448 | DB29: 50.785392 | DC29: 1159320389 | DD29: Q31 | DE29: Ø¨Ù„Ø¬ÙŠÙƒØ§ | DF29: à¦¬à§‡à¦²à¦œà¦¿à¦¯à¦¼à¦¾à¦® | DG29: Belgien | DH29: Belgium | DI29: BÃ©lgica | DJ29: Ø¨Ù„Ú˜ÛŒÚ© | DK29: Belgique | DL29: Î’Î­Î»Î³Î¹Î¿ | DM29: ×‘×œ×’×™×” | DN29: à¤¬à¥‡à¤²à¥à¤œà¤¿à¤¯à¤® | DO29: Belgium | DP29: Belgia | DQ29: Belgio | DR29: ãƒ™ãƒ«ã‚®ãƒ¼ | DS29: ë²¨ê¸°ì— | DT29: BelgiÃ« | DU29: Belgia | DV29: BÃ©lgica | DW29: Ð‘ÐµÐ»ÑŒÐ³Ð¸Ñ | DX29: Belgien | DY29: BelÃ§ika | DZ29: Ð‘ÐµÐ»ÑŒÐ³Ñ–Ñ | EA29: Ø¨Ù„Ø¬Ø¦ÛŒÙ… | EB29: Bá»‰ | EC29: æ¯”åˆ©æ—¶ | ED29: æ¯”åˆ©æ™‚ | EE29: Admin-0 country | EG29: Admin-0 country
A30: Belize | B30: Admin-0 country | C30: 0 | D30: 6 | E30: Belize | F30: BLZ | G30: 0 | H30: 2 | I30: Sovereign country | J30: 1 | K30: Belize | L30: BLZ | M30: 0 | N30: Belize | O30: BLZ | P30: 0 | Q30: Belize | R30: BLZ | S30: 0 | T30: Belize | U30: BLZ | V30: Belize | X30: Belize | Y30: BZ | Z30: Belize | AB30: Belize | AE30: Belize | AG30: 1 | AH30: 4 | AI30: 5 | AJ30: 7 | AK30: 390353 | AL30: 10 | AM30: 2019 | AN30: 1879 | AO30: 2019 | AP30: 6. Developing region | AQ30: 4. Lower middle income | AR30: BH | AS30: BZ | AT30: BZ | AU30: BLZ | AV30: BLZ | AW30: 84 | AX30: 84 | AY30: 84 | AZ30: BZ | BA30: BLZ | BB30: 23424760 | BC30: 23424760 | BD30: Exact WOE match as country | BE30: BLZ | BG30: BLZ | BH30: BLZ | BI30: BLZ | BJ30: BLZ | BK30: BLZ | BL30: BLZ | BM30: BLZ | BN30: BLZ | BO30: BLZ | BP30: BLZ | BQ30: BLZ | BR30: BLZ | BS30: BLZ | BT30: BLZ | BU30: BLZ | BV30: BLZ | BW30: BLZ | BX30: BLZ | BY30: BLZ | BZ30: BLZ | CA30: BLZ | CB30: BLZ | CC30: BLZ | CD30: BLZ | CE30: BLZ | CF30: BLZ | CG30: BLZ | CH30: BLZ | CI30: BLZ | CJ30: BLZ | CK30: BLZ | CL30: BLZ | CM30: -99 | CN30: -99 | CO30: North America | CP30: Americas | CQ30: Central America | CR30: Latin America & Caribbean | CS30: 6 | CT30: 6 | CU30: 6 | CV30: -99 | CW30: 1 | CX30: 0 | CY30: 5 | CZ30: 10 | DA30: -88.712962 | DB30: 17.202068 | DC30: 1159320431 | DD30: Q242 | DE30: Ø¨Ù„ÙŠØ² | DF30: à¦¬à§‡à¦²à¦¿à¦œ | DG30: Belize | DH30: Belize | DI30: Belice | DJ30: Ø¨Ù„ÛŒØ² | DK30: Belize | DL30: ÎœÏ€ÎµÎ»Î¯Î¶ | DM30: ×‘×œ×™×– | DN30: à¤¬à¥‡à¤²à¥€à¤œà¤¼ | DO30: Belize | DP30: Belize | DQ30: Belize | DR30: ãƒ™ãƒªãƒ¼ã‚º | DS30: ë²¨ë¦¬ì¦ˆ | DT30: Belize | DU30: Belize | DV30: Belize | DW30: Ð‘ÐµÐ»Ð¸Ð· | DX30: Belize | DY30: Belize | DZ30: Ð‘ÐµÐ»Ñ–Ð· | EA30: Ø¨ÛŒÙ„ÛŒØ² | EB30: Belize | EC30: ä¼¯åˆ©å…¹ | ED30: è²é‡Œæ–¯ | EE30: Admin-0 country | EG30: Admin-0 country
A31: Benin | B31: Admin-0 country | C31: 0 | D31: 5 | E31: Benin | F31: BEN | G31: 0 | H31: 2 | I31: Sovereign country | J31: 1 | K31: Benin | L31: BEN | M31: 0 | N31: Benin | O31: BEN | P31: 0 | Q31: Benin | R31: BEN | S31: 0 | T31: Benin | U31: BEN | V31: Benin | X31: Benin | Y31: BJ | Z31: Republic of Benin | AB31: Benin | AE31: Benin | AG31: 1 | AH31: 2 | AI31: 2 | AJ31: 12 | AK31: 11801151 | AL31: 14 | AM31: 2019 | AN31: 14390 | AO31: 2019 | AP31: 7. Least developed region | AQ31: 5. Low income | AR31: BN | AS31: BJ | AT31: BJ | AU31: BEN | AV31: BEN | AW31: 204 | AX31: 204 | AY31: 204 | AZ31: BJ | BA31: BEN | BB31: 23424764 | BC31: 23424764 | BD31: Exact WOE match as country | BE31: BEN | BG31: BEN | BH31: BEN | BI31: BEN | BJ31: BEN | BK31: BEN | BL31: BEN | BM31: BEN | BN31: BEN | BO31: BEN | BP31: BEN | BQ31: BEN | BR31: BEN | BS31: BEN | BT31: BEN | BU31: BEN | BV31: BEN | BW31: BEN | BX31: BEN | BY31: BEN | BZ31: BEN | CA31: BEN | CB31: BEN | CC31: BEN | CD31: BEN | CE31: BEN | CF31: BEN | CG31: BEN | CH31: BEN | CI31: BEN | CJ31: BEN | CK31: BEN | CL31: BEN | CM31: -99 | CN31: -99 | CO31: Africa | CP31: Africa | CQ31: Western Africa | CR31: Sub-Saharan Africa | CS31: 5 | CT31: 5 | CU31: 5 | CV31: -99 | CW31: 1 | CX31: 0 | CY31: 4 | CZ31: 9 | DA31: 2.352018 | DB31: 10.324775 | DC31: 1159320399 | DD31: Q962 | DE31: Ø¨Ù†ÙŠÙ† | DF31: à¦¬à§‡à¦¨à¦¿à¦¨ | DG31: Benin | DH31: Benin | DI31: BenÃ­n | DJ31: Ø¨Ù†ÛŒÙ† | DK31: BÃ©nin | DL31: ÎœÏ€ÎµÎ½Î¯Î½ | DM31: ×‘× ×™×Ÿ | DN31: à¤¬à¥‡à¤¨à¤¿à¤¨ | DO31: Benin | DP31: Benin | DQ31: Benin | DR31: ãƒ™ãƒŠãƒ³ | DS31: ë² ëƒ‰ | DT31: Benin | DU31: Benin | DV31: Benim | DW31: Ð‘ÐµÐ½Ð¸Ð½ | DX31: Benin | DY31: Benin | DZ31: Ð‘ÐµÐ½Ñ–Ð½ | EA31: Ø¨ÛŒÙ†Ù† | EB31: BÃ©nin | EC31: è´å® | ED31: è²å— | EE31: Admin-0 country | EG31: Admin-0 country
A32: Bermuda | B32: Admin-0 country | C32: 5 | D32: 6 | E32: United Kingdom | F32: GB1 | G32: 1 | H32: 2 | I32: Dependency | J32: 1 | K32: Bermuda | L32: BMU | M32: 0 | N32: Bermuda | O32: BMU | P32: 0 | Q32: Bermuda | R32: BMU | S32: 0 | T32: Bermuda | U32: BMU | V32: Bermuda | X32: Berm. | Y32: BM | Z32: The Bermudas or Somers Isles | AB32: Bermuda | AC32: U.K. | AE32: Bermuda | AG32: 6 | AH32: 6 | AI32: 6 | AJ32: 3 | AK32: 63918 | AL32: 8 | AM32: 2019 | AN32: 7484 | AO32: 2019 | AP32: 2. Developed region: nonG7 | AQ32: 2. High income: nonOECD | AR32: BD | AS32: BM | AT32: BM | AU32: BMU | AV32: BMU | AW32: 60 | AX32: 60 | AY32: 60 | AZ32: BM | BA32: BMU | BB32: 23424756 | BC32: 23424756 | BD32: Exact WOE match as country | BE32: BMU | BG32: BMU | BH32: BMU | BI32: BMU | BJ32: BMU | BK32: BMU | BL32: BMU | BM32: BMU | BN32: BMU | BO32: BMU | BP32: BMU | BQ32: BMU | BR32: BMU | BS32: BMU | BT32: BMU | BU32: BMU | BV32: BMU | BW32: BMU | BX32: BMU | BY32: BMU | BZ32: BMU | CA32: BMU | CB32: BMU | CC32: BMU | CD32: BMU | CE32: BMU | CF32: BMU | CG32: BMU | CH32: BMU | CI32: BMU | CJ32: BMU | CK32: BMU | CL32: BMU | CM32: -99 | CN32: -99 | CO32: North America | CP32: Americas | CQ32: Northern America | CR32: North America | CS32: 7 | CT32: 7 | CU32: 5 | CV32: 4 | CW32: -99 | CX32: 0 | CY32: 4 | CZ32: 9 | DA32: -64.763573 | DB32: 32.296592 | DC32: 1159320705 | DD32: Q23635 | DE32: Ø¨Ø±Ù…ÙˆØ¯Ø§ | DF32: à¦¬à¦¾à¦°à¦®à§à¦¡à¦¾ | DG32: Bermuda | DH32: Bermuda | DI32: Bermudas | DJ32: Ø¨Ø±Ù…ÙˆØ¯Ø§ | DK32: Bermudes | DL32: Î’ÎµÏÎ¼Î¿ÏÎ´ÎµÏ‚ | DM32: ×‘×¨×ž×•×“×” | DN32: à¤¬à¤°à¤®à¥‚à¤¡à¤¾ | DO32: Bermuda | DP32: Bermuda | DQ32: Bermuda | DR32: ãƒãƒŸãƒ¥ãƒ¼ãƒ€è«¸å³¶ | DS32: ë²„ë®¤ë‹¤ | DT32: Bermuda | DU32: Bermudy | DV32: Bermudas | DW32: Ð‘ÐµÑ€Ð¼ÑƒÐ´ÑÐºÐ¸Ðµ ÐžÑÑ‚Ñ€Ð¾Ð²Ð° | DX32: Bermuda | DY32: Bermuda | DZ32: Ð‘ÐµÑ€Ð¼ÑƒÐ´ÑÑŒÐºÑ– Ð¾ÑÑ‚Ñ€Ð¾Ð²Ð¸ | EA32: Ø¨Ø±Ù…ÙˆØ¯Ø§ | EB32: Bermuda | EC32: ç™¾æ…•å¤§ | ED32: ç™¾æ…•é” | EE32: Admin-0 dependency | EG32: Admin-0 dependency
A33: Bhutan | B33: Admin-0 country | C33: 0 | D33: 5 | E33: Bhutan | F33: BTN | G33: 0 | H33: 2 | I33: Sovereign country | J33: 1 | K33: Bhutan | L33: BTN | M33: 0 | N33: Bhutan | O33: BTN | P33: 0 | Q33: Bhutan | R33: BTN | S33: 0 | T33: Bhutan | U33: BTN | V33: Bhutan | X33: Bhutan | Y33: BT | Z33: Kingdom of Bhutan | AB33: Bhutan | AE33: Bhutan | AG33: 5 | AH33: 6 | AI33: 1 | AJ33: 8 | AK33: 763092 | AL33: 11 | AM33: 2019 | AN33: 2530 | AO33: 2019 | AP33: 7. Least developed region | AQ33: 4. Lower middle income | AR33: BT | AS33: BT | AT33: BT | AU33: BTN | AV33: BTN | AW33: 64 | AX33: 64 | AY33: 64 | AZ33: BT | BA33: BTN | BB33: 23424770 | BC33: 23424770 | BD33: Exact WOE match as country | BE33: BTN | BG33: BTN | BH33: BTN | BI33: BTN | BJ33: BTN | BK33: BTN | BL33: BTN | BM33: BTN | BN33: BTN | BO33: BTN | BP33: BTN | BQ33: BTN | BR33: BTN | BS33: BTN | BT33: BTN | BU33: BTN | BV33: BTN | BW33: BTN | BX33: BTN | BY33: BTN | BZ33: BTN | CA33: BTN | CB33: BTN | CC33: BTN | CD33: BTN | CE33: BTN | CF33: BTN | CG33: BTN | CH33: BTN | CI33: BTN | CJ33: BTN | CK33: BTN | CL33: BTN | CM33: -99 | CN33: -99 | CO33: Asia | CP33: Asia | CQ33: Southern Asia | CR33: South Asia | CS33: 6 | CT33: 6 | CU33: 6 | CV33: -99 | CW33: 1 | CX33: 0 | CY33: 4 | CZ33: 9 | DA33: 90.040294 | DB33: 27.536685 | DC33: 1159320453 | DD33: Q917 | DE33: Ø¨ÙˆØªØ§Ù† | DF33: à¦­à§à¦Ÿà¦¾à¦¨ | DG33: Bhutan | DH33: Bhutan | DI33: ButÃ¡n | DJ33: Ø¨ÙˆØªØ§Ù† | DK33: Bhoutan | DL33: ÎœÏ€Î¿Ï…Ï„Î¬Î½ | DM33: ×‘×”×•×˜×Ÿ | DN33: à¤­à¥‚à¤Ÿà¤¾à¤¨ | DO33: BhutÃ¡n | DP33: Bhutan | DQ33: Bhutan | DR33: ãƒ–ãƒ¼ã‚¿ãƒ³ | DS33: ë¶€íƒ„ | DT33: Bhutan | DU33: Bhutan | DV33: ButÃ£o | DW33: Ð‘ÑƒÑ‚Ð°Ð½ | DX33: Bhutan | DY33: Bhutan | DZ33: Ð‘ÑƒÑ‚Ð°Ð½ | EA33: Ø¨Ú¾ÙˆÙ¹Ø§Ù† | EB33: Bhutan | EC33: ä¸ä¸¹ | ED33: ä¸ä¸¹ | EE33: Admin-0 country | EG33: Admin-0 country
A34: Bir Tawil | B34: Admin-0 country | C34: 0 | D34: 8 | E34: Bir Tawil | F34: BRT | G34: 0 | H34: 2 | I34: Indeterminate | K34: Bir Tawil | L34: BRT | M34: 0 | N34: Bir Tawil | O34: BRT | P34: 0 | Q34: Bir Tawil | R34: BRT | S34: 1 | T34: Bir Tawil | U34: B94 | V34: Bir Tawil | X34: B. Tawil | AD34: Between Egypt and Sudan | AE34: Bir Tawil | AG34: 1 | AH34: 1 | AI34: 2 | AJ34: 5 | AK34: 0 | AL34: 1 | AM34: 2019 | AN34: 0 | AO34: 2019 | AP34: 7. Least developed region | AQ34: 5. Low income | AR34: -99 | AS34: -99 | AT34: -99 | AU34: -99 | AV34: -99 | AW34: -99 | AX34: -99 | AY34: -99 | AZ34: -99 | BA34: -99 | BB34: -99 | BC34: -99 | BD34: No WOE equivalent. | BE34: -99 | BG34: -99 | BH34: BRT | BI34: BRT | BJ34: BRT | BK34: BRT | BL34: BRT | BM34: BRT | BN34: BRT | BO34: BRT | BP34: BRT | BQ34: BRT | BR34: BRT | BS34: BRT | BT34: BRT | BU34: BRT | BV34: BRT | BW34: BRT | BX34: BRT | BY34: BRT | BZ34: BRT | CA34: BRT | CB34: BRT | CC34: BRT | CD34: BRT | CE34: BRT | CF34: BRT | CG34: BRT | CH34: BRT | CI34: BRT | CJ34: BRT | CK34: BRT | CL34: BRT | CM34: -99 | CN34: -99 | CO34: Africa | CP34: Africa | CQ34: Northern Africa | CR34: Middle East & North Africa | CS34: 9 | CT34: 9 | CU34: 8 | CV34: -99 | CW34: -99 | CX34: 7 | CY34: 7 | CZ34: 9 | DA34: 33.673428 | DB34: 21.860442 | DC34: 1729635091 | DD34: Q620634 | DE34: Ø¨Ø¦Ø± Ø·ÙˆÙŠÙ„ | DF34: à¦¬à¦¿à¦° à¦¤à¦¾à¦‰à¦‡à¦² | DG34: Bir Tawil | DH34: Bir Tawil | DI34: Bir Tawil | DJ34: Ø¨Ø¦Ø± Ø·ÙˆÛŒÙ„ | DK34: Bir Tawil | DL34: ÎœÏ€Î¹Ï Î¤Î±Î¿Ï…Î¯Î» | DM34: ×‘×™×¨ ×˜×•×•×™×œ | DN34: à¤¬à¥€à¤° à¤¤à¤¾à¤µà¤¿à¤² | DO34: Bir Tawil | DP34: Bir Tawil | DQ34: Bir Tawil | DR34: ãƒ“ãƒ«ãƒ»ã‚¿ã‚¦ã‚£ãƒ¼ãƒ« | DS34: ë¹„ë¥´ íƒ€ìœŒ | DT34: Bir Tawil | DU34: Bir Tawil | DV34: Bir Tawil | DW34: Ð‘Ð¸Ñ€-Ð¢Ð°Ð²Ð¸Ð»ÑŒ | DX34: Bir Tawil | DY34: Bir Tawil | DZ34: Ð‘Ñ–Ñ€-Ð¢Ð°Ð²Ñ–Ð»ÑŒ | EA34: Ø¨Ø± Ù¹Ø§ÙˆÛŒÙ„ | EB34: Bir Tawil | EC34: æ¯”å°”æ³°ç»´å‹’ | ED34: æ¯”çˆ¾å¡”å¨çˆ¾ | EE34: Unrecognized | EG34: Unrecognized
A35: Bolivia | B35: Admin-0 country | C35: 0 | D35: 3 | E35: Bolivia | F35: BOL | G35: 0 | H35: 2 | I35: Sovereign country | J35: 1 | K35: Bolivia | L35: BOL | M35: 0 | N35: Bolivia | O35: BOL | P35: 0 | Q35: Bolivia | R35: BOL | S35: 0 | T35: Bolivia | U35: BOL | V35: Bolivia | X35: Bolivia | Y35: BO | Z35: Plurinational State of Bolivia | AB35: Bolivia | AE35: Bolivia | AG35: 1 | AH35: 5 | AI35: 2 | AJ35: 3 | AK35: 11513100 | AL35: 14 | AM35: 2019 | AN35: 40895 | AO35: 2019 | AP35: 5. Emerging region: G20 | AQ35: 4. Lower middle income | AR35: BL | AS35: BO | AT35: BO | AU35: BOL | AV35: BOL | AW35: 68 | AX35: 68 | AY35: 68 | AZ35: BO | BA35: BOL | BB35: 23424762 | BC35: 23424762 | BD35: Exact WOE match as country | BE35: BOL | BG35: BOL | BH35: BOL | BI35: BOL | BJ35: BOL | BK35: BOL | BL35: BOL | BM35: BOL | BN35: BOL | BO35: BOL | BP35: BOL | BQ35: BOL | BR35: BOL | BS35: BOL | BT35: BOL | BU35: BOL | BV35: BOL | BW35: BOL | BX35: BOL | BY35: BOL | BZ35: BOL | CA35: BOL | CB35: BOL | CC35: BOL | CD35: BOL | CE35: BOL | CF35: BOL | CG35: BOL | CH35: BOL | CI35: BOL | CJ35: BOL | CK35: BOL | CL35: BOL | CM35: -99 | CN35: -99 | CO35: South America | CP35: Americas | CQ35: South America | CR35: Latin America & Caribbean | CS35: 7 | CT35: 7 | CU35: 7 | CV35: -99 | CW35: 1 | CX35: 0 | CY35: 3 | CZ35: 7.5 | DA35: -64.593433 | DB35: -16.666015 | DC35: 1159320439 | DD35: Q750 | DE35: Ø¨ÙˆÙ„ÙŠÙÙŠØ§ | DF35: à¦¬à¦²à¦¿à¦­à¦¿à¦¯à¦¼à¦¾ | DG35: Bolivien | DH35: Bolivia | DI35: Bolivia | DJ35: Ø¨ÙˆÙ„ÛŒÙˆÛŒ | DK35: Bolivie | DL35: Î’Î¿Î»Î¹Î²Î¯Î± | DM35: ×‘×•×œ×™×‘×™×” | DN35: à¤¬à¥‹à¤²à¤¿à¤µà¤¿à¤¯à¤¾ | DO35: BolÃ­via | DP35: Bolivia | DQ35: Bolivia | DR35: ãƒœãƒªãƒ“ã‚¢ | DS35: ë³¼ë¦¬ë¹„ì•„ | DT35: Bolivia | DU35: Boliwia | DV35: BolÃ­via | DW35: Ð‘Ð¾Ð»Ð¸Ð²Ð¸Ñ | DX35: Bolivia | DY35: Bolivya | DZ35: Ð‘Ð¾Ð»Ñ–Ð²Ñ–Ñ | EA35: Ø¨ÙˆÙ„ÛŒÙˆÛŒØ§ | EB35: Bolivia | EC35: çŽ»åˆ©ç»´äºš | ED35: çŽ»åˆ©ç¶­äºž | EE35: Admin-0 country | EG35: Admin-0 country
A36: Bonaire | B36: Admin-1 states provinces | C36: 10 | L36: NL-BQ1 | FN36: NLD-5149 | FO36: 5149 | FP36: http://en.wikipedia.org/wiki/Bonaire | FQ36: NL | FR36: 3 | FU36: Bijzondere Gemeenten | FV36: Special Municipality | FX36: BQ.BO | GB36: 0 | GC36: 0 | GD36: 0 | GE36: 10 | GH36: 0 | GI36: -99 | GJ36: 20 | GK36: 7 | GL36: 2 | GM36: 9 | GP36: 24549811 | GQ36: Bonaire, AN, Netherlands Antilles | GR36: Bonaire | GS36: 12.2314 | GT36: -68.3029 | GU36: NL1 | GV36: NL-BQ1 | GW36: 6 | GX36: Caribbean Netherlands | GZ36: NLD | HA36: 7609816 | HB36: Bonaire | HC36: 0 | HE36: 1 | HG36: NL.BO | HJ36: 0 | HN36: 11 | HO36: 11 | HP36: 8 | HQ36: Q25396 | HR36: Ø¨ÙˆÙ†ÙŠØ± | HS36: à¦¬à§‹à¦¨à¦¾à¦‡à¦° | HT36: Bonaire | HU36: Bonaire | HV36: Bonaire | HW36: Bonaire | HX36: ÎœÏ€Î¿Î½Î±Î¯Ï | HY36: à¤¬à¥‹à¤¨à¥‡à¤¯à¥‡à¤° | HZ36: Bonaire | IA36: Bonaire | IB36: Bonaire | IC36: ãƒœãƒãƒ¼ãƒ«å³¶ | ID36: ë³´ë„¤ë¥´ì„¬ | IE36: Bonaire | IF36: Bonaire | IG36: Bonaire | IH36: Ð‘Ð¾Ð½ÑÐ¹Ñ€ | II36: Bonaire | IJ36: Bonaire | IK36: Bonaire | IL36: åšå¥ˆå°” | IM36: 1159315527 | IN36: ×‘×•× ×™×™×¨ | IO36: Ð‘Ð¾Ð½Ð°Ð¹Ñ€Ðµ | IP36: Ø¨ÙˆÙ†Ø§ÛŒØ± | IQ36: Ø¨ÙˆÙ†ÛŒØ± | IR36: æ³¢å¥ˆ
A37: Bosnia and Herzegovina | B37: Admin-0 country | C37: 0 | D37: 5 | E37: Bosnia and Herzegovina | F37: BIH | G37: 0 | H37: 2 | I37: Sovereign country | J37: 1 | K37: Bosnia and Herzegovina | L37: BIH | M37: 0 | N37: Bosnia and Herzegovina | O37: BIH | P37: 0 | Q37: Bosnia and Herzegovina | R37: BIH | S37: 0 | T37: Bosnia and Herzegovina | U37: BIH | V37: Bosnia and Herzegovina | X37: B.H. | Y37: BiH | Z37: Bosnia and Herzegovina | AB37: Bosnia and Herzegovina | AE37: Bosnia and Herzegovina | AG37: 1 | AH37: 1 | AI37: 1 | AJ37: 2 | AK37: 3301000 | AL37: 12 | AM37: 2019 | AN37: 20164 | AO37: 2019 | AP37: 6. Developing region | AQ37: 3. Upper middle income | AR37: BK | AS37: BA | AT37: BA | AU37: BIH | AV37: BIH | AW37: 70 | AX37: 70 | AY37: 70 | AZ37: BA | BA37: BIH | BB37: 23424761 | BC37: 23424761 | BD37: Exact WOE match as country | BE37: BIH | BG37: BIH | BH37: BIH | BI37: BIH | BJ37: BIH | BK37: BIH | BL37: BIH | BM37: BIH | BN37: BIH | BO37: BIH | BP37: BIH | BQ37: BIH | BR37: BIH | BS37: BIH | BT37: BIH | BU37: BIH | BV37: BIH | BW37: BIH | BX37: BIH | BY37: BIH | BZ37: BIH | CA37: BIH | CB37: BIH | CC37: BIH | CD37: BIH | CE37: BIH | CF37: BIH | CG37: BIH | CH37: BIH | CI37: BIH | CJ37: BIH | CK37: BIH | CL37: BIH | CM37: -99 | CN37: -99 | CO37: Europe | CP37: Europe | CQ37: Southern Europe | CR37: Europe & Central Asia | CS37: 16 | CT37: 22 | CU37: 4 | CV37: -99 | CW37: 1 | CX37: 0 | CY37: 4.5 | CZ37: 6.8 | DA37: 18.06841 | DB37: 44.091051 | DC37: 1159320417 | DD37: Q225 | DE37: Ø§Ù„Ø¨ÙˆØ³Ù†Ø© ÙˆØ§Ù„Ù‡Ø±Ø³Ùƒ | DF37: à¦¬à¦¸à¦¨à¦¿à¦¯à¦¼à¦¾ à¦“ à¦¹à¦¾à¦°à§à¦œà§‡à¦—à§‹à¦­à¦¿à¦¨à¦¾ | DG37: Bosnien und Herzegowina | DH37: Bosnia and Herzegovina | DI37: Bosnia y Herzegovina | DJ37: Ø¨ÙˆØ³Ù†ÛŒ Ùˆ Ù‡Ø±Ø²Ú¯ÙˆÛŒÙ† | DK37: Bosnie-HerzÃ©govine | DL37: Î’Î¿ÏƒÎ½Î¯Î± ÎºÎ±Î¹ Î•ÏÎ¶ÎµÎ³Î¿Î²Î¯Î½Î· | DM37: ×‘×•×¡× ×™×” ×•×”×¨×¦×’×•×‘×™× ×” | DN37: à¤¬à¥‰à¤¸à¥à¤¨à¤¿à¤¯à¤¾ à¤”à¤° à¤¹à¤°à¥à¤œà¤¼à¥‡à¤—à¥‹à¤µà¤¿à¤¨à¤¾ | DO37: Bosznia-Hercegovina | DP37: Bosnia dan Herzegovina | DQ37: Bosnia ed Erzegovina | DR37: ãƒœã‚¹ãƒ‹ã‚¢ãƒ»ãƒ˜ãƒ«ãƒ„ã‚§ã‚´ãƒ“ãƒŠ | DS37: ë³´ìŠ¤ë‹ˆì•„ í—¤ë¥´ì²´ê³ ë¹„ë‚˜ | DT37: BosniÃ« en Herzegovina | DU37: BoÅ›nia i Hercegowina | DV37: BÃ³snia e Herzegovina | DW37: Ð‘Ð¾ÑÐ½Ð¸Ñ Ð¸ Ð“ÐµÑ€Ñ†ÐµÐ³Ð¾Ð²Ð¸Ð½Ð° | DX37: Bosnien och Hercegovina | DY37: Bosna-Hersek | DZ37: Ð‘Ð¾ÑÐ½Ñ–Ñ Ñ– Ð“ÐµÑ€Ñ†ÐµÐ³Ð¾Ð²Ð¸Ð½Ð° | EA37: Ø¨ÙˆØ³Ù†ÛŒØ§ Ùˆ ÛØ±Ø²ÛŒÚ¯ÙˆÙˆÛŒÙ†Ø§ | EB37: Bosna vÃ Hercegovina | EC37: æ³¢æ–¯å°¼äºšå’Œé»‘å¡žå“¥ç»´é‚£ | ED37: æ³¢å£«å°¼äºžèˆ‡èµ«å¡žå“¥ç¶­ç´ | EE37: Admin-0 country | EG37: Admin-0 country
A38: Botswana | B38: Admin-0 country | C38: 0 | D38: 4 | E38: Botswana | F38: BWA | G38: 0 | H38: 2 | I38: Sovereign country | J38: 1 | K38: Botswana | L38: BWA | M38: 0 | N38: Botswana | O38: BWA | P38: 0 | Q38: Botswana | R38: BWA | S38: 0 | T38: Botswana | U38: BWA | V38: Botswana | X38: Bwa. | Y38: BW | Z38: Republic of Botswana | AB38: Botswana | AE38: Botswana | AG38: 6 | AH38: 5 | AI38: 7 | AJ38: 3 | AK38: 2303697 | AL38: 12 | AM38: 2019 | AN38: 18340 | AO38: 2019 | AP38: 6. Developing region | AQ38: 3. Upper middle income | AR38: BC | AS38: BW | AT38: BW | AU38: BWA | AV38: BWA | AW38: 72 | AX38: 72 | AY38: 72 | AZ38: BW | BA38: BWA | BB38: 23424755 | BC38: 23424755 | BD38: Exact WOE match as country | BE38: BWA | BG38: BWA | BH38: BWA | BI38: BWA | BJ38: BWA | BK38: BWA | BL38: BWA | BM38: BWA | BN38: BWA | BO38: BWA | BP38: BWA | BQ38: BWA | BR38: BWA | BS38: BWA | BT38: BWA | BU38: BWA | BV38: BWA | BW38: BWA | BX38: BWA | BY38: BWA | BZ38: BWA | CA38: BWA | CB38: BWA | CC38: BWA | CD38: BWA | CE38: BWA | CF38: BWA | CG38: BWA | CH38: BWA | CI38: BWA | CJ38: BWA | CK38: BWA | CL38: BWA | CM38: -99 | CN38: -99 | CO38: Africa | CP38: Africa | CQ38: Southern Africa | CR38: Sub-Saharan Africa | CS38: 8 | CT38: 8 | CU38: 4 | CV38: -99 | CW38: 1 | CX38: 0 | CY38: 4 | CZ38: 9 | DA38: 24.179216 | DB38: -22.102634 | DC38: 1159320461 | DD38: Q963 | DE38: Ø¨ÙˆØªØ³ÙˆØ§Ù†Ø§ | DF38: à¦¬à¦¤à¦¸à§‹à¦¯à¦¼à¦¾à¦¨à¦¾ | DG38: Botswana | DH38: Botswana | DI38: Botsuana | DJ38: Ø¨ÙˆØªØ³ÙˆØ§Ù†Ø§ | DK38: Botswana | DL38: ÎœÏ€Î¿Ï„ÏƒÎ¿Ï…Î¬Î½Î± | DM38: ×‘×•×˜×¡×•×× ×” | DN38: à¤¬à¥‹à¤¤à¥à¤¸à¤µà¤¾à¤¨à¤¾ | DO38: Botswana | DP38: Botswana | DQ38: Botswana | DR38: ãƒœãƒ„ãƒ¯ãƒŠ | DS38: ë³´ì¸ ì™€ë‚˜ | DT38: Botswana | DU38: Botswana | DV38: Botsuana | DW38: Ð‘Ð¾Ñ‚ÑÐ²Ð°Ð½Ð° | DX38: Botswana | DY38: Botsvana | DZ38: Ð‘Ð¾Ñ‚ÑÐ²Ð°Ð½Ð° | EA38: Ø¨ÙˆÙ¹Ø³ÙˆØ§Ù†Ø§ | EB38: Botswana | EC38: åšèŒ¨ç“¦çº³ | ED38: æ³¢æœ­é‚£ | EE38: Admin-0 country | EG38: Admin-0 country
A39: Br. Indian Ocean Ter. | B39: Admin-0 country | C39: 5 | D39: 5 | E39: United Kingdom | F39: GB1 | G39: 1 | H39: 2 | I39: Disputed | J39: 1 | K39: British Indian Ocean Territory | L39: IOT | M39: 0 | N39: British Indian Ocean Territory | O39: IOT | P39: 0 | Q39: British Indian Ocean Territory | R39: IOT | S39: 1 | T39: British Indian Ocean Territory | U39: B69 | V39: Br. Indian Ocean Ter. | X39: I.O.T. | Y39: IO | AC39: U.K. | AD39: Admin. by U.K.; Claimed by Mauritius and Seychelles | AE39: British Indian Ocean Territory | AG39: 6 | AH39: 6 | AI39: 6 | AJ39: 3 | AK39: 3000 | AL39: 4 | AM39: 2018 | AN39: 120 | AO39: 2013 | AP39: 2. Developed region: nonG7 | AQ39: 2. High income: nonOECD | AR39: IO | AS39: IO | AT39: IO | AU39: IOT | AV39: IOT | AW39: 86 | AX39: 86 | AY39: -99 | AZ39: -99 | BA39: -99 | BB39: 23424849 | BC39: 23424849 | BD39: Exact WOE match as country | BE39: B69 | BG39: B69 | BH39: IOT | BI39: IOT | BJ39: IOT | BK39: IOT | BL39: IOT | BM39: IOT | BN39: IOT | BO39: IOT | BP39: IOT | BQ39: IOT | BR39: IOT | BS39: IOT | BT39: IOT | BU39: IOT | BV39: IOT | BW39: IOT | BX39: IOT | BY39: IOT | BZ39: IOT | CA39: IOT | CB39: IOT | CC39: IOT | CD39: IOT | CE39: IOT | CF39: IOT | CG39: IOT | CH39: IOT | CI39: IOT | CJ39: IOT | CK39: IOT | CL39: IOT | CM39: -99 | CN39: -99 | CO39: Seven seas (open ocean) | CP39: Africa | CQ39: Seven seas (open ocean) | CR39: Sub-Saharan Africa | CS39: 21 | CT39: 30 | CU39: 6 | CV39: 5 | CW39: -99 | CX39: 0 | CY39: 5 | CZ39: 9.5 | DA39: 71.348349 | DB39: -6.190826 | DC39: 1159320723 | DD39: Q43448 | DE39: Ø¥Ù‚Ù„ÙŠÙ… Ø§Ù„Ù…Ø­ÙŠØ· Ø§Ù„Ù‡Ù†Ø¯ÙŠ Ø§Ù„Ø¨Ø±ÙŠØ·Ø§Ù†ÙŠ | DF39: à¦¬à§à¦°à¦¿à¦Ÿà¦¿à¦¶ à¦­à¦¾à¦°à¦¤ à¦®à¦¹à¦¾à¦¸à¦¾à¦—à¦°à§€à¦¯à¦¼ à¦à¦²à¦¾à¦•à¦¾ | DG39: Britisches Territorium im Indischen Ozean | DH39: British Indian Ocean Territory | DI39: Territorio BritÃ¡nico del OcÃ©ano Ãndico | DJ39: Ù‚Ù„Ù…Ø±Ùˆ Ø¨Ø±ÛŒØªØ§Ù†ÛŒØ§ Ø¯Ø± Ø§Ù‚ÛŒØ§Ù†ÙˆØ³ Ù‡Ù†Ø¯ | DK39: Territoire britannique de lâ€™ocÃ©an Indien | DL39: Î’ÏÎµÏ„Î±Î½Î¹ÎºÏŒ ÎˆÎ´Î±Ï†Î¿Ï‚ Î™Î½Î´Î¹ÎºÎ¿Ï Î©ÎºÎµÎ±Î½Î¿Ï | DM39: ×”×˜×¨×™×˜×•×¨×™×” ×”×‘×¨×™×˜×™×ª ×‘××•×§×™×™× ×•×¡ ×”×”×•×“×™ | DN39: à¤¬à¥à¤°à¤¿à¤Ÿà¤¿à¤¶ à¤¹à¤¿à¤‚à¤¦ à¤®à¤¹à¤¾à¤¸à¤¾à¤—à¤° à¤•à¥à¤·à¥‡à¤¤à¥à¤° | DO39: Brit Indiai-Ã³ceÃ¡ni TerÃ¼let | DP39: Wilayah Samudra Hindia Britania | DQ39: Territorio britannico dell'oceano Indiano | DR39: ã‚¤ã‚®ãƒªã‚¹é ˜ã‚¤ãƒ³ãƒ‰æ´‹åœ°åŸŸ | DS39: ì˜êµ­ë ¹ ì¸ë„ì–‘ ì§€ì—­ | DT39: Brits Indische Oceaanterritorium | DU39: Brytyjskie Terytorium Oceanu Indyjskiego | DV39: TerritÃ³rio BritÃ¢nico do Oceano Ãndico | DW39: Ð‘Ñ€Ð¸Ñ‚Ð°Ð½ÑÐºÐ°Ñ Ñ‚ÐµÑ€Ñ€Ð¸Ñ‚Ð¾Ñ€Ð¸Ñ Ð² Ð˜Ð½Ð´Ð¸Ð¹ÑÐºÐ¾Ð¼ Ð¾ÐºÐµÐ°Ð½Ðµ | DX39: Brittiska territoriet i Indiska oceanen | DY39: Britanya Hint Okyanusu TopraklarÄ± | DZ39: Ð‘Ñ€Ð¸Ñ‚Ð°Ð½ÑÑŒÐºÐ° Ñ‚ÐµÑ€Ð¸Ñ‚Ð¾Ñ€Ñ–Ñ Ð² Ð†Ð½Ð´Ñ–Ð¹ÑÑŒÐºÐ¾Ð¼Ñƒ Ð¾ÐºÐµÐ°Ð½Ñ– | EA39: Ø¨Ø±Ø·Ø§Ù†ÙˆÛŒ Ø¨Ø­Ø±ÛÙ†Ø¯ Ú©Ø§ Ø®Ø·Û | EB39: LÃ£nh thá»• áº¤n Äá»™ DÆ°Æ¡ng thuá»™c Anh | EC39: è‹±å±žå°åº¦æ´‹é¢†åœ° | ED39: è‹±å±¬å°åº¦æ´‹é ˜åœ° | EE39: Admin-0 dependency | EG39: Admin-0 dependency
A40: Brazil | B40: Admin-0 country | C40: 0 | D40: 2 | E40: Brazil | F40: BRA | G40: 0 | H40: 2 | I40: Sovereign country | J40: 1 | K40: Brazil | L40: BRA | M40: 0 | N40: Brazil | O40: BRA | P40: 0 | Q40: Brazil | R40: BRA | S40: 0 | T40: Brazil | U40: BRA | V40: Brazil | X40: Brazil | Y40: BR | Z40: Federative Republic of Brazil | AB40: Brazil | AE40: Brazil | AG40: 5 | AH40: 6 | AI40: 5 | AJ40: 7 | AK40: 211049527 | AL40: 17 | AM40: 2019 | AN40: 1839758 | AO40: 2019 | AP40: 3. Emerging region: BRIC | AQ40: 3. Upper middle income | AR40: BR | AS40: BR | AT40: BR | AU40: BRA | AV40: BRA | AW40: 76 | AX40: 76 | AY40: 76 | AZ40: BR | BA40: BRA | BB40: 23424768 | BC40: 23424768 | BD40: Exact WOE match as country | BE40: BRA | BG40: BRA | BH40: BRA | BI40: BRA | BJ40: BRA | BK40: BRA | BL40: BRA | BM40: BRA | BN40: BRA | BO40: BRA | BP40: BRA | BQ40: BRA | BR40: BRA | BS40: BRA | BT40: BRA | BU40: BRA | BV40: BRA | BW40: BRA | BX40: BRA | BY40: BRA | BZ40: BRA | CA40: BRA | CB40: BRA | CC40: BRA | CD40: BRA | CE40: BRA | CF40: BRA | CG40: BRA | CH40: BRA | CI40: BRA | CJ40: BRA | CK40: BRA | CL40: BRA | CM40: -99 | CN40: -99 | CO40: South America | CP40: Americas | CQ40: South America | CR40: Latin America & Caribbean | CS40: 6 | CT40: 6 | CU40: 6 | CV40: -99 | CW40: 1 | CX40: 0 | CY40: 1.7 | CZ40: 5.7 | DA40: -49.55945 | DB40: -12.098687 | DC40: 1159320441 | DD40: Q155 | DE40: Ø§Ù„Ø¨Ø±Ø§Ø²ÙŠÙ„ | DF40: à¦¬à§à¦°à¦¾à¦œà¦¿à¦² | DG40: Brasilien | DH40: Brazil | DI40: Brasil | DJ40: Ø¨Ø±Ø²ÛŒÙ„ | DK40: BrÃ©sil | DL40: Î’ÏÎ±Î¶Î¹Î»Î¯Î± | DM40: ×‘×¨×–×™×œ | DN40: à¤¬à¥à¤°à¤¾à¤œà¤¼à¥€à¤² | DO40: BrazÃ­lia | DP40: Brasil | DQ40: Brasile | DR40: ãƒ–ãƒ©ã‚¸ãƒ« | DS40: ë¸Œë¼ì§ˆ | DT40: BraziliÃ« | DU40: Brazylia | DV40: Brasil | DW40: Ð‘Ñ€Ð°Ð·Ð¸Ð»Ð¸Ñ | DX40: Brasilien | DY40: Brezilya | DZ40: Ð‘Ñ€Ð°Ð·Ð¸Ð»Ñ–Ñ | EA40: Ø¨Ø±Ø§Ø²ÛŒÙ„ | EB40: Brasil | EC40: å·´è¥¿ | ED40: å·´è¥¿ | EE40: Admin-0 country | EG40: Admin-0 country
A41: Brazilian I. | B41: Admin-0 country | C41: 0 | D41: 9 | E41: Brazilian Island | F41: BRI | G41: 0 | H41: 2 | I41: Indeterminate | K41: Brazilian Island | L41: BRI | M41: 0 | N41: Brazilian Island | O41: BRI | P41: 0 | Q41: Brazilian Island | R41: BRI | S41: 1 | T41: Brazilian Island | U41: B85 | V41: Brazilian Island | AD41: Claimed by Brazil and Uruguay | AE41: Brazil (Brazilian I.) | AG41: 1 | AH41: 5 | AI41: 2 | AJ41: 3 | AK41: 0 | AL41: 1 | AM41: 2019 | AN41: 0 | AO41: 2019 | AP41: 3. Emerging region: BRIC | AQ41: 3. Upper middle income | AR41: -99 | AS41: -99 | AT41: BR | AU41: -99 | AV41: BRA | AW41: -99 | AX41: 76 | AY41: -99 | AZ41: -99 | BA41: -99 | BB41: -99 | BC41: -99 | BD41: No WOE equivalent. | BE41: -99 | BG41: -99 | BH41: BRI | BI41: BRI | BJ41: BRI | BK41: BRI | BL41: BRI | BM41: BRI | BN41: BRI | BO41: BRI | BP41: BRI | BQ41: BRI | BR41: BRI | BS41: BRA | BT41: BRI | BU41: BRI | BV41: BRI | BW41: BRI | BX41: BRI | BY41: BRI | BZ41: BRI | CA41: BRI | CB41: BRI | CC41: BRI | CD41: BRI | CE41: BRI | CF41: BRI | CG41: BRI | CH41: BRI | CI41: BRI | CJ41: BRI | CK41: BRI | CL41: BRI | CM41: -99 | CN41: -99 | CO41: South America | CP41: Americas | CQ41: South America | CR41: Latin America & Caribbean | CS41: 12 | CT41: 16 | CU41: 0 | CV41: -99 | CW41: -99 | CX41: 7 | CY41: 7.7 | CZ41: 9 | DA41: -57.623042 | DB41: -30.187555 | DC41: 1729632181 | DD41: Q2093778 | DE41: Ø¨Ø±Ø§Ø²ÙŠÙ„ÙŠØ§Ù† Ø¢ÙŠÙ„Ø§Ù†Ø¯ | DF41: à¦¬à§à¦°à¦¾à¦œà¦¿à¦²à¦¿à§Ÿà¦¾à¦¨ à¦†à¦‡à¦²à§à¦¯à¦¾à¦¨à§à¦¡ | DG41: Isla Brasilera | DH41: Brazilian Island | DI41: Isla Brasilera | DJ41: Ø¬Ø²ÛŒØ±Ù‡ Ø¨Ø±Ø²ÛŒÙ„ÛŒ | DK41: Ilha Brasileira | DL41: ÎœÏ€ÏÎ±Î¶Î¯Î»Î¹Î±Î½ Î†Î¹Î»Î±Î½Ï„ | DM41: ××™ ×‘×¨×–×™×œ××™ | DN41: à¤¬à¥à¤°à¤¾à¤œà¤¼à¥€à¤²à¤¿à¤¯à¤¨ à¤†à¤‡à¤²à¥ˆà¤‚à¤¡ | DO41: Brazil-sziget | DP41: Brazilian Island | DQ41: Isola brasiliana | DR41: ãƒ–ãƒ©ã‚¸ãƒ¬ã‚¤ãƒ©å³¶ | DS41: ë¸Œë¼ì§ˆë¦¬ì•ˆ ì•„ì¼ëžœë“œ | DT41: Brazilian Island | DU41: Isla Brasilera | DV41: Ilha Brasileira | DW41: Ð¾ÑÑ‚Ñ€Ð¾Ð² Ð‘Ñ€Ð°Ð·Ð¸Ð»ÐµÑ€Ð° | DX41: Isla BrasileÃ±a | DY41: Brezilya AdasÄ± | DZ41: ÐžÑÑ‚Ñ€Ñ–Ð² Ð‘Ñ€Ð°Ð·Ð¸Ð»ÑŒÑÑŒÐºÐ¸Ð¹ | EA41: Ø¨Ø±Ø§Ø²ÛŒÙ„ÛŒÙ† Ø¢Ø¦ÛŒ | EB41: Äáº£o Brazilian | EC41: å·´è¥¿å²› | ED41: å·´è¥¿å³¶ | EE41: Unrecognized | EG41: Unrecognized
A42: British Virgin Islands | B42: Admin-0 country | C42: 3 | D42: 6 | E42: United Kingdom | F42: GB1 | G42: 1 | H42: 2 | I42: Dependency | J42: 1 | K42: British Virgin Islands | L42: VGB | M42: 0 | N42: British Virgin Islands | O42: VGB | P42: 0 | Q42: British Virgin Islands | R42: VGB | S42: 0 | T42: British Virgin Islands | U42: VGB | V42: British Virgin Is. | X42: V.I. (Br.) | Y42: VG | Z42: British Virgin Islands | AB42: British Virgin Islands | AC42: U.K. | AE42: British Virgin Islands | AG42: 6 | AH42: 6 | AI42: 6 | AJ42: 3 | AK42: 30030 | AL42: 7 | AM42: 2019 | AN42: 500 | AO42: 2017 | AP42: 2. Developed region: nonG7 | AQ42: 1. High income: OECD | AR42: VI | AS42: VG | AT42: VG | AU42: VGB | AV42: VGB | AW42: 92 | AX42: 92 | AY42: 92 | AZ42: -99 | BA42: -99 | BB42: 23424983 | BC42: 23424983 | BD42: Exact WOE match as country | BE42: VGB | BG42: VGB | BH42: VGB | BI42: VGB | BJ42: VGB | BK42: VGB | BL42: VGB | BM42: VGB | BN42: VGB | BO42: VGB | BP42: VGB | BQ42: VGB | BR42: VGB | BS42: VGB | BT42: VGB | BU42: VGB | BV42: VGB | BW42: VGB | BX42: VGB | BY42: VGB | BZ42: VGB | CA42: VGB | CB42: VGB | CC42: VGB | CD42: VGB | CE42: VGB | CF42: VGB | CG42: VGB | CH42: VGB | CI42: VGB | CJ42: VGB | CK42: VGB | CL42: VGB | CM42: -99 | CN42: -99 | CO42: North America | CP42: Americas | CQ42: Caribbean | CR42: Latin America & Caribbean | CS42: 18 | CT42: 22 | CU42: 10 | CV42: 3 | CW42: -99 | CX42: 0 | CY42: 5 | CZ42: 9.5 | DA42: -64.63661 | DB42: 18.426606 | DC42: 1159320739 | DD42: Q25305 | DE42: Ø¬Ø²Ø± Ø§Ù„Ø¹Ø°Ø±Ø§Ø¡ Ø§Ù„Ø¨Ø±ÙŠØ·Ø§Ù†ÙŠØ© | DF42: à¦¬à§à¦°à¦¿à¦Ÿà¦¿à¦¶ à¦­à¦¾à¦°à§à¦œà¦¿à¦¨ à¦¦à§à¦¬à§€à¦ªà¦ªà§à¦žà§à¦œ | DG42: Britische Jungferninseln | DH42: British Virgin Islands | DI42: Islas VÃ­rgenes BritÃ¡nicas | DJ42: Ø¬Ø²Ø§ÛŒØ± ÙˆÛŒØ±Ø¬ÛŒÙ† Ø¨Ø±ÛŒØªØ§Ù†ÛŒØ§ | DK42: Ã®les Vierges britanniques | DL42: Î’ÏÎµÏ„Î±Î½Î¹ÎºÎ­Ï‚ Î Î±ÏÎ¸Î­Î½Î¿Î¹ ÎÎ®ÏƒÎ¿Î¹ | DM42: ××™×™ ×”×‘×ª×•×œ×” ×”×‘×¨×™×˜×™×™× | DN42: à¤¬à¥à¤°à¤¿à¤Ÿà¤¿à¤¶ à¤µà¤°à¥à¤œà¤¿à¤¨ à¤¦à¥à¤µà¥€à¤ªà¤¸à¤®à¥‚à¤¹ | DO42: Brit Virgin-szigetek | DP42: Kepulauan Virgin Britania Raya | DQ42: Isole Vergini britanniche | DR42: ã‚¤ã‚®ãƒªã‚¹é ˜ãƒ´ã‚¡ãƒ¼ã‚¸ãƒ³è«¸å³¶ | DS42: ì˜êµ­ë ¹ ë²„ì§„ì•„ì¼ëžœë“œ | DT42: Britse Maagdeneilanden | DU42: Brytyjskie Wyspy Dziewicze | DV42: Ilhas Virgens BritÃ¢nicas | DW42: Ð‘Ñ€Ð¸Ñ‚Ð°Ð½ÑÐºÐ¸Ðµ Ð’Ð¸Ñ€Ð³Ð¸Ð½ÑÐºÐ¸Ðµ Ð¾ÑÑ‚Ñ€Ð¾Ð²Ð° | DX42: Brittiska JungfruÃ¶arna | DY42: Britanya Virjin AdalarÄ± | DZ42: Ð‘Ñ€Ð¸Ñ‚Ð°Ð½ÑÑŒÐºÑ– Ð’Ñ–Ñ€Ð³Ñ–Ð½ÑÑŒÐºÑ– Ð¾ÑÑ‚Ñ€Ð¾Ð²Ð¸ | EA42: Ø¨Ø±Ø·Ø§Ù†ÙˆÛŒ Ø¬Ø²Ø§Ø¦Ø± ÙˆØ±Ø¬Ù† | EB42: Quáº§n Ä‘áº£o Virgin thuá»™c Anh | EC42: è‹±å±žç»´å°”äº¬ç¾¤å²› | ED42: è‹±å±¬ç¶­äº¬ç¾¤å³¶ | EE42: Admin-0 dependency | EG42: Admin-0 dependency
A43: Brunei | B43: Admin-0 country | C43: 0 | D43: 6 | E43: Brunei | F43: BRN | G43: 0 | H43: 2 | I43: Sovereign country | J43: 1 | K43: Brunei | L43: BRN | M43: 0 | N43: Brunei | O43: BRN | P43: 0 | Q43: Brunei | R43: BRN | S43: 0 | T43: Brunei Darussalam | U43: BRN | V43: Brunei | X43: Brunei | Y43: BN | Z43: Negara Brunei Darussalam | AB43: Brunei | AE43: Brunei | AG43: 4 | AH43: 6 | AI43: 6 | AJ43: 12 | AK43: 433285 | AL43: 10 | AM43: 2019 | AN43: 13469 | AO43: 2019 | AP43: 6. Developing region | AQ43: 2. High income: nonOECD | AR43: BX | AS43: BN | AT43: BN | AU43: BRN | AV43: BRN | AW43: 96 | AX43: 96 | AY43: 96 | AZ43: BN | BA43: BRN | BB43: 23424773 | BC43: 23424773 | BD43: Exact WOE match as country | BE43: BRN | BG43: BRN | BH43: BRN | BI43: BRN | BJ43: BRN | BK43: BRN | BL43: BRN | BM43: BRN | BN43: BRN | BO43: BRN | BP43: BRN | BQ43: BRN | BR43: BRN | BS43: BRN | BT43: BRN | BU43: BRN | BV43: BRN | BW43: BRN | BX43: BRN | BY43: BRN | BZ43: BRN | CA43: BRN | CB43: BRN | CC43: BRN | CD43: BRN | CE43: BRN | CF43: BRN | CG43: BRN | CH43: BRN | CI43: BRN | CJ43: BRN | CK43: BRN | CL43: BRN | CM43: -99 | CN43: -99 | CO43: Asia | CP43: Asia | CQ43: South-Eastern Asia | CR43: East Asia & Pacific | CS43: 6 | CT43: 17 | CU43: 6 | CV43: 2 | CW43: 1 | CX43: 0 | CY43: 4 | CZ43: 9 | DA43: 114.55194 | DB43: 4.448298 | DC43: 1159320451 | DD43: Q921 | DE43: Ø¨Ø±ÙˆÙ†Ø§ÙŠ | DF43: à¦¬à§à¦°à§à¦¨à¦¾à¦‡ | DG43: Brunei | DH43: Brunei | DI43: BrunÃ©i | DJ43: Ø¨Ø±ÙˆÙ†Ø¦ÛŒ | DK43: Brunei | DL43: ÎœÏ€ÏÎ¿Ï…Î½Î­Î¹ | DM43: ×‘×¨×•× ×™×™ | DN43: à¤¬à¥à¤°à¥à¤¨à¥‡à¤ˆ | DO43: Brunei | DP43: Brunei Darussalam | DQ43: Brunei | DR43: ãƒ–ãƒ«ãƒã‚¤ | DS43: ë¸Œë£¨ë‚˜ì´ | DT43: Brunei | DU43: Brunei | DV43: Brunei | DW43: Ð‘Ñ€ÑƒÐ½ÐµÐ¹ | DX43: Brunei | DY43: Brunei | DZ43: Ð‘Ñ€ÑƒÐ½ÐµÐ¹ | EA43: Ø¨Ø±ÙˆÙ†Ø§Ø¦ÛŒ Ø¯Ø§Ø± Ø§Ù„Ø³Ù„Ø§Ù… | EB43: Brunei | EC43: æ–‡èŽ± | ED43: æ±¶èŠ | EE43: Admin-0 country | EG43: Admin-0 country
A44: Bulgaria | B44: Admin-0 country | C44: 0 | D44: 4 | E44: Bulgaria | F44: BGR | G44: 0 | H44: 2 | I44: Sovereign country | J44: 1 | K44: Bulgaria | L44: BGR | M44: 0 | N44: Bulgaria | O44: BGR | P44: 0 | Q44: Bulgaria | R44: BGR | S44: 0 | T44: Bulgaria | U44: BGR | V44: Bulgaria | X44: Bulg. | Y44: BG | Z44: Republic of Bulgaria | AB44: Bulgaria | AE44: Bulgaria | AG44: 4 | AH44: 5 | AI44: 1 | AJ44: 8 | AK44: 6975761 | AL44: 13 | AM44: 2019 | AN44: 68558 | AO44: 2019 | AP44: 2. Developed region: nonG7 | AQ44: 3. Upper middle income | AR44: BU | AS44: BG | AT44: BG | AU44: BGR | AV44: BGR | AW44: 100 | AX44: 100 | AY44: 100 | AZ44: BG | BA44: BGR | BB44: 23424771 | BC44: 23424771 | BD44: Exact WOE match as country | BE44: BGR | BG44: BGR | BH44: BGR | BI44: BGR | BJ44: BGR | BK44: BGR | BL44: BGR | BM44: BGR | BN44: BGR | BO44: BGR | BP44: BGR | BQ44: BGR | BR44: BGR | BS44: BGR | BT44: BGR | BU44: BGR | BV44: BGR | BW44: BGR | BX44: BGR | BY44: BGR | BZ44: BGR | CA44: BGR | CB44: BGR | CC44: BGR | CD44: BGR | CE44: BGR | CF44: BGR | CG44: BGR | CH44: BGR | CI44: BGR | CJ44: BGR | CK44: BGR | CL44: BGR | CM44: -99 | CN44: -99 | CO44: Europe | CP44: Europe | CQ44: Eastern Europe | CR44: Europe & Central Asia | CS44: 8 | CT44: 8 | CU44: 5 | CV44: -99 | CW44: 1 | CX44: 0 | CY44: 4 | CZ44: 9 | DA44: 25.15709 | DB44: 42.508785 | DC44: 1159320409 | DD44: Q219 | DE44: Ø¨Ù„ØºØ§Ø±ÙŠØ§ | DF44: à¦¬à§à¦²à¦—à§‡à¦°à¦¿à¦¯à¦¼à¦¾ | DG44: Bulgarien | DH44: Bulgaria | DI44: Bulgaria | DJ44: Ø¨Ù„ØºØ§Ø±Ø³ØªØ§Ù† | DK44: Bulgarie | DL44: Î’Î¿Ï…Î»Î³Î±ÏÎ¯Î± | DM44: ×‘×•×œ×’×¨×™×” | DN44: à¤¬à¥à¤²à¥à¤—à¤¾à¤°à¤¿à¤¯à¤¾ | DO44: BulgÃ¡ria | DP44: Bulgaria | DQ44: Bulgaria | DR44: ãƒ–ãƒ«ã‚¬ãƒªã‚¢ | DS44: ë¶ˆê°€ë¦¬ì•„ | DT44: Bulgarije | DU44: BuÅ‚garia | DV44: BulgÃ¡ria | DW44: Ð‘Ð¾Ð»Ð³Ð°Ñ€Ð¸Ñ | DX44: Bulgarien | DY44: Bulgaristan | DZ44: Ð‘Ð¾Ð»Ð³Ð°Ñ€Ñ–Ñ | EA44: Ø¨Ù„ØºØ§Ø±ÛŒÛ | EB44: Bulgaria | EC44: ä¿åŠ åˆ©äºš | ED44: ä¿åŠ åˆ©äºž | EE44: Admin-0 country | EG44: Admin-0 country
A45: Burkina Faso | B45: Admin-0 country | C45: 0 | D45: 3 | E45: Burkina Faso | F45: BFA | G45: 0 | H45: 2 | I45: Sovereign country | J45: 1 | K45: Burkina Faso | L45: BFA | M45: 0 | N45: Burkina Faso | O45: BFA | P45: 0 | Q45: Burkina Faso | R45: BFA | S45: 0 | T45: Burkina Faso | U45: BFA | V45: Burkina Faso | X45: B.F. | Y45: BF | Z45: Burkina Faso | AB45: Burkina Faso | AE45: Burkina Faso | AG45: 2 | AH45: 1 | AI45: 5 | AJ45: 11 | AK45: 20321378 | AL45: 15 | AM45: 2019 | AN45: 15990 | AO45: 2019 | AP45: 7. Least developed region | AQ45: 5. Low income | AR45: UV | AS45: BF | AT45: BF | AU45: BFA | AV45: BFA | AW45: 854 | AX45: 854 | AY45: 854 | AZ45: BF | BA45: BFA | BB45: 23424978 | BC45: 23424978 | BD45: Exact WOE match as country | BE45: BFA | BG45: BFA | BH45: BFA | BI45: BFA | BJ45: BFA | BK45: BFA | BL45: BFA | BM45: BFA | BN45: BFA | BO45: BFA | BP45: BFA | BQ45: BFA | BR45: BFA | BS45: BFA | BT45: BFA | BU45: BFA | BV45: BFA | BW45: BFA | BX45: BFA | BY45: BFA | BZ45: BFA | CA45: BFA | CB45: BFA | CC45: BFA | CD45: BFA | CE45: BFA | CF45: BFA | CG45: BFA | CH45: BFA | CI45: BFA | CJ45: BFA | CK45: BFA | CL45: BFA | CM45: -99 | CN45: -99 | CO45: Africa | CP45: Africa | CQ45: Western Africa | CR45: Sub-Saharan Africa | CS45: 12 | CT45: 12 | CU45: 4 | CV45: -99 | CW45: 1 | CX45: 0 | CY45: 3 | CZ45: 8 | DA45: -1.36388 | DB45: 12.673048 | DC45: 1159320405 | DD45: Q965 | DE45: Ø¨ÙˆØ±ÙƒÙŠÙ†Ø§ ÙØ§Ø³Ùˆ | DF45: à¦¬à§à¦°à§à¦•à¦¿à¦¨à¦¾ à¦«à¦¾à¦¸à§‹ | DG45: Burkina Faso | DH45: Burkina Faso | DI45: Burkina Faso | DJ45: Ø¨ÙˆØ±Ú©ÛŒÙ†Ø§ÙØ§Ø³Ùˆ | DK45: Burkina Faso | DL45: ÎœÏ€Î¿Ï…ÏÎºÎ¯Î½Î± Î¦Î¬ÏƒÎ¿ | DM45: ×‘×•×¨×§×™× ×” ×¤××¡×• | DN45: à¤¬à¥à¤°à¥à¤•à¤¿à¤¨à¤¾ à¤«à¤¾à¤¸à¥‹ | DO45: Burkina Faso | DP45: Burkina Faso | DQ45: Burkina Faso | DR45: ãƒ–ãƒ«ã‚­ãƒŠãƒ•ã‚¡ã‚½ | DS45: ë¶€ë¥´í‚¤ë‚˜íŒŒì†Œ | DT45: Burkina Faso | DU45: Burkina Faso | DV45: Burkina Faso | DW45: Ð‘ÑƒÑ€ÐºÐ¸Ð½Ð°-Ð¤Ð°ÑÐ¾ | DX45: Burkina Faso | DY45: Burkina Faso | DZ45: Ð‘ÑƒÑ€ÐºÑ–Ð½Ð°-Ð¤Ð°ÑÐ¾ | EA45: Ø¨Ø±Ú©ÛŒÙ†Ø§ ÙØ§Ø³Ùˆ | EB45: Burkina Faso | EC45: å¸ƒåŸºçº³æ³•ç´¢ | ED45: å¸ƒåŸºç´æ³•ç´¢ | EE45: Admin-0 country | EG45: Admin-0 country
A46: Burundi | B46: Admin-0 country | C46: 0 | D46: 6 | E46: Burundi | F46: BDI | G46: 0 | H46: 2 | I46: Sovereign country | J46: 1 | K46: Burundi | L46: BDI | M46: 0 | N46: Burundi | O46: BDI | P46: 0 | Q46: Burundi | R46: BDI | S46: 0 | T46: Burundi | U46: BDI | V46: Burundi | X46: Bur. | Y46: BI | Z46: Republic of Burundi | AB46: Burundi | AE46: Burundi | AG46: 2 | AH46: 2 | AI46: 5 | AJ46: 8 | AK46: 11530580 | AL46: 14 | AM46: 2019 | AN46: 3012 | AO46: 2019 | AP46: 7. Least developed region | AQ46: 5. Low income | AR46: BY | AS46: BI | AT46: BI | AU46: BDI | AV46: BDI | AW46: 108 | AX46: 108 | AY46: 108 | AZ46: BI | BA46: BDI | BB46: 23424774 | BC46: 23424774 | BD46: Exact WOE match as country | BE46: BDI | BG46: BDI | BH46: BDI | BI46: BDI | BJ46: BDI | BK46: BDI | BL46: BDI | BM46: BDI | BN46: BDI | BO46: BDI | BP46: BDI | BQ46: BDI | BR46: BDI | BS46: BDI | BT46: BDI | BU46: BDI | BV46: BDI | BW46: BDI | BX46: BDI | BY46: BDI | BZ46: BDI | CA46: BDI | CB46: BDI | CC46: BDI | CD46: BDI | CE46: BDI | CF46: BDI | CG46: BDI | CH46: BDI | CI46: BDI | CJ46: BDI | CK46: BDI | CL46: BDI | CM46: -99 | CN46: -99 | CO46: Africa | CP46: Africa | CQ46: Eastern Africa | CR46: Sub-Saharan Africa | CS46: 7 | CT46: 7 | CU46: 4 | CV46: -99 | CW46: 1 | CX46: 0 | CY46: 4 | CZ46: 9 | DA46: 29.917086 | DB46: -3.332836 | DC46: 1159320387 | DD46: Q967 | DE46: Ø¨ÙˆØ±ÙˆÙ†Ø¯ÙŠ | DF46: à¦¬à§à¦°à§à¦¨à§à¦¡à¦¿ | DG46: Burundi | DH46: Burundi | DI46: Burundi | DJ46: Ø¨ÙˆØ±ÙˆÙ†Ø¯ÛŒ | DK46: Burundi | DL46: ÎœÏ€Î¿Ï…ÏÎ¿ÏÎ½Ï„Î¹ | DM46: ×‘×•×¨×•× ×“×™ | DN46: à¤¬à¥à¤°à¥à¤£à¥à¤¡à¥€ | DO46: Burundi | DP46: Burundi | DQ46: Burundi | DR46: ãƒ–ãƒ«ãƒ³ã‚¸ | DS46: ë¶€ë£¬ë”” | DT46: Burundi | DU46: Burundi | DV46: Burundi | DW46: Ð‘ÑƒÑ€ÑƒÐ½Ð´Ð¸ | DX46: Burundi | DY46: Burundi | DZ46: Ð‘ÑƒÑ€ÑƒÐ½Ð´Ñ– | EA46: Ø¨Ø±ÙˆÙ†ÚˆÛŒ | EB46: Burundi | EC46: å¸ƒéš†è¿ª | ED46: è’²éš†åœ° | EE46: Admin-0 country | EG46: Admin-0 country
A47: Cóte d'Ivoire | B47: Admin-0 country | C47: 0 | D47: 3 | E47: Ivory Coast | F47: CIV | G47: 0 | H47: 2 | I47: Sovereign country | J47: 1 | K47: Ivory Coast | L47: CIV | M47: 0 | N47: Ivory Coast | O47: CIV | P47: 0 | Q47: Ivory Coast | R47: CIV | S47: 0 | T47: CÃ´te d'Ivoire | U47: CIV | V47: CÃ´te d'Ivoire | X47: I.C. | Y47: CI | Z47: Republic of Ivory Coast | AA47: Republic of Cote D'Ivoire | AB47: Cote D'ivoire | AE47: CÃ´te d'Ivoire | AG47: 4 | AH47: 6 | AI47: 3 | AJ47: 3 | AK47: 25716544 | AL47: 15 | AM47: 2019 | AN47: 58539 | AO47: 2019 | AP47: 6. Developing region | AQ47: 4. Lower middle income | AR47: IV | AS47: CI | AT47: CI | AU47: CIV | AV47: CIV | AW47: 384 | AX47: 384 | AY47: 384 | AZ47: CI | BA47: CIV | BB47: 23424854 | BC47: 23424854 | BD47: Exact WOE match as country | BE47: CIV | BG47: CIV | BH47: CIV | BI47: CIV | BJ47: CIV | BK47: CIV | BL47: CIV | BM47: CIV | BN47: CIV | BO47: CIV | BP47: CIV | BQ47: CIV | BR47: CIV | BS47: CIV | BT47: CIV | BU47: CIV | BV47: CIV | BW47: CIV | BX47: CIV | BY47: CIV | BZ47: CIV | CA47: CIV | CB47: CIV | CC47: CIV | CD47: CIV | CE47: CIV | CF47: CIV | CG47: CIV | CH47: CIV | CI47: CIV | CJ47: CIV | CK47: CIV | CL47: CIV | CM47: -99 | CN47: -99 | CO47: Africa | CP47: Africa | CQ47: Western Africa | CR47: Sub-Saharan Africa | CS47: 13 | CT47: 13 | CU47: 4 | CV47: -99 | CW47: 1 | CX47: 0 | CY47: 2.5 | CZ47: 8 | DA47: -5.568618 | DB47: 7.49139 | DC47: 1159320507 | DD47: Q1008 | DE47: Ø³Ø§Ø­Ù„ Ø§Ù„Ø¹Ø§Ø¬ | DF47: à¦•à§‹à¦¤ à¦¦à¦¿à¦­à§‹à¦¯à¦¼à¦¾à¦° | DG47: ElfenbeinkÃ¼ste | DH47: Ivory Coast | DI47: Costa de Marfil | DJ47: Ø³Ø§Ø­Ù„ Ø¹Ø§Ø¬ | DK47: CÃ´te d'Ivoire | DL47: Î‘ÎºÏ„Î® Î•Î»ÎµÏ†Î±Î½Ï„Î¿ÏƒÏ„Î¿Ï | DM47: ×—×•×£ ×”×©× ×”×‘ | DN47: à¤•à¥‹à¤¤ à¤¦à¤¿à¤µà¥à¤µà¤¾à¤° | DO47: ElefÃ¡ntcsontpart | DP47: Pantai Gading | DQ47: Costa d'Avorio | DR47: ã‚³ãƒ¼ãƒˆã‚¸ãƒœãƒ¯ãƒ¼ãƒ« | DS47: ì½”íŠ¸ë””ë¶€ì•„ë¥´ | DT47: Ivoorkust | DU47: WybrzeÅ¼e KoÅ›ci SÅ‚oniowej | DV47: Costa do Marfim | DW47: ÐšÐ¾Ñ‚-Ð´â€™Ð˜Ð²ÑƒÐ°Ñ€ | DX47: Elfenbenskusten | DY47: FildiÅŸi Sahili | DZ47: ÐšÐ¾Ñ‚-Ð´'Ð†Ð²ÑƒÐ°Ñ€ | EA47: Ú©ÙˆØª Ø¯Ø§ÙˆÙˆØ§Øº | EB47: Bá» Biá»ƒn NgÃ | EC47: ç§‘ç‰¹è¿ªç“¦ | ED47: è±¡ç‰™æµ·å²¸ | EE47: Admin-0 country | EG47: Admin-0 country
A48: Cabo Verde | B48: Admin-0 country | C48: 3 | D48: 4 | E48: Cabo Verde | F48: CPV | G48: 0 | H48: 2 | I48: Sovereign country | J48: 1 | K48: Cabo Verde | L48: CPV | M48: 0 | N48: Cabo Verde | O48: CPV | P48: 0 | Q48: Cabo Verde | R48: CPV | S48: 0 | T48: Republic of Cabo Verde | U48: CPV | V48: Cabo Verde | X48: C.Vd. | Y48: CV | Z48: Republic of Cabo Verde | AB48: Cabo Verde | AE48: Cabo Verde | AG48: 1 | AH48: 1 | AI48: 4 | AJ48: 11 | AK48: 549935 | AL48: 11 | AM48: 2019 | AN48: 1981 | AO48: 2019 | AP48: 6. Developing region | AQ48: 4. Lower middle income | AR48: CV | AS48: CV | AT48: CV | AU48: CPV | AV48: CPV | AW48: 132 | AX48: 132 | AY48: 132 | AZ48: CV | BA48: CPV | BB48: 23424794 | BC48: 23424794 | BD48: Exact WOE match as country | BE48: CPV | BG48: CPV | BH48: CPV | BI48: CPV | BJ48: CPV | BK48: CPV | BL48: CPV | BM48: CPV | BN48: CPV | BO48: CPV | BP48: CPV | BQ48: CPV | BR48: CPV | BS48: CPV | BT48: CPV | BU48: CPV | BV48: CPV | BW48: CPV | BX48: CPV | BY48: CPV | BZ48: CPV | CA48: CPV | CB48: CPV | CC48: CPV | CD48: CPV | CE48: CPV | CF48: CPV | CG48: CPV | CH48: CPV | CI48: CPV | CJ48: CPV | CK48: CPV | CL48: CPV | CM48: -99 | CN48: -99 | CO48: Africa | CP48: Africa | CQ48: Western Africa | CR48: Sub-Saharan Africa | CS48: 10 | CT48: 22 | CU48: 5 | CV48: -99 | CW48: 1 | CX48: 0 | CY48: 4 | CZ48: 9 | DA48: -23.639434 | DB48: 15.074761 | DC48: 1159320523 | DD48: Q1011 | DE48: Ø§Ù„Ø±Ø£Ø³ Ø§Ù„Ø£Ø®Ø¶Ø± | DF48: à¦•à¦¾à¦¬à§ à¦­à§‡à¦°à§à¦¦à¦¿ | DG48: Kap Verde | DH48: Cape Verde | DI48: Cabo Verde | DJ48: Ú©ÛŒÙ¾ ÙˆØ±Ø¯ | DK48: Cap-Vert | DL48: Î ÏÎ¬ÏƒÎ¹Î½Î¿ Î‘ÎºÏÏ‰Ï„Î®ÏÎ¹Î¿ | DM48: ×›×£ ×•×¨×“×” | DN48: à¤•à¥‡à¤ª à¤µà¤°à¥à¤¦à¥‡ | DO48: ZÃ¶ld-foki KÃ¶ztÃ¡rsasÃ¡g | DP48: Tanjung Verde | DQ48: Capo Verde | DR48: ã‚«ãƒ¼ãƒœãƒ™ãƒ«ãƒ‡ | DS48: ì¹´ë³´ë² ë¥´ë° | DT48: KaapverdiÃ« | DU48: Republika Zielonego PrzylÄ…dka | DV48: Cabo Verde | DW48: ÐšÐ°Ð±Ð¾-Ð’ÐµÑ€Ð´Ðµ | DX48: Kap Verde | DY48: YeÅŸil Burun AdalarÄ± | DZ48: ÐšÐ°Ð±Ð¾-Ð’ÐµÑ€Ð´Ðµ | EA48: Ú©ÛŒÙ¾ ÙˆØ±ÚˆÛŒ | EB48: Cabo Verde | EC48: ä½›å¾—è§’ | ED48: ç¶­å¾·è§’ | EE48: Admin-0 country | EG48: Admin-0 country
A49: Cambodia | B49: Admin-0 country | C49: 0 | D49: 3 | E49: Cambodia | F49: KHM | G49: 0 | H49: 2 | I49: Sovereign country | J49: 1 | K49: Cambodia | L49: KHM | M49: 0 | N49: Cambodia | O49: KHM | P49: 0 | Q49: Cambodia | R49: KHM | S49: 0 | T49: Cambodia | U49: KHM | V49: Cambodia | X49: Camb. | Y49: KH | Z49: Kingdom of Cambodia | AB49: Cambodia | AE49: Cambodia | AG49: 6 | AH49: 3 | AI49: 6 | AJ49: 5 | AK49: 16486542 | AL49: 14 | AM49: 2019 | AN49: 27089 | AO49: 2019 | AP49: 7. Least developed region | AQ49: 5. Low income | AR49: CB | AS49: KH | AT49: KH | AU49: KHM | AV49: KHM | AW49: 116 | AX49: 116 | AY49: 116 | AZ49: KH | BA49: KHM | BB49: 23424776 | BC49: 23424776 | BD49: Exact WOE match as country | BE49: KHM | BG49: KHM | BH49: KHM | BI49: KHM | BJ49: KHM | BK49: KHM | BL49: KHM | BM49: KHM | BN49: KHM | BO49: KHM | BP49: KHM | BQ49: KHM | BR49: KHM | BS49: KHM | BT49: KHM | BU49: KHM | BV49: KHM | BW49: KHM | BX49: KHM | BY49: KHM | BZ49: KHM | CA49: KHM | CB49: KHM | CC49: KHM | CD49: KHM | CE49: KHM | CF49: KHM | CG49: KHM | CH49: KHM | CI49: KHM | CJ49: KHM | CK49: KHM | CL49: KHM | CM49: -99 | CN49: -99 | CO49: Asia | CP49: Asia | CQ49: South-Eastern Asia | CR49: East Asia & Pacific | CS49: 8 | CT49: 8 | CU49: 5 | CV49: -99 | CW49: 1 | CX49: 0 | CY49: 3 | CZ49: 8 | DA49: 104.50487 | DB49: 12.647584 | DC49: 1159320979 | DD49: Q424 | DE49: ÙƒÙ…Ø¨ÙˆØ¯ÙŠØ§ | DF49: à¦•à¦®à§à¦¬à§‹à¦¡à¦¿à¦¯à¦¼à¦¾ | DG49: Kambodscha | DH49: Cambodia | DI49: Camboya | DJ49: Ú©Ø§Ù…Ø¨ÙˆØ¬ | DK49: Cambodge | DL49: ÎšÎ±Î¼Ï€ÏŒÏ„Î¶Î· | DM49: ×§×ž×‘×•×“×™×” | DN49: à¤•à¤®à¥à¤¬à¥‹à¤¡à¤¿à¤¯à¤¾ | DO49: Kambodzsa | DP49: Kamboja | DQ49: Cambogia | DR49: ã‚«ãƒ³ãƒœã‚¸ã‚¢ | DS49: ìº„ë³´ë””ì•„ | DT49: Cambodja | DU49: KambodÅ¼a | DV49: Camboja | DW49: ÐšÐ°Ð¼Ð±Ð¾Ð´Ð¶Ð° | DX49: Kambodja | DY49: KamboÃ§ya | DZ49: ÐšÐ°Ð¼Ð±Ð¾Ð´Ð¶Ð° | EA49: Ú©Ù…Ø¨ÙˆÚˆÛŒØ§ | EB49: Campuchia | EC49: æŸ¬åŸ”å¯¨ | ED49: æŸ¬åŸ”å¯¨ | EE49: Admin-0 country | EG49: Admin-0 country
A50: Cameroon | B50: Admin-0 country | C50: 0 | D50: 3 | E50: Cameroon | F50: CMR | G50: 0 | H50: 2 | I50: Sovereign country | J50: 1 | K50: Cameroon | L50: CMR | M50: 0 | N50: Cameroon | O50: CMR | P50: 0 | Q50: Cameroon | R50: CMR | S50: 0 | T50: Cameroon | U50: CMR | V50: Cameroon | X50: Cam. | Y50: CM | Z50: Republic of Cameroon | AB50: Cameroon | AE50: Cameroon | AG50: 1 | AH50: 4 | AI50: 1 | AJ50: 3 | AK50: 25876380 | AL50: 15 | AM50: 2019 | AN50: 39007 | AO50: 2019 | AP50: 6. Developing region | AQ50: 4. Lower middle income | AR50: CM | AS50: CM | AT50: CM | AU50: CMR | AV50: CMR | AW50: 120 | AX50: 120 | AY50: 120 | AZ50: CM | BA50: CMR | BB50: 23424785 | BC50: 23424785 | BD50: Exact WOE match as country | BE50: CMR | BG50: CMR | BH50: CMR | BI50: CMR | BJ50: CMR | BK50: CMR | BL50: CMR | BM50: CMR | BN50: CMR | BO50: CMR | BP50: CMR | BQ50: CMR | BR50: CMR | BS50: CMR | BT50: CMR | BU50: CMR | BV50: CMR | BW50: CMR | BX50: CMR | BY50: CMR | BZ50: CMR | CA50: CMR | CB50: CMR | CC50: CMR | CD50: CMR | CE50: CMR | CF50: CMR | CG50: CMR | CH50: CMR | CI50: CMR | CJ50: CMR | CK50: CMR | CL50: CMR | CM50: -99 | CN50: -99 | CO50: Africa | CP50: Africa | CQ50: Middle Africa | CR50: Sub-Saharan Africa | CS50: 8 | CT50: 8 | CU50: 4 | CV50: -99 | CW50: 1 | CX50: 0 | CY50: 3 | CZ50: 8 | DA50: 12.473488 | DB50: 4.585041 | DC50: 1159320509 | DD50: Q1009 | DE50: Ø§Ù„ÙƒØ§Ù…ÙŠØ±ÙˆÙ† | DF50: à¦•à§à¦¯à¦¾à¦®à§‡à¦°à§à¦¨ | DG50: Kamerun | DH50: Cameroon | DI50: CamerÃºn | DJ50: Ú©Ø§Ù…Ø±ÙˆÙ† | DK50: Cameroun | DL50: ÎšÎ±Î¼ÎµÏÎ¿ÏÎ½ | DM50: ×§×ž×¨×•×Ÿ | DN50: à¤•à¥ˆà¤®à¤°à¥à¤¨ | DO50: Kamerun | DP50: Kamerun | DQ50: Camerun | DR50: ã‚«ãƒ¡ãƒ«ãƒ¼ãƒ³ | DS50: ì¹´ë©”ë£¬ | DT50: Kameroen | DU50: Kamerun | DV50: CamarÃµes | DW50: ÐšÐ°Ð¼ÐµÑ€ÑƒÐ½ | DX50: Kamerun | DY50: Kamerun | DZ50: ÐšÐ°Ð¼ÐµÑ€ÑƒÐ½ | EA50: Ú©ÛŒÙ…Ø±ÙˆÙ† | EB50: Cameroon | EC50: å–€éº¦éš† | ED50: å–€éº¥éš† | EE50: Admin-0 country | EG50: Admin-0 country
A51: Canada | B51: Admin-0 country | C51: 0 | D51: 2 | E51: Canada | F51: CAN | G51: 0 | H51: 2 | I51: Sovereign country | J51: 1 | K51: Canada | L51: CAN | M51: 0 | N51: Canada | O51: CAN | P51: 0 | Q51: Canada | R51: CAN | S51: 0 | T51: Canada | U51: CAN | V51: Canada | X51: Can. | Y51: CA | Z51: Canada | AB51: Canada | AE51: Canada | AG51: 6 | AH51: 6 | AI51: 2 | AJ51: 2 | AK51: 37589262 | AL51: 15 | AM51: 2019 | AN51: 1736425 | AO51: 2019 | AP51: 1. Developed region: G7 | AQ51: 1. High income: OECD | AR51: CA | AS51: CA | AT51: CA | AU51: CAN | AV51: CAN | AW51: 124 | AX51: 124 | AY51: 124 | AZ51: CA | BA51: CAN | BB51: 23424775 | BC51: 23424775 | BD51: Exact WOE match as country | BE51: CAN | BG51: CAN | BH51: CAN | BI51: CAN | BJ51: CAN | BK51: CAN | BL51: CAN | BM51: CAN | BN51: CAN | BO51: CAN | BP51: CAN | BQ51: CAN | BR51: CAN | BS51: CAN | BT51: CAN | BU51: CAN | BV51: CAN | BW51: CAN | BX51: CAN | BY51: CAN | BZ51: CAN | CA51: CAN | CB51: CAN | CC51: CAN | CD51: CAN | CE51: CAN | CF51: CAN | CG51: CAN | CH51: CAN | CI51: CAN | CJ51: CAN | CK51: CAN | CL51: CAN | CM51: -99 | CN51: -99 | CO51: North America | CP51: Americas | CQ51: Northern America | CR51: North America | CS51: 6 | CT51: 6 | CU51: 4 | CV51: -99 | CW51: 1 | CX51: 0 | CY51: 1.7 | CZ51: 5.7 | DA51: -101.9107 | DB51: 60.324287 | DC51: 1159320467 | DD51: Q16 | DE51: ÙƒÙ†Ø¯Ø§ | DF51: à¦•à¦¾à¦¨à¦¾à¦¡à¦¾ | DG51: Kanada | DH51: Canada | DI51: CanadÃ¡ | DJ51: Ú©Ø§Ù†Ø§Ø¯Ø§ | DK51: Canada | DL51: ÎšÎ±Î½Î±Î´Î¬Ï‚ | DM51: ×§× ×“×” | DN51: à¤•à¤¨à¤¾à¤¡à¤¾ | DO51: Kanada | DP51: Kanada | DQ51: Canada | DR51: ã‚«ãƒŠãƒ€ | DS51: ìºë‚˜ë‹¤ | DT51: Canada | DU51: Kanada | DV51: CanadÃ¡ | DW51: ÐšÐ°Ð½Ð°Ð´Ð° | DX51: Kanada | DY51: Kanada | DZ51: ÐšÐ°Ð½Ð°Ð´Ð° | EA51: Ú©ÛŒÙ†ÛŒÚˆØ§ | EB51: Canada | EC51: åŠ æ‹¿å¤§ | ED51: åŠ æ‹¿å¤§ | EE51: Admin-0 country | EG51: Admin-0 country
A52: Canary Islands | B52: Admin-1 states provinces | C52: 10 | L52: ES-CN | FN52: ESP-5842 | FO52: 5842 | FQ52: ES | FR52: 3 | FU52: Comunidad AutÃ³noma | FV52: Autonomous Community | FX52: ES.CN | GA52: Canary Is. | GB52: 0 | GC52: 0 | GD52: 0 | GE52: 10 | GH52: 0 | GI52: -99 | GJ52: 20 | GK52: 22 | GL52: 5 | GM52: 5 | GP52: 12602109 | GR52: Santa Cruz de Tenerife | GS52: 28.2566 | GT52: -16.6144 | GU52: ESP | GV52: ES-CN | GW52: 5 | GX52: Spain | HA52: 2511173 | HB52: Provincia de Santa Cruz de Tenerife | HC52: -401687 | HD52: Santa Cruz de Tenerife, Provincia de | HE52: 2 | HG52: ES.TF | HJ52: 2 | HM52: SP53 | HN52: 7.7 | HO52: 11 | HP52: 7.7 | HQ52: Q99976 | HR52: Ø³Ø§Ù†ØªØ§ ÙƒØ±ÙˆØ« Ø¯ÙŠ ØªÙŠÙ†ÙŠØ±ÙŠÙÙ‡ | HS52: à¦¸à§à¦¯à¦¾à¦¨à§à¦Ÿà¦¾ à¦•à§à¦°à§à¦œ à¦¦à§‡ à¦Ÿà§‡à¦¨à§‡à¦²à¦¿à¦«à§‡ à¦ªà§à¦°à¦¦à§‡à¦¶ | HT52: Santa Cruz de Tenerife | HU52: Santa Cruz de Tenerife | HV52: Santa Cruz de Tenerife | HW52: Santa Cruz de TÃ©nÃ©rife | HX52: Î£Î¬Î½Ï„Î± ÎšÏÎ¿ÏÎ¸ ÎÏ„Îµ Î¤ÎµÎ½ÎµÏÎ¯Ï†Îµ | HY52: à¤¸à¥ˆà¤‚à¤Ÿà¤¾ à¤•à¥à¤°à¥‚à¤œà¤¼ à¤¡à¥€ à¤Ÿà¥ˆà¤¨à¥‡à¤°à¥€à¤« à¤ªà¥à¤°à¤¾à¤‚à¤¤ | HZ52: Santa Cruz de Tenerife | IA52: Santa Cruz de Tenerife | IB52: Santa Cruz de Tenerife | IC52: ã‚µãƒ³ã‚¿ãƒ»ã‚¯ãƒ«ã‚¹ãƒ»ãƒ‡ãƒ»ãƒ†ãƒãƒªãƒ•ã‚§çœŒ | ID52: ì‚°íƒ€í¬ë£¨ìŠ¤ë°í…Œë„¤ë¦¬íŽ˜ | IE52: Santa Cruz de Tenerife | IF52: Santa Cruz de Tenerife | IG52: Santa Cruz de Tenerife | IH52: Ð¡Ð°Ð½Ñ‚Ð°-ÐšÑ€ÑƒÑ-Ð´Ðµ-Ð¢ÐµÐ½ÐµÑ€Ð¸Ñ„Ðµ | II52: Santa Cruz de Tenerife | IJ52: Santa Cruz de Tenerife Ä°li | IK52: Santa Cruz de Tenerife | IL52: åœ£å…‹é²æ–¯-å¾·ç‰¹å†…é‡Œè´¹çœ | IM52: 1159315577 | IN52: ×¡× ×˜×” ×§×¨×•×– ×“×” ×˜× ×¨×™×£ | IO52: Ð¡Ð°Ð½Ñ‚Ð°-ÐšÑ€ÑƒÑ-Ð´Ðµ-Ð¢ÐµÐ½ÐµÑ€Ð¸Ñ„Ðµ | IP52: ØµÙˆØ¨Û Ø³Ø§Ù†ØªØ§ Ú©Ø±ÙˆØ² Ø¯Û’ ÙÛŒÙ†ÛŒØ±ÛŒÙÛ’ | IQ52: Ø³Ø§Ù†ØªØ§ Ú©Ø±ÙˆØ³ | IR52: è–å…‹é­¯æ–¯-å¾·ç‰¹å…§é‡Œè²»çœ | IS52: ES.CN
A53: Cayman Islands | B53: Admin-0 country | C53: 3 | D53: 5 | E53: United Kingdom | F53: GB1 | G53: 1 | H53: 2 | I53: Dependency | J53: 1 | K53: Cayman Islands | L53: CYM | M53: 0 | N53: Cayman Islands | O53: CYM | P53: 0 | Q53: Cayman Islands | R53: CYM | S53: 0 | T53: Cayman Islands | U53: CYM | V53: Cayman Islands | X53: Cym. Is. | Y53: KY | Z53: Cayman Islands | AB53: Cayman Islands | AC53: U.K. | AE53: Cayman Islands | AG53: 6 | AH53: 6 | AI53: 6 | AJ53: 3 | AK53: 64948 | AL53: 8 | AM53: 2019 | AN53: 5517 | AO53: 2018 | AP53: 5. Emerging region: G20 | AQ53: 2. High income: nonOECD | AR53: CJ | AS53: KY | AT53: KY | AU53: CYM | AV53: CYM | AW53: 136 | AX53: 136 | AY53: 136 | AZ53: KY | BA53: CYM | BB53: 23424783 | BC53: 23424783 | BD53: Exact WOE match as country | BE53: CYM | BG53: CYM | BH53: CYM | BI53: CYM | BJ53: CYM | BK53: CYM | BL53: CYM | BM53: CYM | BN53: CYM | BO53: CYM | BP53: CYM | BQ53: CYM | BR53: CYM | BS53: CYM | BT53: CYM | BU53: CYM | BV53: CYM | BW53: CYM | BX53: CYM | BY53: CYM | BZ53: CYM | CA53: CYM | CB53: CYM | CC53: CYM | CD53: CYM | CE53: CYM | CF53: CYM | CG53: CYM | CH53: CYM | CI53: CYM | CJ53: CYM | CK53: CYM | CL53: CYM | CM53: -99 | CN53: -99 | CO53: North America | CP53: Americas | CQ53: Caribbean | CR53: Latin America & Caribbean | CS53: 10 | CT53: 14 | CU53: 8 | CV53: 2 | CW53: -99 | CX53: 0 | CY53: 5 | CZ53: 9.5 | DA53: -81.24055 | DB53: 19.319862 | DC53: 1159320707 | DD53: Q5785 | DE53: Ø¬Ø²Ø± ÙƒØ§ÙŠÙ…Ø§Ù† | DF53: à¦•à§‡à¦‡à¦®à§à¦¯à¦¾à¦¨ à¦¦à§à¦¬à§€à¦ªà¦ªà§à¦žà§à¦œ | DG53: Cayman Islands | DH53: Cayman Islands | DI53: Islas CaimÃ¡n | DJ53: Ø¬Ø²Ø§ÛŒØ± Ú©ÛŒÙ…Ù† | DK53: Ã®les CaÃ¯mans | DL53: ÎÎ·ÏƒÎ¹Î¬ ÎšÎ±Ï‹Î¼Î¬Î½ | DM53: ××™×™ ×§×™×™×ž×Ÿ | DN53: à¤•à¥‡à¤®à¤¨ à¤¦à¥à¤µà¥€à¤ªà¤¸à¤®à¥‚à¤¹ | DO53: KajmÃ¡n-szigetek | DP53: Kepulauan Cayman | DQ53: Isole Cayman | DR53: ã‚±ã‚¤ãƒžãƒ³è«¸å³¶ | DS53: ì¼€ì´ë§¨ ì œë„ | DT53: Kaaimaneilanden | DU53: Kajmany | DV53: Ilhas CaimÃ£o | DW53: Ð¾ÑÑ‚Ñ€Ð¾Ð²Ð° ÐšÐ°Ð¹Ð¼Ð°Ð½ | DX53: CaymanÃ¶arna | DY53: Cayman AdalarÄ± | DZ53: ÐšÐ°Ð¹Ð¼Ð°Ð½Ð¾Ð²Ñ– Ð¾ÑÑ‚Ñ€Ð¾Ð²Ð¸ | EA53: Ø¬Ø²Ø§Ø¦Ø± Ú©ÛŒÙ…ÛŒÙ† | EB53: Quáº§n Ä‘áº£o Cayman | EC53: å¼€æ›¼ç¾¤å²› | ED53: é–‹æ›¼ç¾¤å³¶ | EE53: Admin-0 dependency | EG53: Admin-0 dependency
A54: Central African Republic | B54: Admin-0 country | C54: 0 | D54: 4 | E54: Central African Republic | F54: CAF | G54: 0 | H54: 2 | I54: Sovereign country | J54: 1 | K54: Central African Republic | L54: CAF | M54: 0 | N54: Central African Republic | O54: CAF | P54: 0 | Q54: Central African Republic | R54: CAF | S54: 0 | T54: Central African Republic | U54: CAF | V54: Central African Rep. | X54: C.A.R. | Y54: CF | Z54: Central African Republic | AB54: Central African Republic | AE54: Central African Republic | AG54: 5 | AH54: 6 | AI54: 6 | AJ54: 9 | AK54: 4745185 | AL54: 12 | AM54: 2019 | AN54: 2220 | AO54: 2019 | AP54: 7. Least developed region | AQ54: 5. Low income | AR54: CT | AS54: CF | AT54: CF | AU54: CAF | AV54: CAF | AW54: 140 | AX54: 140 | AY54: 140 | AZ54: CF | BA54: CAF | BB54: 23424792 | BC54: 23424792 | BD54: Exact WOE match as country | BE54: CAF | BG54: CAF | BH54: CAF | BI54: CAF | BJ54: CAF | BK54: CAF | BL54: CAF | BM54: CAF | BN54: CAF | BO54: CAF | BP54: CAF | BQ54: CAF | BR54: CAF | BS54: CAF | BT54: CAF | BU54: CAF | BV54: CAF | BW54: CAF | BX54: CAF | BY54: CAF | BZ54: CAF | CA54: CAF | CB54: CAF | CC54: CAF | CD54: CAF | CE54: CAF | CF54: CAF | CG54: CAF | CH54: CAF | CI54: CAF | CJ54: CAF | CK54: CAF | CL54: CAF | CM54: -99 | CN54: -99 | CO54: Africa | CP54: Africa | CQ54: Middle Africa | CR54: Sub-Saharan Africa | CS54: 20 | CT54: 24 | CU54: 6 | CV54: -99 | CW54: 1 | CX54: 0 | CY54: 4 | CZ54: 9 | DA54: 20.906897 | DB54: 6.989681 | DC54: 1159320463 | DD54: Q929 | DE54: Ø¬Ù…Ù‡ÙˆØ±ÙŠØ© Ø£ÙØ±ÙŠÙ‚ÙŠØ§ Ø§Ù„ÙˆØ³Ø·Ù‰ | DF54: à¦®à¦§à§à¦¯ à¦†à¦«à§à¦°à¦¿à¦•à¦¾à¦¨ à¦ªà§à¦°à¦œà¦¾à¦¤à¦¨à§à¦¤à§à¦° | DG54: Zentralafrikanische Republik | DH54: Central African Republic | DI54: RepÃºblica Centroafricana | DJ54: Ø¬Ù…Ù‡ÙˆØ±ÛŒ Ø¢ÙØ±ÛŒÙ‚Ø§ÛŒ Ù…Ø±Ú©Ø²ÛŒ | DK54: RÃ©publique centrafricaine | DL54: ÎšÎµÎ½Ï„ÏÎ¿Î±Ï†ÏÎ¹ÎºÎ±Î½Î¹ÎºÎ® Î”Î·Î¼Î¿ÎºÏÎ±Ï„Î¯Î± | DM54: ×”×¨×¤×•×‘×œ×™×§×” ×”×ž×¨×›×–-××¤×¨×™×§××™×ª | DN54: à¤®à¤§à¥à¤¯ à¤…à¤«à¤¼à¥à¤°à¥€à¤•à¥€ à¤—à¤£à¤°à¤¾à¤œà¥à¤¯ | DO54: KÃ¶zÃ©p-afrikai KÃ¶ztÃ¡rsasÃ¡g | DP54: Republik Afrika Tengah | DQ54: Repubblica Centrafricana | DR54: ä¸­å¤®ã‚¢ãƒ•ãƒªã‚«å…±å’Œå›½ | DS54: ì¤‘ì•™ì•„í”„ë¦¬ì¹´ ê³µí™”êµ­ | DT54: Centraal-Afrikaanse Republiek | DU54: Republika ÅšrodkowoafrykaÅ„ska | DV54: RepÃºblica Centro-Africana | DW54: Ð¦ÐµÐ½Ñ‚Ñ€Ð°Ð»ÑŒÐ½Ð¾Ð°Ñ„Ñ€Ð¸ÐºÐ°Ð½ÑÐºÐ°Ñ Ð ÐµÑÐ¿ÑƒÐ±Ð»Ð¸ÐºÐ° | DX54: Centralafrikanska republiken | DY54: Orta Afrika Cumhuriyeti | DZ54: Ð¦ÐµÐ½Ñ‚Ñ€Ð°Ð»ÑŒÐ½Ð¾Ð°Ñ„Ñ€Ð¸ÐºÐ°Ð½ÑÑŒÐºÐ° Ð ÐµÑÐ¿ÑƒÐ±Ð»Ñ–ÐºÐ° | EA54: ÙˆØ³Ø·ÛŒ Ø§ÙØ±ÛŒÙ‚ÛŒ Ø¬Ù…ÛÙˆØ±ÛŒÛ | EB54: Cá»™ng hÃ²a Trung Phi | EC54: ä¸­éžå…±å’Œå›½ | ED54: ä¸­éžå…±å’Œåœ‹ | EE54: Admin-0 country | EG54: Admin-0 country
A55: Ceuta | B55: Admin-1 states provinces | C55: 3 | L55: ES-CE | FN55: ESP-5815 | FO55: 5815 | FQ55: ES | FR55: 5 | FU55: Ciudades AutÃ³nomas | FV55: Autonomous City | FX55: ES.CE | GA55: Ceuta | GB55: 23 | GC55: 1 | GD55: 20 | GE55: 3 | GG55: CE | GH55: 0 | GI55: 9 | GJ55: 9 | GK55: 5 | GL55: 5 | GM55: 5 | GN55: SP00 | GO55: SP| | GP55: 55862983 | GQ55: Ceuta Province, ES, Spain | GR55: Ceuta | GS55: 35.8803 | GT55: -5.341 | GU55: ESP | GV55: ES-CE | GW55: 5 | GX55: Spain | HA55: 8335119 | HB55: Ceuta | HC55: -99 | HE55: 2 | HG55: ES.CE | HJ55: 1 | HN55: 7.7 | HO55: 11 | HP55: 7.7 | HQ55: Q5823 | HR55: Ø³Ø¨ØªØ© | HS55: à¦¸à¦¿à¦‰à¦šà¦¾ | HT55: Ceuta | HU55: Ceuta | HV55: Ceuta | HW55: Ceuta | HX55: Î˜Î­Î¿Ï…Ï„Î± | HY55: à¤¸à¥‡à¤‰à¤Ÿà¤¾ | HZ55: Ceuta | IA55: Ceuta | IB55: Ceuta | IC55: ã‚»ã‚¦ã‚¿ | ID55: ì„¸ìš°íƒ€ | IE55: Ceuta | IF55: Ceuta | IG55: Ceuta | IH55: Ð¡ÐµÑƒÑ‚Ð° | II55: Ceuta | IJ55: Ceuta | IK55: Ceuta | IL55: ä¼‘è¾¾ | IM55: 1159310507 | IN55: ×¡××•×˜×” | IO55: Ð¡ÐµÑƒÑ‚Ð° | IP55: Ø³Ø¨ØªÙ‡ | IQ55: Ø³Ø¨ØªÙ‡ | IR55: ä¼‘é” | IS55: ES.CE
A56: Chad | B56: Admin-0 country | C56: 0 | D56: 3 | E56: Chad | F56: TCD | G56: 0 | H56: 2 | I56: Sovereign country | J56: 1 | K56: Chad | L56: TCD | M56: 0 | N56: Chad | O56: TCD | P56: 0 | Q56: Chad | R56: TCD | S56: 0 | T56: Chad | U56: TCD | V56: Chad | X56: Chad | Y56: TD | Z56: Republic of Chad | AB56: Chad | AE56: Chad | AG56: 6 | AH56: 1 | AI56: 8 | AJ56: 6 | AK56: 15946876 | AL56: 14 | AM56: 2019 | AN56: 11314 | AO56: 2019 | AP56: 7. Least developed region | AQ56: 5. Low income | AR56: CD | AS56: TD | AT56: TD | AU56: TCD | AV56: TCD | AW56: 148 | AX56: 148 | AY56: 148 | AZ56: TD | BA56: TCD | BB56: 23424777 | BC56: 23424777 | BD56: Exact WOE match as country | BE56: TCD | BG56: TCD | BH56: TCD | BI56: TCD | BJ56: TCD | BK56: TCD | BL56: TCD | BM56: TCD | BN56: TCD | BO56: TCD | BP56: TCD | BQ56: TCD | BR56: TCD | BS56: TCD | BT56: TCD | BU56: TCD | BV56: TCD | BW56: TCD | BX56: TCD | BY56: TCD | BZ56: TCD | CA56: TCD | CB56: TCD | CC56: TCD | CD56: TCD | CE56: TCD | CF56: TCD | CG56: TCD | CH56: TCD | CI56: TCD | CJ56: TCD | CK56: TCD | CL56: TCD | CM56: -99 | CN56: -99 | CO56: Africa | CP56: Africa | CQ56: Middle Africa | CR56: Sub-Saharan Africa | CS56: 4 | CT56: 4 | CU56: 4 | CV56: -99 | CW56: 1 | CX56: 0 | CY56: 3 | CZ56: 8 | DA56: 18.645041 | DB56: 15.142959 | DC56: 1159321301 | DD56: Q657 | DE56: ØªØ´Ø§Ø¯ | DF56: à¦šà¦¾à¦¦ | DG56: Tschad | DH56: Chad | DI56: Chad | DJ56: Ú†Ø§Ø¯ | DK56: Tchad | DL56: Î¤ÏƒÎ±Î½Ï„ | DM56: ×¦'××“ | DN56: à¤šà¤¾à¤¡ | DO56: CsÃ¡d | DP56: Chad | DQ56: Ciad | DR56: ãƒãƒ£ãƒ‰ | DS56: ì°¨ë“œ | DT56: Tsjaad | DU56: Czad | DV56: Chade | DW56: Ð§Ð°Ð´ | DX56: Tchad | DY56: Ã‡ad | DZ56: Ð§Ð°Ð´ | EA56: Ú†Ø§Úˆ | EB56: Tchad | EC56: ä¹å¾— | ED56: æŸ¥å¾· | EE56: Admin-0 country | EG56: Admin-0 country
A57: Chile | B57: Admin-0 country | C57: 0 | D57: 2 | E57: Chile | F57: CHL | G57: 0 | H57: 2 | I57: Sovereign country | J57: 1 | K57: Chile | L57: CHL | M57: 0 | N57: Chile | O57: CHL | P57: 0 | Q57: Chile | R57: CHL | S57: 0 | T57: Chile | U57: CHL | V57: Chile | X57: Chile | Y57: CL | Z57: Republic of Chile | AB57: Chile | AE57: Chile | AG57: 5 | AH57: 1 | AI57: 5 | AJ57: 9 | AK57: 18952038 | AL57: 14 | AM57: 2019 | AN57: 282318 | AO57: 2019 | AP57: 5. Emerging region: G20 | AQ57: 3. Upper middle income | AR57: CI | AS57: CL | AT57: CL | AU57: CHL | AV57: CHL | AW57: 152 | AX57: 152 | AY57: 152 | AZ57: CL | BA57: CHL | BB57: 23424782 | BC57: 23424782 | BD57: Exact WOE match as country | BE57: CHL | BG57: CHL | BH57: CHL | BI57: CHL | BJ57: CHL | BK57: CHL | BL57: CHL | BM57: CHL | BN57: CHL | BO57: CHL | BP57: CHL | BQ57: CHL | BR57: CHL | BS57: CHL | BT57: CHL | BU57: CHL | BV57: CHL | BW57: CHL | BX57: CHL | BY57: CHL | BZ57: CHL | CA57: CHL | CB57: CHL | CC57: CHL | CD57: CHL | CE57: CHL | CF57: CHL | CG57: CHL | CH57: CHL | CI57: CHL | CJ57: CHL | CK57: CHL | CL57: CHL | CM57: -99 | CN57: -99 | CO57: South America | CP57: Americas | CQ57: South America | CR57: Latin America & Caribbean | CS57: 5 | CT57: 5 | CU57: 5 | CV57: -99 | CW57: 1 | CX57: 0 | CY57: 1.7 | CZ57: 6.7 | DA57: -72.318871 | DB57: -38.151771 | DC57: 1159320493 | DD57: Q298 | DE57: ØªØ´ÙŠÙ„ÙŠ | DF57: à¦šà¦¿à¦²à¦¿ | DG57: Chile | DH57: Chile | DI57: Chile | DJ57: Ø´ÛŒÙ„ÛŒ | DK57: Chili | DL57: Î§Î¹Î»Î® | DM57: ×¦'×™×œ×” | DN57: à¤šà¤¿à¤²à¥€ | DO57: Chile | DP57: Chili | DQ57: Cile | DR57: ãƒãƒª | DS57: ì¹ ë ˆ | DT57: Chili | DU57: Chile | DV57: Chile | DW57: Ð§Ð¸Ð»Ð¸ | DX57: Chile | DY57: Åžili | DZ57: Ð§Ð¸Ð»Ñ– | EA57: Ú†Ù„ÛŒ | EB57: Chile | EC57: æ™ºåˆ© | ED57: æ™ºåˆ© | EE57: Admin-0 country | EG57: Admin-0 country
A58: China | B58: Admin-0 country | C58: 0 | D58: 2 | E58: China | F58: CH1 | G58: 1 | H58: 2 | I58: Country | J58: 1 | K58: China | L58: CHN | M58: 0 | N58: China | O58: CHN | P58: 0 | Q58: China | R58: CHN | S58: 0 | T58: China | U58: CHN | V58: China | X58: China | Y58: CN | Z58: People's Republic of China | AB58: China | AE58: China | AG58: 4 | AH58: 4 | AI58: 4 | AJ58: 3 | AK58: 1397715000 | AL58: 18 | AM58: 2019 | AN58: 14342903 | AO58: 2019 | AP58: 3. Emerging region: BRIC | AQ58: 3. Upper middle income | AR58: CH | AS58: CN | AT58: CN | AU58: CHN | AV58: CHN | AW58: 156 | AX58: 156 | AY58: 156 | AZ58: CN | BA58: CHN | BB58: 23424781 | BC58: 23424781 | BD58: Exact WOE match as country | BE58: CHN | BG58: CHN | BH58: CHN | BI58: CHN | BJ58: CHN | BK58: CHN | BL58: CHN | BM58: TWN | BN58: CHN | BO58: CHN | BP58: CHN | BQ58: CHN | BR58: CHN | BS58: CHN | BT58: CHN | BU58: CHN | BV58: CHN | BW58: CHN | BX58: CHN | BY58: CHN | BZ58: CHN | CA58: CHN | CB58: CHN | CC58: CHN | CD58: CHN | CE58: CHN | CF58: CHN | CG58: CHN | CH58: CHN | CI58: CHN | CJ58: CHN | CK58: CHN | CL58: CHN | CM58: -99 | CN58: -99 | CO58: Asia | CP58: Asia | CQ58: Eastern Asia | CR58: East Asia & Pacific | CS58: 5 | CT58: 5 | CU58: 5 | CV58: -99 | CW58: 1 | CX58: 0 | CY58: 1.7 | CZ58: 5.7 | DA58: 106.33729 | DB58: 32.498178 | DC58: 1159320471 | DD58: Q148 | DE58: Ø§Ù„ØµÙŠÙ† | DF58: à¦—à¦£à¦šà§€à¦¨ | DG58: Volksrepublik China | DH58: People's Republic of China | DI58: China | DJ58: Ø¬Ù…Ù‡ÙˆØ±ÛŒ Ø®Ù„Ù‚ Ú†ÛŒÙ† | DK58: RÃ©publique populaire de Chine | DL58: Î›Î±ÏŠÎºÎ® Î”Î·Î¼Î¿ÎºÏÎ±Ï„Î¯Î± Ï„Î·Ï‚ ÎšÎ¯Î½Î±Ï‚ | DM58: ×”×¨×¤×•×‘×œ×™×§×” ×”×¢×ž×ž×™×ª ×©×œ ×¡×™×Ÿ | DN58: à¤šà¥€à¤¨à¥€ à¤œà¤¨à¤µà¤¾à¤¦à¥€ à¤—à¤£à¤°à¤¾à¤œà¥à¤¯ | DO58: KÃ­na | DP58: Republik Rakyat Tiongkok | DQ58: Cina | DR58: ä¸­è¯äººæ°‘å…±å’Œå›½ | DS58: ì¤‘í™”ì¸ë¯¼ê³µí™”êµ­ | DT58: Volksrepubliek China | DU58: ChiÅ„ska Republika Ludowa | DV58: China | DW58: ÐšÐ¸Ñ‚Ð°Ð¹ÑÐºÐ°Ñ ÐÐ°Ñ€Ð¾Ð´Ð½Ð°Ñ Ð ÐµÑÐ¿ÑƒÐ±Ð»Ð¸ÐºÐ° | DX58: Kina | DY58: Ã‡in Halk Cumhuriyeti | DZ58: ÐšÐ¸Ñ‚Ð°Ð¹ÑÑŒÐºÐ° ÐÐ°Ñ€Ð¾Ð´Ð½Ð° Ð ÐµÑÐ¿ÑƒÐ±Ð»Ñ–ÐºÐ° | EA58: Ø¹ÙˆØ§Ù…ÛŒ Ø¬Ù…ÛÙˆØ±ÛŒÛ Ú†ÛŒÙ† | EB58: Trung Quá»‘c | EC58: ä¸­åŽäººæ°‘å…±å’Œå›½ | ED58: ä¸­è¯äººæ°‘å…±å’Œåœ‹ | EE58: Admin-0 country | EG58: Admin-0 country | EM58: Unrecognized
A59: China | B59: Admin-0 country | C59: 0 | D59: 2 | E59: China | F59: CH1 | G59: 1 | H59: 2 | I59: Country | J59: 1 | K59: China | L59: CHN | M59: 0 | N59: China | O59: CHN | P59: 0 | Q59: China | R59: CHN | S59: 0 | T59: China | U59: CHN | V59: China | W59: null | X59: China | Y59: CN | Z59: People's Republic of China | AA59: null | AB59: China | AC59: null | AD59: null | AE59: China | AF59: null | AG59: 4 | AH59: 4 | AI59: 4 | AJ59: 3 | AK59: 1397715000 | AL59: 18 | AM59: 2019 | AN59: 14342903 | AO59: 2019 | AP59: 3. Emerging region: BRIC | AQ59: 3. Upper middle income | AR59: CH | AS59: CN | AT59: CN | AU59: CHN | AV59: CHN | AZ59: CN | BA59: CHN | BB59: 23424781 | BC59: 23424781 | BD59: Exact WOE match as country | BE59: CHN | BF59: null | BG59: CHN | BH59: CHN | BI59: CHN | BJ59: CHN | BK59: CHN | BL59: CHN | BM59: TWN | BN59: CHN | BO59: CHN | BP59: CHN | BQ59: CHN | BR59: CHN | BS59: CHN | BT59: CHN | BU59: CHN | BV59: CHN | BW59: CHN | BX59: CHN | BY59: CHN | BZ59: CHN | CA59: CHN | CB59: CHN | CC59: CHN | CD59: CHN | CE59: CHN | CF59: CHN | CG59: CHN | CH59: CHN | CI59: CHN | CJ59: CHN | CK59: CHN | CL59: CHN | CM59: -99 | CN59: -99 | CO59: Asia | CP59: Asia | CQ59: Eastern Asia | CR59: East Asia & Pacific | CS59: 5 | CT59: 5 | CU59: 5 | CV59: -99 | CW59: 1 | CX59: 0 | CY59: 1.7 | CZ59: 5.7 | DA59: 106.33729 | DB59: 32.498178 | DC59: 1159320471 | DD59: Q148 | DE59: Ø§Ù„ØµÙŠÙ† | DF59: à¦—à¦£à¦šà§€à¦¨ | DG59: Volksrepublik China | DH59: People's Republic of China | DI59: China | FM59: CN
A60: Clipperton Island | B60: Admin-0 country | C60: 6 | D60: 5 | E60: France | F60: FR1 | G60: 1 | H60: 2 | I60: Dependency | J60: 1 | K60: Clipperton Island | L60: CLP | M60: 0 | N60: Clipperton Island | O60: CLP | P60: 0 | Q60: Clipperton Island | R60: CLP | S60: 0 | T60: Clipperton Island | U60: CLP | V60: Clipperton I. | X60: Clp. I. | Y60: CI | AC60: Fr. | AE60: Clipperton Island | AG60: 7 | AH60: 5 | AI60: 9 | AJ60: 11 | AK60: 0 | AL60: 1 | AM60: 2019 | AN60: 0 | AO60: 2016 | AP60: 7. Least developed region | AQ60: 5. Low income | AR60: IP | AS60: -99 | AT60: FR | AU60: -99 | AV60: FRA | AW60: -99 | AX60: 250 | AY60: -99 | AZ60: -99 | BA60: -99 | BB60: 23424850 | BC60: 23424850 | BD60: WOE Admin-1 states provinces (territory) match. | BE60: FRA | BF60: 1 | BG60: CLP | BH60: CLP | BI60: CLP | BJ60: CLP | BK60: CLP | BL60: CLP | BM60: CLP | BN60: CLP | BO60: CLP | BP60: CLP | BQ60: CLP | BR60: CLP | BS60: CLP | BT60: CLP | BU60: CLP | BV60: CLP | BW60: CLP | BX60: CLP | BY60: CLP | BZ60: CLP | CA60: CLP | CB60: CLP | CC60: CLP | CD60: CLP | CE60: CLP | CF60: CLP | CG60: CLP | CH60: CLP | CI60: CLP | CJ60: CLP | CK60: CLP | CL60: CLP | CM60: -99 | CN60: -99 | CO60: Seven seas (open ocean) | CP60: Americas | CQ60: Central America | CR60: Latin America & Caribbean | CS60: 13 | CT60: 17 | CU60: 7 | CV60: -99 | CW60: -99 | CX60: 0 | CY60: 5 | CZ60: 9.5 | DA60: -109.22045 | DB60: 10.297324 | DC60: 1159320635 | DD60: Q161258 | DE60: Ø¬Ø²ÙŠØ±Ø© ÙƒÙ„ÙŠØ¨Ø±ØªÙˆÙ† | DF60: à¦•à§à¦²à¦¿à¦ªà¦¾à¦°à¦Ÿà¦¨ à¦¦à§à¦¬à§€à¦ªà¦ªà§à¦žà§à¦œ | DG60: Clipperton-Insel | DH60: Clipperton Island | DI60: Isla Clipperton | DJ60: Ø¬Ø²ÛŒØ±Ù‡ Ú©Ù„ÛŒÙ¾Ø±ØªÙˆÙ† | DK60: Ã®le Clipperton | DL60: ÎÎ®ÏƒÎ¿Ï‚ ÎšÎ»Î¯Ï€ÎµÏÏ„Î¿Î½ | DM60: ×§×œ×™×¤×¨×˜×•×Ÿ | DN60: à¤•à¥à¤²à¤¿à¤ªà¤°à¤Ÿà¤¨ à¤¦à¥à¤µà¥€à¤ª | DO60: Clipperton-sziget | DP60: Pulau Clipperton | DQ60: Clipperton | DR60: ã‚¯ãƒªãƒƒãƒ‘ãƒ¼ãƒˆãƒ³å³¶ | DS60: í´ë¦¬í¼í„´ì„¬ | DT60: Clipperton | DU60: Wyspa Clippertona | DV60: Ilha de Clipperton | DW60: ÐšÐ»Ð¸Ð¿Ð¿ÐµÑ€Ñ‚Ð¾Ð½ | DX60: ClippertonÃ¶n | DY60: Clipperton AdasÄ± | DZ60: ÐšÐ»Ñ–Ð¿Ð¿ÐµÑ€Ñ‚Ð¾Ð½ | EA60: Ø¬Ø²ÛŒØ±Û Ú©Ù„Ù¾Ø±Ù¹Ù† | EB60: Clipperton | EC60: å…‹åˆ©ç€é¡¿å²› | ED60: å…‹åˆ©ç€é “å³¶ | EE60: Unrecognized | EF60: 1 | EG60: Admin-0 dependency
A61: Colombia | B61: Admin-0 country | C61: 0 | D61: 2 | E61: Colombia | F61: COL | G61: 0 | H61: 2 | I61: Sovereign country | J61: 1 | K61: Colombia | L61: COL | M61: 0 | N61: Colombia | O61: COL | P61: 0 | Q61: Colombia | R61: COL | S61: 0 | T61: Colombia | U61: COL | V61: Colombia | X61: Col. | Y61: CO | Z61: Republic of Colombia | AB61: Colombia | AE61: Colombia | AG61: 2 | AH61: 1 | AI61: 3 | AJ61: 1 | AK61: 50339443 | AL61: 16 | AM61: 2019 | AN61: 323615 | AO61: 2019 | AP61: 6. Developing region | AQ61: 3. Upper middle income | AR61: CO | AS61: CO | AT61: CO | AU61: COL | AV61: COL | AW61: 170 | AX61: 170 | AY61: 170 | AZ61: CO | BA61: COL | BB61: 23424787 | BC61: 23424787 | BD61: Exact WOE match as country | BE61: COL | BG61: COL | BH61: COL | BI61: COL | BJ61: COL | BK61: COL | BL61: COL | BM61: COL | BN61: COL | BO61: COL | BP61: COL | BQ61: COL | BR61: COL | BS61: COL | BT61: COL | BU61: COL | BV61: COL | BW61: COL | BX61: COL | BY61: COL | BZ61: COL | CA61: COL | CB61: COL | CC61: COL | CD61: COL | CE61: COL | CF61: COL | CG61: COL | CH61: COL | CI61: COL | CJ61: COL | CK61: COL | CL61: COL | CM61: -99 | CN61: -99 | CO61: South America | CP61: Americas | CQ61: South America | CR61: Latin America & Caribbean | CS61: 8 | CT61: 8 | CU61: 4 | CV61: -99 | CW61: 1 | CX61: 0 | CY61: 3 | CZ61: 7 | DA61: -73.174347 | DB61: 3.373111 | DC61: 1159320517 | DD61: Q739 | DE61: ÙƒÙˆÙ„ÙˆÙ…Ø¨ÙŠØ§ | DF61: à¦•à¦²à¦®à§à¦¬à¦¿à¦¯à¦¼à¦¾ | DG61: Kolumbien | DH61: Colombia | DI61: Colombia | DJ61: Ú©Ù„Ù…Ø¨ÛŒØ§ | DK61: Colombie | DL61: ÎšÎ¿Î»Î¿Î¼Î²Î¯Î± | DM61: ×§×•×œ×•×ž×‘×™×” | DN61: à¤•à¥‹à¤²à¤®à¥à¤¬à¤¿à¤¯à¤¾ | DO61: Kolumbia | DP61: Kolombia | DQ61: Colombia | DR61: ã‚³ãƒ­ãƒ³ãƒ“ã‚¢ | DS61: ì½œë¡¬ë¹„ì•„ | DT61: Colombia | DU61: Kolumbia | DV61: ColÃ´mbia | DW61: ÐšÐ¾Ð»ÑƒÐ¼Ð±Ð¸Ñ | DX61: Colombia | DY61: Kolombiya | DZ61: ÐšÐ¾Ð»ÑƒÐ¼Ð±Ñ–Ñ | EA61: Ú©ÙˆÙ„Ù…Ø¨ÛŒØ§ | EB61: Colombia | EC61: å“¥ä¼¦æ¯”äºš | ED61: å“¥å€«æ¯”äºž | EE61: Admin-0 country | EG61: Admin-0 country
A62: Comoros | B62: Admin-0 country | C62: 3 | D62: 6 | E62: Comoros | F62: COM | G62: 0 | H62: 2 | I62: Sovereign country | J62: 1 | K62: Comoros | L62: COM | M62: 0 | N62: Comoros | O62: COM | P62: 0 | Q62: Comoros | R62: COM | S62: 0 | T62: Comoros | U62: COM | V62: Comoros | X62: Com. | Y62: KM | Z62: Union of the Comoros | AB62: Comoros | AE62: Comoros | AG62: 2 | AH62: 1 | AI62: 4 | AJ62: 10 | AK62: 850886 | AL62: 11 | AM62: 2019 | AN62: 1165 | AO62: 2019 | AP62: 7. Least developed region | AQ62: 5. Low income | AR62: CN | AS62: KM | AT62: KM | AU62: COM | AV62: COM | AW62: 174 | AX62: 174 | AY62: 174 | AZ62: KM | BA62: COM | BB62: 23424786 | BC62: 23424786 | BD62: Exact WOE match as country | BE62: COM | BG62: COM | BH62: COM | BI62: COM | BJ62: COM | BK62: COM | BL62: COM | BM62: COM | BN62: COM | BO62: COM | BP62: COM | BQ62: COM | BR62: COM | BS62: COM | BT62: COM | BU62: COM | BV62: COM | BW62: COM | BX62: COM | BY62: COM | BZ62: COM | CA62: COM | CB62: COM | CC62: COM | CD62: COM | CE62: COM | CF62: COM | CG62: COM | CH62: COM | CI62: COM | CJ62: COM | CK62: COM | CL62: COM | CM62: -99 | CN62: -99 | CO62: Africa | CP62: Africa | CQ62: Eastern Africa | CR62: Sub-Saharan Africa | CS62: 7 | CT62: 7 | CU62: 4 | CV62: 2 | CW62: 1 | CX62: 0 | CY62: 4 | CZ62: 9 | DA62: 43.318094 | DB62: -11.727683 | DC62: 1159320521 | DD62: Q970 | DE62: Ø¬Ø²Ø± Ø§Ù„Ù‚Ù…Ø± | DF62: à¦•à§‹à¦®à§‹à¦°à§‹à¦¸ | DG62: Komoren | DH62: Comoros | DI62: Comoras | DJ62: Ù…Ø¬Ù…Ø¹Ø§Ù„Ø¬Ø²Ø§ÛŒØ± Ù‚Ù…Ø± | DK62: Comores | DL62: ÎšÎ¿Î¼ÏŒÏÎµÏ‚ | DM62: ×§×•×ž×•×¨×• | DN62: à¤•à¥‹à¤®à¥‹à¤°à¥‹à¤¸ | DO62: Comore-szigetek | DP62: Komoro | DQ62: Comore | DR62: ã‚³ãƒ¢ãƒ­ | DS62: ì½”ëª¨ë¡œ | DT62: Comoren | DU62: Komory | DV62: Comores | DW62: ÐšÐ¾Ð¼Ð¾Ñ€Ñ‹ | DX62: Komorerna | DY62: Komorlar | DZ62: ÐšÐ¾Ð¼Ð¾Ñ€ÑÑŒÐºÑ– ÐžÑÑ‚Ñ€Ð¾Ð²Ð¸ | EA62: Ø§ØªØ­Ø§Ø¯ Ø§Ù„Ù‚Ù…Ø±ÛŒ | EB62: Comoros | EC62: ç§‘æ‘©ç½— | ED62: è‘›æ‘© | EE62: Admin-0 country | EG62: Admin-0 country
A63: Cook Islands | B63: Admin-0 country | C63: 5 | D63: 4 | E63: New Zealand | F63: NZ1 | G63: 1 | H63: 2 | I63: Dependency | J63: 1 | K63: Cook Islands | L63: COK | M63: 0 | N63: Cook Islands | O63: COK | P63: 0 | Q63: Cook Islands | R63: COK | S63: 0 | T63: Cook Islands | U63: COK | V63: Cook Is. | X63: Cook Is. | Y63: CK | AB63: Cook Islands | AC63: Assoc. with N.Z. | AD63: Assoc. with N.Z. | AE63: Cook Islands | AG63: 3 | AH63: 3 | AI63: 4 | AJ63: 4 | AK63: 17459 | AL63: 6 | AM63: 2016 | AN63: 244 | AO63: 2010 | AP63: 6. Developing region | AQ63: 3. Upper middle income | AR63: CW | AS63: CK | AT63: CK | AU63: COK | AV63: COK | AW63: 184 | AX63: 184 | AY63: 184 | AZ63: -99 | BA63: -99 | BB63: 23424795 | BC63: 23424795 | BD63: Exact WOE match as country | BE63: COK | BG63: COK | BH63: COK | BI63: COK | BJ63: COK | BK63: COK | BL63: COK | BM63: COK | BN63: COK | BO63: COK | BP63: COK | BQ63: COK | BR63: COK | BS63: COK | BT63: COK | BU63: COK | BV63: COK | BW63: COK | BX63: COK | BY63: COK | BZ63: COK | CA63: COK | CB63: COK | CC63: COK | CD63: COK | CE63: COK | CF63: COK | CG63: COK | CH63: COK | CI63: COK | CJ63: COK | CK63: COK | CL63: COK | CM63: -99 | CN63: -99 | CO63: Oceania | CP63: Oceania | CQ63: Polynesia | CR63: East Asia & Pacific | CS63: 8 | CT63: 12 | CU63: 8 | CV63: 3 | CW63: -99 | CX63: 0 | CY63: 4 | CZ63: 9 | DA63: -159.78567 | DB63: -21.215993 | DC63: 1159321129 | DD63: Q26988 | DE63: Ø¬Ø²Ø± ÙƒÙˆÙƒ | DF63: à¦•à§à¦• à¦¦à§à¦¬à§€à¦ªà¦ªà§à¦žà§à¦œ | DG63: Cookinseln | DH63: Cook Islands | DI63: Islas Cook | DJ63: Ø¬Ø²Ø§ÛŒØ± Ú©ÙˆÚ© | DK63: ÃŽles Cook | DL63: ÎÎ®ÏƒÎ¿Î¹ ÎšÎ¿Ï…Îº | DM63: ××™×™ ×§×•×§ | DN63: à¤•à¥à¤• à¤¦à¥à¤µà¥€à¤ªà¤¸à¤®à¥‚à¤¹ | DO63: Cook-szigetek | DP63: Kepulauan Cook | DQ63: Isole Cook | DR63: ã‚¯ãƒƒã‚¯è«¸å³¶ | DS63: ì¿¡ ì œë„ | DT63: Cookeilanden | DU63: Wyspy Cooka | DV63: Ilhas Cook | DW63: ÐžÑÑ‚Ñ€Ð¾Ð²Ð° ÐšÑƒÐºÐ° | DX63: CookÃ¶arna | DY63: Cook AdalarÄ± | DZ63: ÐžÑÑ‚Ñ€Ð¾Ð²Ð¸ ÐšÑƒÐºÐ° | EA63: Ø¬Ø²Ø§Ø¦Ø± Ú©Ú© | EB63: Quáº§n Ä‘áº£o Cook | EC63: åº“å…‹ç¾¤å²› | ED63: åº«å…‹ç¾¤å³¶ | EE63: Admin-0 dependency | EG63: Admin-0 dependency
A64: Coral Sea Islands | B64: Admin-0 country | C64: 6 | D64: 5 | E64: Australia | F64: AU1 | G64: 1 | H64: 2 | I64: Dependency | J64: 1 | K64: Coral Sea Islands | L64: CSI | M64: 0 | N64: Coral Sea Islands | O64: CSI | P64: 0 | Q64: Coral Sea Islands | R64: CSI | S64: 0 | T64: Coral Sea Islands | U64: CSI | V64: Coral Sea Is. | X64: C.S.I. | Y64: CS | Z64: Coral Sea Islands Territory | AC64: Auz. | AE64: Coral Sea Islands | AG64: 1 | AH64: 2 | AI64: 2 | AJ64: 7 | AK64: 4 | AL64: 1 | AM64: 2019 | AN64: 0 | AO64: 2016 | AP64: 7. Least developed region | AQ64: 5. Low income | AR64: CR | AS64: -99 | AT64: AU | AU64: -99 | AV64: AUS | AW64: -99 | AX64: 36 | AY64: -99 | AZ64: -99 | BA64: -99 | BB64: 23424790 | BC64: 23424790 | BD64: Exact WOE match as country | BE64: AUS | BF64: 1 | BG64: CSI | BH64: CSI | BI64: CSI | BJ64: CSI | BK64: CSI | BL64: CSI | BM64: CSI | BN64: CSI | BO64: CSI | BP64: CSI | BQ64: CSI | BR64: CSI | BS64: CSI | BT64: CSI | BU64: CSI | BV64: CSI | BW64: CSI | BX64: CSI | BY64: CSI | BZ64: CSI | CA64: CSI | CB64: CSI | CC64: CSI | CD64: CSI | CE64: CSI | CF64: CSI | CG64: CSI | CH64: CSI | CI64: CSI | CJ64: CSI | CK64: CSI | CL64: CSI | CM64: -99 | CN64: -99 | CO64: Oceania | CP64: Oceania | CQ64: Australia and New Zealand | CR64: East Asia & Pacific | CS64: 13 | CT64: 17 | CU64: 6 | CV64: -99 | CW64: -99 | CX64: 0 | CY64: 4.5 | CZ64: 9.5 | DA64: 154.39059 | DB64: -21.029311 | DC64: 1159320359 | DD64: Q172216 | DE64: Ø¬Ø²Ø± Ø¨Ø­Ø± Ø§Ù„Ù…Ø±Ø¬Ø§Ù† | DF64: à¦•à§‹à¦°à¦¾à¦² à¦¸à¦¾à¦—à¦° à¦¦à§à¦¬à§€à¦ªà¦ªà§à¦žà§à¦œ | DG64: Korallenmeerinseln | DH64: Coral Sea Islands | DI64: islas del mar del Coral | DJ64: Ø¬Ø²Ø§ÛŒØ± Ú©ÙˆØ±Ø§Ù„ | DK64: ÃŽles de la mer de Corail | DL64: ÎÎ·ÏƒÎ¹Î¬ Î˜Î¬Î»Î±ÏƒÏƒÎ±Ï‚ Ï„Ï‰Î½ ÎšÎ¿ÏÎ±Î»Î¯Ï‰Î½ | DM64: ×˜×¨×™×˜×•×¨×™×™×ª ××™×™ ×™× ×”××œ×ž×•×’×™× | DN64: à¤•à¥‹à¤°à¤² à¤¸à¤¾à¤—à¤° à¤¦à¥à¤µà¥€à¤ª à¤¸à¤®à¥‚à¤¹ | DO64: Korall-tengeri-szigetek | DP64: Kepulauan Laut Karang | DQ64: Isole del Mar dei Coralli | DR64: ã‚³ãƒ¼ãƒ©ãƒ«ãƒ»ã‚·ãƒ¼è«¸å³¶ | DS64: ì‚°í˜¸í•´ ì œë„ | DT64: Koraalzee-eilanden | DU64: Wyspy Morza Koralowego | DV64: Ilhas do Mar de Coral | DW64: Ð¢ÐµÑ€Ñ€Ð¸Ñ‚Ð¾Ñ€Ð¸Ñ Ð¾ÑÑ‚Ñ€Ð¾Ð²Ð¾Ð² ÐšÐ¾Ñ€Ð°Ð»Ð»Ð¾Ð²Ð¾Ð³Ð¾ Ð¼Ð¾Ñ€Ñ | DX64: KorallhavsÃ¶arna | DY64: Mercan Denizi AdalarÄ± | DZ64: ÐžÑÑ‚Ñ€Ð¾Ð²Ð¸ ÐšÐ¾Ñ€Ð°Ð»Ð¾Ð²Ð¾Ð³Ð¾ Ð¼Ð¾Ñ€Ñ | EA64: Ú©ÙˆØ±Ù„ Ø³Ù…Ù†Ø¯Ø±ÛŒ Ø¬Ø²Ø§Ø¦Ø± | EB64: Quáº§n Ä‘áº£o Biá»ƒn San hÃ´ | EC64: çŠç‘šæµ·ç¾¤å²› | ED64: çŠç‘šæµ·ç¾¤å³¶ | EE64: Unrecognized | EF64: 1 | EG64: Admin-0 dependency
A65: Costa Rica | B65: Admin-0 country | C65: 0 | D65: 5 | E65: Costa Rica | F65: CRI | G65: 0 | H65: 2 | I65: Sovereign country | J65: 1 | K65: Costa Rica | L65: CRI | M65: 0 | N65: Costa Rica | O65: CRI | P65: 0 | Q65: Costa Rica | R65: CRI | S65: 0 | T65: Costa Rica | U65: CRI | V65: Costa Rica | X65: C.R. | Y65: CR | Z65: Republic of Costa Rica | AB65: Costa Rica | AE65: Costa Rica | AG65: 3 | AH65: 2 | AI65: 4 | AJ65: 2 | AK65: 5047561 | AL65: 13 | AM65: 2019 | AN65: 61801 | AO65: 2019 | AP65: 5. Emerging region: G20 | AQ65: 3. Upper middle income | AR65: CS | AS65: CR | AT65: CR | AU65: CRI | AV65: CRI | AW65: 188 | AX65: 188 | AY65: 188 | AZ65: CR | BA65: CRI | BB65: 23424791 | BC65: 23424791 | BD65: Exact WOE match as country | BE65: CRI | BG65: CRI | BH65: CRI | BI65: CRI | BJ65: CRI | BK65: CRI | BL65: CRI | BM65: CRI | BN65: CRI | BO65: CRI | BP65: CRI | BQ65: CRI | BR65: CRI | BS65: CRI | BT65: CRI | BU65: CRI | BV65: CRI | BW65: CRI | BX65: CRI | BY65: CRI | BZ65: CRI | CA65: CRI | CB65: CRI | CC65: CRI | CD65: CRI | CE65: CRI | CF65: CRI | CG65: CRI | CH65: CRI | CI65: CRI | CJ65: CRI | CK65: CRI | CL65: CRI | CM65: -99 | CN65: -99 | CO65: North America | CP65: Americas | CQ65: Central America | CR65: Latin America & Caribbean | CS65: 10 | CT65: 10 | CU65: 4 | CV65: -99 | CW65: 1 | CX65: 0 | CY65: 2.5 | CZ65: 8 | DA65: -84.077922 | DB65: 10.0651 | DC65: 1159320525 | DD65: Q800 | DE65: ÙƒÙˆØ³ØªØ§Ø±ÙŠÙƒØ§ | DF65: à¦•à§‹à¦¸à§à¦Ÿà¦¾ à¦°à¦¿à¦•à¦¾ | DG65: Costa Rica | DH65: Costa Rica | DI65: Costa Rica | DJ65: Ú©Ø§Ø³ØªØ§Ø±ÛŒÚ©Ø§ | DK65: Costa Rica | DL65: ÎšÏŒÏƒÏ„Î± Î¡Î¯ÎºÎ± | DM65: ×§×•×¡×˜×” ×¨×™×§×” | DN65: à¤•à¥‹à¤¸à¥à¤Ÿà¤¾ à¤°à¥€à¤•à¤¾ | DO65: Costa Rica | DP65: Kosta Rika | DQ65: Costa Rica | DR65: ã‚³ã‚¹ã‚¿ãƒªã‚« | DS65: ì½”ìŠ¤íƒ€ë¦¬ì¹´ | DT65: Costa Rica | DU65: Kostaryka | DV65: Costa Rica | DW65: ÐšÐ¾ÑÑ‚Ð°-Ð Ð¸ÐºÐ° | DX65: Costa Rica | DY65: Kosta Rika | DZ65: ÐšÐ¾ÑÑ‚Ð°-Ð Ð¸ÐºÐ° | EA65: Ú©ÙˆØ³Ù¹Ø§Ø±ÛŒÚ©Ø§ | EB65: Costa Rica | EC65: å“¥æ–¯è¾¾é»ŽåŠ | ED65: å“¥æ–¯å¤§é»ŽåŠ | EE65: Admin-0 country | EG65: Admin-0 country
A66: Croatia | B66: Admin-0 country | C66: 0 | D66: 6 | E66: Croatia | F66: HRV | G66: 0 | H66: 2 | I66: Sovereign country | J66: 1 | K66: Croatia | L66: HRV | M66: 0 | N66: Croatia | O66: HRV | P66: 0 | Q66: Croatia | R66: HRV | S66: 0 | T66: Croatia | U66: HRV | V66: Croatia | X66: Cro. | Y66: HR | Z66: Republic of Croatia | AB66: Croatia | AE66: Croatia | AG66: 5 | AH66: 4 | AI66: 5 | AJ66: 1 | AK66: 4067500 | AL66: 12 | AM66: 2019 | AN66: 60752 | AO66: 2019 | AP66: 2. Developed region: nonG7 | AQ66: 2. High income: nonOECD | AR66: HR | AS66: HR | AT66: HR | AU66: HRV | AV66: HRV | AW66: 191 | AX66: 191 | AY66: 191 | AZ66: HR | BA66: HRV | BB66: 23424843 | BC66: 23424843 | BD66: Exact WOE match as country | BE66: HRV | BG66: HRV | BH66: HRV | BI66: HRV | BJ66: HRV | BK66: HRV | BL66: HRV | BM66: HRV | BN66: HRV | BO66: HRV | BP66: HRV | BQ66: HRV | BR66: HRV | BS66: HRV | BT66: HRV | BU66: HRV | BV66: HRV | BW66: HRV | BX66: HRV | BY66: HRV | BZ66: HRV | CA66: HRV | CB66: HRV | CC66: HRV | CD66: HRV | CE66: HRV | CF66: HRV | CG66: HRV | CH66: HRV | CI66: HRV | CJ66: HRV | CK66: HRV | CL66: HRV | CM66: -99 | CN66: -99 | CO66: Europe | CP66: Europe | CQ66: Southern Europe | CR66: Europe & Central Asia | CS66: 7 | CT66: 7 | CU66: 4 | CV66: -99 | CW66: 1 | CX66: 0 | CY66: 4 | CZ66: 9 | DA66: 16.37241 | DB66: 45.805799 | DC66: 1159320833 | DD66: Q224 | DE66: ÙƒØ±ÙˆØ§ØªÙŠØ§ | DF66: à¦•à§à¦°à§‹à¦¯à¦¼à§‡à¦¶à¦¿à¦¯à¦¼à¦¾ | DG66: Kroatien | DH66: Croatia | DI66: Croacia | DJ66: Ú©Ø±ÙˆØ§Ø³ÛŒ | DK66: Croatie | DL66: ÎšÏÎ¿Î±Ï„Î¯Î± | DM66: ×§×¨×•××˜×™×” | DN66: à¤•à¥à¤°à¥‹à¤à¤¶à¤¿à¤¯à¤¾ | DO66: HorvÃ¡torszÃ¡g | DP66: Kroasia | DQ66: Croazia | DR66: ã‚¯ãƒ­ã‚¢ãƒã‚¢ | DS66: í¬ë¡œì•„í‹°ì•„ | DT66: KroatiÃ« | DU66: Chorwacja | DV66: CroÃ¡cia | DW66: Ð¥Ð¾Ñ€Ð²Ð°Ñ‚Ð¸Ñ | DX66: Kroatien | DY66: HÄ±rvatistan | DZ66: Ð¥Ð¾Ñ€Ð²Ð°Ñ‚Ñ–Ñ | EA66: Ú©Ø±ÙˆØ´ÛŒØ§ | EB66: Croatia | EC66: å…‹ç½—åœ°äºš | ED66: å…‹ç¾…åœ°äºž | EE66: Admin-0 country | EG66: Admin-0 country
A67: Cuba | B67: Admin-0 country | C67: 0 | D67: 3 | E67: Cuba | F67: CU1 | G67: 1 | H67: 1 | I67: Sovereignty | J67: 1 | K67: Cuba | L67: CUB | M67: 0 | N67: Cuba | O67: CUB | P67: 0 | Q67: Cuba | R67: CUB | S67: 0 | T67: Cuba | U67: CUB | V67: Cuba | X67: Cuba | Y67: CU | Z67: Republic of Cuba | AB67: Cuba | AE67: Cuba | AG67: 3 | AH67: 5 | AI67: 3 | AJ67: 4 | AK67: 11333483 | AL67: 14 | AM67: 2019 | AN67: 100023 | AO67: 2018 | AP67: 5. Emerging region: G20 | AQ67: 3. Upper middle income | AR67: CU | AS67: CU | AT67: CU | AU67: CUB | AV67: CUB | AW67: 192 | AX67: 192 | AY67: 192 | AZ67: CU | BA67: CUB | BB67: 23424793 | BC67: 23424793 | BD67: Exact WOE match as country | BE67: CUB | BG67: CUB | BH67: CUB | BI67: CUB | BJ67: CUB | BK67: CUB | BL67: CUB | BM67: CUB | BN67: CUB | BO67: CUB | BP67: CUB | BQ67: CUB | BR67: CUB | BS67: CUB | BT67: CUB | BU67: CUB | BV67: CUB | BW67: CUB | BX67: CUB | BY67: CUB | BZ67: CUB | CA67: CUB | CB67: CUB | CC67: CUB | CD67: CUB | CE67: CUB | CF67: CUB | CG67: CUB | CH67: CUB | CI67: CUB | CJ67: CUB | CK67: CUB | CL67: CUB | CM67: -99 | CN67: -99 | CO67: North America | CP67: Americas | CQ67: Caribbean | CR67: Latin America & Caribbean | CS67: 4 | CT67: 4 | CU67: 4 | CV67: -99 | CW67: 1 | CX67: 0 | CY67: 2.7 | CZ67: 8 | DA67: -77.975855 | DB67: 21.334024 | DC67: 1159320527 | DD67: Q241 | DE67: ÙƒÙˆØ¨Ø§ | DF67: à¦•à¦¿à¦‰à¦¬à¦¾ | DG67: Kuba | DH67: Cuba | DI67: Cuba | DJ67: Ú©ÙˆØ¨Ø§ | DK67: Cuba | DL67: ÎšÎ¿ÏÎ²Î± | DM67: ×§×•×‘×” | DN67: à¤•à¥à¤¯à¥‚à¤¬à¤¾ | DO67: Kuba | DP67: Kuba | DQ67: Cuba | DR67: ã‚­ãƒ¥ãƒ¼ãƒ | DS67: ì¿ ë°” | DT67: Cuba | DU67: Kuba | DV67: Cuba | DW67: ÐšÑƒÐ±Ð° | DX67: Kuba | DY67: KÃ¼ba | DZ67: ÐšÑƒÐ±Ð° | EA67: Ú©ÛŒÙˆØ¨Ø§ | EB67: Cuba | EC67: å¤å·´ | ED67: å¤å·´ | EE67: Admin-0 country | EG67: Admin-0 country
A68: Curação | B68: Admin-0 country | C68: 3 | D68: 5 | E68: Netherlands | F68: NL1 | G68: 1 | H68: 2 | I68: Country | J68: 1 | K68: CuraÃ§ao | L68: CUW | M68: 0 | N68: CuraÃ§ao | O68: CUW | P68: 0 | Q68: CuraÃ§ao | R68: CUW | S68: 0 | T68: CuraÃ§ao | U68: CUW | V68: CuraÃ§ao | X68: Cur. | Y68: CW | Z68: CuraÃ§ao | AB68: Curacao | AC68: Neth. | AE68: CuraÃ§ao | AG68: 4 | AH68: 2 | AI68: 2 | AJ68: 9 | AK68: 157538 | AL68: 9 | AM68: 2019 | AN68: 3101 | AO68: 2019 | AP68: 6. Developing region | AQ68: 2. High income: nonOECD | AR68: NT | AS68: CW | AT68: CW | AU68: CUW | AV68: CUW | AW68: 531 | AX68: 531 | AY68: 531 | AZ68: CW | BA68: CUW | BB68: -90 | BC68: 24549810 | BD68: Expired subunits of Netherlands Antilles (23424914). | BE68: CUW | BG68: CUW | BH68: CUW | BI68: CUW | BJ68: CUW | BK68: CUW | BL68: CUW | BM68: CUW | BN68: CUW | BO68: CUW | BP68: CUW | BQ68: CUW | BR68: CUW | BS68: CUW | BT68: CUW | BU68: CUW | BV68: CUW | BW68: CUW | BX68: CUW | BY68: CUW | BZ68: CUW | CA68: CUW | CB68: CUW | CC68: CUW | CD68: CUW | CE68: CUW | CF68: CUW | CG68: CUW | CH68: CUW | CI68: CUW | CJ68: CUW | CK68: CUW | CL68: CUW | CM68: -99 | CN68: -99 | CO68: North America | CP68: Americas | CQ68: Caribbean | CR68: Latin America & Caribbean | CS68: 7 | CT68: 7 | CU68: 4 | CV68: 4 | CW68: -99 | CX68: 0 | CY68: 5 | CZ68: 10 | DA68: -68.920578 | DB68: 12.145039 | DC68: 1159321099 | DD68: Q25279 | DE68: ÙƒÙˆØ±Ø§Ø³Ø§Ùˆ | DF68: à¦•à¦¿à¦‰à¦°à¦¾à¦¸à¦¾à¦“ | DG68: CuraÃ§ao | DH68: CuraÃ§ao | DI68: Curazao | DJ68: Ú©ÙˆØ±Ø§Ø³Ø§Ø¦Ùˆ | DK68: CuraÃ§ao | DL68: ÎšÎ¿Ï…ÏÎ±ÏƒÎ¬Î¿ | DM68: ×§×•×¨××¡××• | DN68: à¤•à¥à¤°à¤¾à¤•à¤¾à¤“ | DO68: CuraÃ§ao | DP68: CuraÃ§ao | DQ68: CuraÃ§ao | DR68: ã‚­ãƒ¥ãƒ©ã‚½ãƒ¼ | DS68: í€´ë¼ì†Œ | DT68: CuraÃ§ao | DU68: CuraÃ§ao | DV68: CuraÃ§ao | DW68: ÐšÑŽÑ€Ð°ÑÐ°Ð¾ | DX68: CuraÃ§ao | DY68: CuraÃ§ao | DZ68: ÐšÑŽÑ€Ð°ÑÐ°Ð¾ | EA68: Ú©ÛŒÙˆØ±Ø§Ø³Ø§Ø¤ | EB68: CuraÃ§ao | EC68: åº“æ‹‰ç´¢ | ED68: å¤æ‹‰ç´¢ | EE68: Admin-0 dependency | EG68: Admin-0 dependency
A69: Cyprus | B69: Admin-0 country | C69: 1 | D69: 5 | E69: Cyprus | F69: CYP | G69: 0 | H69: 2 | I69: Sovereign country | J69: 1 | K69: Cyprus | L69: CYP | M69: 0 | N69: Cyprus | O69: CYP | P69: 0 | Q69: Cyprus | R69: CYP | S69: 0 | T69: Cyprus | U69: CYP | V69: Cyprus | X69: Cyp. | Y69: CY | Z69: Republic of Cyprus | AB69: Cyprus | AE69: Cyprus | AG69: 1 | AH69: 2 | AI69: 3 | AJ69: 7 | AK69: 1198575 | AL69: 12 | AM69: 2019 | AN69: 24948 | AO69: 2019 | AP69: 6. Developing region | AQ69: 2. High income: nonOECD | AR69: CY | AS69: CY | AT69: CY | AU69: CYP | AV69: CYP | AW69: 196 | AX69: 196 | AY69: 196 | AZ69: CY | BA69: CYP | BB69: -90 | BC69: 23424994 | BD69: WOE lists as subunit of united Cyprus | BE69: CYP | BG69: CYP | BH69: CYP | BI69: CYP | BJ69: CYP | BK69: CYP | BL69: CYP | BM69: CYP | BN69: CYP | BO69: CYP | BP69: CYP | BQ69: CYP | BR69: CYP | BS69: CYP | BT69: CYP | BU69: CYP | BV69: CYP | BW69: CYP | BX69: CYP | BY69: CYP | BZ69: CYP | CA69: CYP | CB69: CYP | CC69: CYP | CD69: CYP | CE69: CYP | CF69: CYP | CG69: CYP | CH69: CYP | CI69: CYP | CJ69: CYP | CK69: CYP | CL69: CYP | CM69: -99 | CN69: -99 | CO69: Asia | CP69: Asia | CQ69: Western Asia | CR69: Europe & Central Asia | CS69: 6 | CT69: 6 | CU69: 4 | CV69: -99 | CW69: 1 | CX69: 0 | CY69: 4.5 | CZ69: 9.5 | DA69: 33.084182 | DB69: 34.913329 | DC69: 1159320533 | DD69: Q229 | DE69: Ù‚Ø¨Ø±Øµ | DF69: à¦¸à¦¾à¦‡à¦ªà§à¦°à¦¾à¦¸ | DG69: Republik Zypern | DH69: Cyprus | DI69: Chipre | DJ69: Ù‚Ø¨Ø±Ø³ | DK69: Chypre | DL69: ÎšÏÏ€ÏÎ¿Ï‚ | DM69: ×§×¤×¨×™×¡×™×Ÿ | DN69: à¤¸à¤¾à¤‡à¤ªà¥à¤°à¤¸ | DO69: Ciprus | DP69: Siprus | DQ69: Cipro | DR69: ã‚­ãƒ—ãƒ­ã‚¹ | DS69: í‚¤í”„ë¡œìŠ¤ | DT69: Cyprus | DU69: Cypr | DV69: Chipre | DW69: ÐšÐ¸Ð¿Ñ€ | DX69: Cypern | DY69: KÄ±brÄ±s Cumhuriyeti | DZ69: ÐšÑ–Ð¿Ñ€ | EA69: Ù‚Ø¨Ø±Øµ | EB69: Cá»™ng hÃ²a SÃ­p | EC69: å¡žæµ¦è·¯æ–¯ | ED69: è³½æ™®å‹’æ–¯ | EE69: Admin-0 country | EG69: Admin-0 country
A70: Cyprus U.N. Buffer Zone | B70: Admin-0 country | C70: 1 | D70: 9 | E70: Cyprus No Mans Area | F70: CNM | G70: 0 | H70: 2 | I70: Indeterminate | K70: Cyprus No Mans Area | L70: CNM | M70: 0 | N70: Cyprus No Mans Area | O70: CNM | P70: 0 | Q70: Cyprus No Mans Area | R70: CNM | S70: 1 | T70: Cyprus U.N. Buffer Zone | U70: B43 | V70: Cyprus U.N. Buffer Zone | Z70: Cyprus No Mans Land | AE70: Cyprus No Mans Area | AG70: 4 | AH70: 1 | AI70: 1 | AJ70: -99 | AK70: 10000 | AL70: 6 | AM70: 2019 | AN70: 280 | AO70: 2013 | AP70: 6. Developing region | AQ70: 2. High income: nonOECD | AR70: -99 | AS70: -99 | AT70: -99 | AU70: -99 | AV70: -99 | AW70: -99 | AX70: -99 | AY70: -99 | AZ70: -99 | BA70: -99 | BB70: -99 | BC70: -99 | BD70: No WOE equivalent. | BE70: CYP | BG70: CYP | BH70: CYP | BI70: CYP | BJ70: CYP | BK70: CYP | BL70: CYP | BM70: CYP | BN70: CYP | BO70: CYP | BP70: CYP | BQ70: CYP | BR70: CYP | BS70: CYP | BT70: CYP | BU70: CYP | BV70: CYP | BW70: CYP | BX70: CYP | BY70: CYP | BZ70: CYP | CA70: CYP | CB70: CYP | CC70: CYP | CD70: CYP | CE70: CYP | CF70: CYP | CG70: CYP | CH70: CYP | CI70: CYP | CJ70: CYP | CK70: CYP | CL70: CYP | CM70: -99 | CN70: -99 | CO70: Asia | CP70: Asia | CQ70: Western Asia | CR70: Europe & Central Asia | CS70: 23 | CT70: 23 | CU70: 0 | CV70: -99 | CW70: 1 | CX70: 7 | CY70: 7.7 | CZ70: 11 | DA70: 33.288134 | DB70: 35.140713 | DC70: 1159320511 | DD70: Q116970 | DE70: Ù…Ù‚Ø§Ø·Ø¹Ø© Ø§Ù„Ø£Ù…Ù… Ø§Ù„Ù…ØªØ­Ø¯Ø© Ø§Ù„Ø¹Ø§Ø²Ù„Ø© ÙÙŠ Ù‚Ø¨Ø±Øµ | DF70: à¦¸à¦¾à¦‡à¦ªà§à¦°à¦¾à¦¸ à¦œà¦¾à¦¤à¦¿à¦¸à¦‚à¦˜ à¦¬à¦¾à¦«à¦¾à¦° à¦œà§‹à¦¨ | DG70: UN-Pufferzone in Zypern | DH70: United Nations Buffer Zone in Cyprus | DI70: LÃ­nea Verde | DJ70: Ø®Ø· Ø¢ØªÛŒÙ„Ø§ | DK70: Zone tampon des Nations unies Ã Chypre | DL70: Î ÏÎ¬ÏƒÎ¹Î½Î· Î“ÏÎ±Î¼Î¼Î® | DM70: ×”×§×• ×”×™×¨×•×§ | DN70: à¤¸à¤‚à¤¯à¥à¤•à¥à¤¤ à¤°à¤¾à¤·à¥à¤Ÿà¥à¤° à¤¬à¤«à¤° à¤•à¥à¤·à¥‡à¤¤à¥à¤° | DO70: ZÃ¶ld vonal | DP70: United Nations Buffer Zone di Cyprus | DQ70: Linea Verde | DR70: ã‚°ãƒªãƒ¼ãƒ³ãƒ©ã‚¤ãƒ³ | DS70: ìœ ì—” í‚¤í”„ë¡œìŠ¤ ì™„ì¶© ì§€ëŒ€ | DT70: VN-Bufferzone | DU70: Zielona linia | DV70: Linha Verde | DW70: Ð—ÐµÐ»Ñ‘Ð½Ð°Ñ Ð»Ð¸Ð½Ð¸Ñ | DX70: FN:s buffertzon pÃ¥ Cypern | DY70: YeÅŸil Hat | DZ70: Ð‘ÑƒÑ„ÐµÑ€Ð½Ð° Ð·Ð¾Ð½Ð° ÐžÐžÐ Ð½Ð° ÐšÑ–Ð¿Ñ€Ñ– | EA70: Ù‚Ø¨Ø±ØµØŒ Ø¨ÙØ± Ø²ÙˆÙ† Ø§Ù‚ÙˆØ§Ù… Ù…ØªØ­Ø¯Û | EB70: VÃ¹ng Ä‘á»‡m LiÃªn Hiá»‡p Quá»‘c á»Ÿ Cá»™ng hÃ²a SÃ­p | EC70: å¡žæµ¦è·¯æ–¯è”åˆå›½ç¼“å†²åŒº | ED70: è³½æ™®å‹’æ–¯è¯åˆåœ‹ç·©è¡å€ | EE70: Unrecognized | EG70: Unrecognized | EI70: Unrecognized | EJ70: Unrecognized | EK70: Unrecognized | EL70: Unrecognized | EM70: Unrecognized | EN70: Unrecognized | EO70: Unrecognized | EP70: Unrecognized | EQ70: Unrecognized | ER70: Unrecognized | ES70: Unrecognized | ET70: Unrecognized | EU70: Unrecognized | EV70: Unrecognized | EW70: Unrecognized | EX70: Unrecognized | EY70: Unrecognized | EZ70: Unrecognized | FA70: Unrecognized | FB70: Unrecognized | FC70: Unrecognized | FD70: Unrecognized | FE70: Unrecognized | FF70: Unrecognized | FG70: Unrecognized | FH70: Unrecognized | FI70: Unrecognized | FJ70: Unrecognized | FK70: Unrecognized | FL70: Unrecognized
